Workbook

Sheet 01_Data
A1: SECTION A — DAILY PRICE DATA
A2: DEF: Daily Price Data | O2: SECTION B — DAILY LOG RETURNS | AE2: SECTION C — MACRO INDICATORS | AY2: SECTION D — REGIME FLAGS | BE2: SECTION E — EVENT WINDOWS
A3: Date | B3: XOM | C3: CVX | D3: COP | E3: OXY | F3: LNG | G3: VG | H3: FRO | I3: STNG | J3: ET | K3: BIL | L3: WTI | M3: Brent | O3: Date | P3: r_XOM | Q3: r_CVX | R3: r_COP | S3: r_OXY | T3: r_LNG | U3: r_VG | V3: r_FRO | W3: r_STNG | X3: r_ET | Y3: r_BIL | Z3: r_SPY | AA3: r_WTI | AB3: r_Brent | AE3: Date | AF3: VIX | AG3: OVX | AH3: MOVE | AI3: Brent_WTI_Spread | AJ3: HenryHub | AK3: TTF | AL3: TTF_HH_Spread | AM3: FedFunds | AN3: DGS2 | AO3: DGS10 | AP3: Spread_2s10s | AQ3: T10YIE | AR3: DXY | AS3: Gold | AT3: CPI | AU3: IndProd | AV3: UMich | AY3: Date | AZ3: OVX_Stress | BA3: VIX_Stress | BB3: Conflict_Period | BE3: Date | BF3: Event_Label | BG3: Event_ID
A4: 43467 | B4: 50.0018 | C4: 80.6042 | D4: 49.3966 | E4: 52.7249 | F4: 57.5313 | H4: 3.3249 | I4: 15.9018 | J4: 7.0074 | K4: 75.929 | L4: 46.31 | M4: 54.06 | O4: 43467 | AE4: 43467 | AF4: 23.22 | AG4: 54.72 | AH4: 62.8 | AI4: =IF(AND(M4<>"",L4<>""),M4-L4,"") -> 7.75 | AJ4: 3.25 | AK4: 22.475 | AL4: =IF(AND(AK4<>"",AJ4<>""),AK4-AJ4,"") -> 19.225 | AM4: 2.4 | AN4: 2.5 | AO4: 2.66 | AP4: =IF(AND(AO4<>"",AN4<>""),AO4-AN4,"") -> 0.16 | AQ4: 1.7 | AR4: 115.7689 | AS4: 1281 | AY4: 43467 | AZ4: 0 | BA4: 0 | BB4: 0 | BE4: 43467 | BF4: Pre-COVID | BG4: 1
A5: 43468 | B5: 49.2341 | C5: 79.0605 | D5: 48.4614 | E5: 52.0786 | F5: 57.5982 | H5: 3.3544 | I5: 16.412 | J5: 7.055 | K5: 75.9539 | L5: 46.92 | M5: 53.23 | O5: 43468 | P5: =IF(AND(B5<>"",B4<>""),LN(B5/B4),"") -> -0.015472532 | Q5: =IF(AND(C5<>"",C4<>""),LN(C5/C4),"") -> -0.019337375 | R5: =IF(AND(D5<>"",D4<>""),LN(D5/D4),"") -> -0.019113991 | S5: =IF(AND(E5<>"",E4<>""),LN(E5/E4),"") -> -0.012333714 | T5: =IF(AND(F5<>"",F4<>""),LN(F5/F4),"") -> 0.0011621697 | U5: =IF(AND(G5<>"",G4<>""),LN(G5/G4),"") | V5: =IF(AND(H5<>"",H4<>""),LN(H5/H4),"") -> 0.0088333184 | W5: =IF(AND(I5<>"",I4<>""),LN(I5/I4),"") -> 0.031580464 | ... Y5: =IF(AND(K5<>"",K4<>""),LN(K5/K4),"") -> 0.00032788418 | Z5: -0.024152 | AA5: =IF(AND(L5<>"",L4<>""),LN(L5/L4),"") -> 0.013086103 | AB5: =IF(AND(M5<>"",M4<>""),LN(M5/M4),"") -> -0.015472394 | AE5: 43468 | AF5: 25.45 | AG5: 53.57 | AH5: 65.79 | AI5: =IF(AND(M5<>"",L5<>""),M5-L5,"") -> 6.31 | AJ5: 2.72 | AK5: 22.255 | AL5: =IF(AND(AK5<>"",AJ5<>""),AK5-AJ5,"") -> 19.535 | AM5: 2.4 | AN5: 2.39 | AO5: 2.56 | AP5: =IF(AND(AO5<>"",AN5<>""),AO5-AN5,"") -> 0.17 | AQ5: 1.68 | AR5: 115.4622 | AS5: 1291.8 | AY5: 43468 | AZ5: 0 | BA5: 0 | BB5: 0 | BE5: 43468 | BF5: Pre-COVID | BG5: 1
A6: 43469 | B6: 51.0494 | C6: 80.6989 | D6: 49.685 | E6: 53.7539 | F6: 59.0126 | H6: 3.5077 | I6: 17.0072 | J6: 7.4993 | K6: 75.9622 | L6: 47.76 | M6: 55.64 | O6: 43469 | P6: =IF(AND(B6<>"",B5<>""),LN(B6/B5),"") -> 0.036207319 | Q6: =IF(AND(C6<>"",C5<>""),LN(C6/C5),"") -> 0.020511562 | R6: =IF(AND(D6<>"",D5<>""),LN(D6/D5),"") -> 0.024935472 | S6: =IF(AND(E6<>"",E5<>""),LN(E6/E5),"") -> 0.031662107 | T6: =IF(AND(F6<>"",F5<>""),LN(F6/F5),"") -> 0.024259663 | U6: =IF(AND(G6<>"",G5<>""),LN(G6/G5),"") | V6: =IF(AND(H6<>"",H5<>""),LN(H6/H5),"") -> 0.044687635 | W6: =IF(AND(I6<>"",I5<>""),LN(I6/I5),"") -> 0.035624009 | ... Y6: =IF(AND(K6<>"",K5<>""),LN(K6/K5),"") -> 0.00010927084 | Z6: 0.032947 | AA6: =IF(AND(L6<>"",L5<>""),LN(L6/L5),"") -> 0.017744445 | AB6: =IF(AND(M6<>"",M5<>""),LN(M6/M5),"") -> 0.04428022 | AE6: 43469 | AF6: 21.38 | AG6: 51.52 | AH6: 65.82 | AI6: =IF(AND(M6<>"",L6<>""),M6-L6,"") -> 7.88 | AJ6: 2.8 | AK6: 22.93 | AL6: =IF(AND(AK6<>"",AJ6<>""),AK6-AJ6,"") -> 20.13 | AM6: 2.4 | AN6: 2.5 | AO6: 2.67 | AP6: =IF(AND(AO6<>"",AN6<>""),AO6-AN6,"") -> 0.17 | AQ6: 1.76 | AR6: 114.9821 | AS6: 1282.7 | AY6: 43469 | AZ6: 0 | BA6: 0 | BB6: 0 | BE6: 43469 | BF6: Pre-COVID | BG6: 1
A7: 43472 | B7: 51.3148 | C7: 81.7475 | D7: 49.4667 | E7: 54.8339 | F7: 59.7675 | H7: 3.5489 | I7: 17.3474 | J7: 7.6473 | K7: 75.9622 | L7: 48.27 | M7: 57.1 | O7: 43472 | P7: =IF(AND(B7<>"",B6<>""),LN(B7/B6),"") -> 0.0051854182 | Q7: =IF(AND(C7<>"",C6<>""),LN(C7/C6),"") -> 0.012910284 | R7: =IF(AND(D7<>"",D6<>""),LN(D7/D6),"") -> -0.0044033608 | S7: =IF(AND(E7<>"",E6<>""),LN(E7/E6),"") -> 0.019892393 | T7: =IF(AND(F7<>"",F6<>""),LN(F7/F6),"") -> 0.012711055 | U7: =IF(AND(G7<>"",G6<>""),LN(G7/G6),"") | V7: =IF(AND(H7<>"",H6<>""),LN(H7/H6),"") -> 0.011677144 | W7: =IF(AND(I7<>"",I6<>""),LN(I7/I6),"") -> 0.019805855 | ... Y7: =IF(AND(K7<>"",K6<>""),LN(K7/K6),"") -> 0 | Z7: 0.007854 | AA7: =IF(AND(L7<>"",L6<>""),LN(L7/L6),"") -> 0.010621781 | AB7: =IF(AND(M7<>"",M6<>""),LN(M7/M6),"") -> 0.02590175 | AE7: 43472 | AF7: 21.4 | AG7: 50.42 | AH7: 60.88 | AI7: =IF(AND(M7<>"",L7<>""),M7-L7,"") -> 8.83 | AJ7: 2.74 | AK7: 21.53 | AL7: =IF(AND(AK7<>"",AJ7<>""),AK7-AJ7,"") -> 18.79 | AM7: 2.4 | AN7: 2.53 | AO7: 2.7 | AP7: =IF(AND(AO7<>"",AN7<>""),AO7-AN7,"") -> 0.17 | AQ7: 1.78 | AR7: 114.5628 | AS7: 1286.8 | AY7: 43472 | AZ7: 0 | BA7: 0 | BB7: 0 | BE7: 43472 | BF7: Pre-COVID | BG7: 1
A8: 43473 | B8: 51.688 | C8: 81.3907 | D8: 50.1292 | E8: 55.2676 | F8: 61.5164 | H8: 3.6197 | I8: 17.3474 | J8: 7.8166 | K8: 75.9622 | L8: 49.58 | M8: 56.91 | O8: 43473 | P8: =IF(AND(B8<>"",B7<>""),LN(B8/B7),"") -> 0.0072464367 | Q8: =IF(AND(C8<>"",C7<>""),LN(C8/C7),"") -> -0.0043742124 | R8: =IF(AND(D8<>"",D7<>""),LN(D8/D7),"") -> 0.013303957 | S8: =IF(AND(E8<>"",E7<>""),LN(E8/E7),"") -> 0.0078782259 | T8: =IF(AND(F8<>"",F7<>""),LN(F8/F7),"") -> 0.028841771 | U8: =IF(AND(G8<>"",G7<>""),LN(G8/G7),"") | V8: =IF(AND(H8<>"",H7<>""),LN(H8/H7),"") -> 0.019753453 | W8: =IF(AND(I8<>"",I7<>""),LN(I8/I7),"") -> 0 | ... Y8: =IF(AND(K8<>"",K7<>""),LN(K8/K7),"") -> 0 | Z8: 0.009351 | AA8: =IF(AND(L8<>"",L7<>""),LN(L8/L7),"") -> 0.026777277 | AB8: =IF(AND(M8<>"",M7<>""),LN(M8/M7),"") -> -0.003333044 | AE8: 43473 | AF8: 20.47 | AG8: 46.08 | AH8: 59.05 | AI8: =IF(AND(M8<>"",L8<>""),M8-L8,"") -> 7.33 | AJ8: 2.89 | AK8: 22.09 | AL8: =IF(AND(AK8<>"",AJ8<>""),AK8-AJ8,"") -> 19.2 | AM8: 2.4 | AN8: 2.58 | AO8: 2.73 | AP8: =IF(AND(AO8<>"",AN8<>""),AO8-AN8,"") -> 0.15 | AQ8: 1.82 | AR8: 114.7281 | AS8: 1283.2 | AY8: 43473 | AZ8: 0 | BA8: 0 | BB8: 0 | BE8: 43473 | BF8: Pre-COVID | BG8: 1
A9: 43474 | B9: 51.9606 | C9: 82.483 | D9: 51.7893 | E9: 55.9394 | F9: 62.1854 | H9: 3.6786 | I9: 17.1773 | J9: 7.9911 | K9: 75.9622 | L9: 52.19 | M9: 59.46 | O9: 43474 | P9: =IF(AND(B9<>"",B8<>""),LN(B9/B8),"") -> 0.0052600928 | Q9: =IF(AND(C9<>"",C8<>""),LN(C9/C8),"") -> 0.013331196 | R9: =IF(AND(D9<>"",D8<>""),LN(D9/D8),"") -> 0.032579892 | S9: =IF(AND(E9<>"",E8<>""),LN(E9/E8),"") -> 0.01208212 | T9: =IF(AND(F9<>"",F8<>""),LN(F9/F8),"") -> 0.01081644 | U9: =IF(AND(G9<>"",G8<>""),LN(G9/G8),"") | V9: =IF(AND(H9<>"",H8<>""),LN(H9/H8),"") -> 0.016141096 | W9: =IF(AND(I9<>"",I8<>""),LN(I9/I8),"") -> -0.0098538945 | ... Y9: =IF(AND(K9<>"",K8<>""),LN(K9/K8),"") -> 0 | Z9: 0.004663 | AA9: =IF(AND(L9<>"",L8<>""),LN(L9/L8),"") -> 0.051303379 | AB9: =IF(AND(M9<>"",M8<>""),LN(M9/M8),"") -> 0.043832745 | AE9: 43474 | AF9: 19.98 | AG9: 44.36 | AH9: 57.02 | AI9: =IF(AND(M9<>"",L9<>""),M9-L9,"") -> 7.27 | AJ9: 2.92 | AK9: 21.72 | AL9: =IF(AND(AK9<>"",AJ9<>""),AK9-AJ9,"") -> 18.8 | AM9: 2.4 | AN9: 2.56 | AO9: 2.74 | AP9: =IF(AND(AO9<>"",AN9<>""),AO9-AN9,"") -> 0.18 | AQ9: 1.83 | AR9: 114.1406 | AS9: 1289.3 | AY9: 43474 | AZ9: 0 | BA9: 0 | BB9: 0 | BE9: 43474 | BF9: Pre-COVID | BG9: 1
A10: 43475 | B10: 51.6951 | C10: 82.6141 | D10: 52.9505 | E10: 56.2881 | F10: 62.797 | H10: 3.4251 | I10: 17.0923 | J10: 7.9858 | K10: 75.9705 | L10: 52.42 | M10: 60.47 | O10: 43475 | P10: =IF(AND(B10<>"",B9<>""),LN(B10/B9),"") -> -0.0051227396 | Q10: =IF(AND(C10<>"",C9<>""),LN(C10/C9),"") -> 0.0015881566 | R10: =IF(AND(D10<>"",D9<>""),LN(D10/D9),"") -> 0.022173951 | S10: =IF(AND(E10<>"",E9<>""),LN(E10/E9),"") -> 0.0062141832 | T10: =IF(AND(F10<>"",F9<>""),LN(F10/F9),"") -> 0.0097870561 | U10: =IF(AND(G10<>"",G9<>""),LN(G10/G9),"") | V10: =IF(AND(H10<>"",H9<>""),LN(H10/H9),"") -> -0.071401577 | W10: =IF(AND(I10<>"",I9<>""),LN(I10/I9),"") -> -0.004960675 | ... Y10: =IF(AND(K10<>"",K9<>""),LN(K10/K9),"") -> 0.0001092589 | Z10: 0.003521 | AA10: =IF(AND(L10<>"",L9<>""),LN(L10/L9),"") -> 0.0043972922 | AB10: =IF(AND(M10<>"",M9<>""),LN(M10/M9),"") -> 0.016843557 | AE10: 43475 | AF10: 19.5 | AG10: 42.99 | AH10: 56.65 | AI10: =IF(AND(M10<>"",L10<>""),M10-L10,"") -> 8.05 | AJ10: 2.95 | AK10: 21.675 | AL10: =IF(AND(AK10<>"",AJ10<>""),AK10-AJ10,"") -> 18.725 | AM10: 2.4 | AN10: 2.56 | AO10: 2.74 | AP10: =IF(AND(AO10<>"",AN10<>""),AO10-AN10,"") -> 0.18 | AQ10: 1.81 | AR10: 114.0496 | AS10: 1284.7 | AY10: 43475 | AZ10: 0 | BA10: 0 | BB10: 0 | BE10: 43475 | BF10: Pre-COVID | BG10: 1
A11: 43476 | B11: 51.4584 | C11: 81.9514 | D11: 51.7425 | E11: 56.3136 | F11: 61.6406 | H11: 3.3072 | I11: 16.8372 | J11: 7.9541 | K11: 75.9871 | L11: 51.44 | M11: 59.24 | O11: 43476 | P11: =IF(AND(B11<>"",B10<>""),LN(B11/B10),"") -> -0.0045892852 | Q11: =IF(AND(C11<>"",C10<>""),LN(C11/C10),"") -> -0.0080539795 | R11: =IF(AND(D11<>"",D10<>""),LN(D11/D10),"") -> -0.023078021 | S11: =IF(AND(E11<>"",E10<>""),LN(E11/E10),"") -> 0.0004529239 | T11: =IF(AND(F11<>"",F10<>""),LN(F11/F10),"") -> -0.018586557 | U11: =IF(AND(G11<>"",G10<>""),LN(G11/G10),"") | V11: =IF(AND(H11<>"",H10<>""),LN(H11/H10),"") -> -0.035028758 | W11: =IF(AND(I11<>"",I10<>""),LN(I11/I10),"") -> -0.015037345 | ... Y11: =IF(AND(K11<>"",K10<>""),LN(K11/K10),"") -> 0.000218482 | Z11: 0.000386 | AA11: =IF(AND(L11<>"",L10<>""),LN(L11/L10),"") -> -0.018872118 | AB11: =IF(AND(M11<>"",M10<>""),LN(M11/M10),"") -> -0.020550385 | AE11: 43476 | AF11: 18.19 | AG11: 40.99 | AH11: 55.94 | AI11: =IF(AND(M11<>"",L11<>""),M11-L11,"") -> 7.8 | AJ11: 2.95 | AK11: 22.255 | AL11: =IF(AND(AK11<>"",AJ11<>""),AK11-AJ11,"") -> 19.305 | AM11: 2.4 | AN11: 2.55 | AO11: 2.71 | AP11: =IF(AND(AO11<>"",AN11<>""),AO11-AN11,"") -> 0.16 | AQ11: 1.83 | AR11: 114.0404 | AS11: 1287.1 | AY11: 43476 | AZ11: 0 | BA11: 0 | BB11: 0 | BE11: 43476 | BF11: Pre-COVID | BG11: 1
A12: 43479 | B12: 51.3938 | C12: 81.3543 | D12: 51.1346 | E12: 55.7693 | F12: 61.6406 | H12: 3.2306 | I12: 16.497 | J12: 7.7796 | K12: 75.9788 | L12: 50.31 | M12: 58.8 | O12: 43479 | P12: =IF(AND(B12<>"",B11<>""),LN(B12/B11),"") -> -0.0012561716 | Q12: =IF(AND(C12<>"",C11<>""),LN(C12/C11),"") -> -0.0073126983 | R12: =IF(AND(D12<>"",D11<>""),LN(D12/D11),"") -> -0.011818122 | S12: =IF(AND(E12<>"",E11<>""),LN(E12/E11),"") -> -0.0097125303 | T12: =IF(AND(F12<>"",F11<>""),LN(F12/F11),"") -> 0 | U12: =IF(AND(G12<>"",G11<>""),LN(G12/G11),"") | V12: =IF(AND(H12<>"",H11<>""),LN(H12/H11),"") -> -0.023434031 | W12: =IF(AND(I12<>"",I11<>""),LN(I12/I11),"") -> -0.020412178 | ... Y12: =IF(AND(K12<>"",K11<>""),LN(K12/K11),"") -> -0.00010923503 | Z12: -0.00612 | AA12: =IF(AND(L12<>"",L11<>""),LN(L12/L11),"") -> -0.022212215 | AB12: =IF(AND(M12<>"",M11<>""),LN(M12/M11),"") -> -0.0074551345 | AE12: 43479 | AF12: 19.07 | AG12: 40.81 | AH12: 55.34 | AI12: =IF(AND(M12<>"",L12<>""),M12-L12,"") -> 8.49 | AJ12: 3.36 | AK12: 21.675 | AL12: =IF(AND(AK12<>"",AJ12<>""),AK12-AJ12,"") -> 18.315 | AM12: 2.4 | AN12: 2.53 | AO12: 2.71 | AP12: =IF(AND(AO12<>"",AN12<>""),AO12-AN12,"") -> 0.18 | AQ12: 1.81 | AS12: 1289.1 | AY12: 43479 | AZ12: 0 | BA12: 0 | BB12: 0 | BE12: 43479 | BF12: Pre-COVID | BG12: 1
A13: 43480 | B13: 51.4225 | C13: 81.6456 | D13: 51.4619 | E13: 55.7183 | F13: 62.0133 | H13: 3.3367 | I13: 16.9222 | J13: 7.8642 | K13: 75.9954 | L13: 51.8 | M13: 58.65 | O13: 43480 | P13: =IF(AND(B13<>"",B12<>""),LN(B13/B12),"") -> 0.00055827725 | Q13: =IF(AND(C13<>"",C12<>""),LN(C13/C12),"") -> 0.0035742391 | R13: =IF(AND(D13<>"",D12<>""),LN(D13/D12),"") -> 0.0063803563 | S13: =IF(AND(E13<>"",E12<>""),LN(E13/E12),"") -> -0.00091490002 | T13: =IF(AND(F13<>"",F12<>""),LN(F13/F12),"") -> 0.0060281338 | U13: =IF(AND(G13<>"",G12<>""),LN(G13/G12),"") | V13: =IF(AND(H13<>"",H12<>""),LN(H13/H12),"") -> 0.032314416 | W13: =IF(AND(I13<>"",I12<>""),LN(I13/I12),"") -> 0.025447823 | ... Y13: =IF(AND(K13<>"",K12<>""),LN(K13/K12),"") -> 0.00021845813 | Z13: 0.011396 | AA13: =IF(AND(L13<>"",L12<>""),LN(L13/L12),"") -> 0.029186285 | AB13: =IF(AND(M13<>"",M12<>""),LN(M13/M12),"") -> -0.0025542798 | AE13: 43480 | AF13: 18.6 | AG13: 39.75 | AH13: 53.01 | AI13: =IF(AND(M13<>"",L13<>""),M13-L13,"") -> 6.85 | AJ13: 3.54 | AK13: 22 | AL13: =IF(AND(AK13<>"",AJ13<>""),AK13-AJ13,"") -> 18.46 | AM13: 2.4 | AN13: 2.53 | AO13: 2.72 | AP13: =IF(AND(AO13<>"",AN13<>""),AO13-AN13,"") -> 0.19 | AQ13: 1.81 | AR13: 114.3402 | AS13: 1286.2 | AY13: 43480 | AZ13: 0 | BA13: 0 | BB13: 0 | BE13: 43480 | BF13: Pre-COVID | BG13: 1
A14: 43481 | B14: 51.4009 | C14: 81.1213 | D14: 51.1736 | E14: 55.3951 | F14: 60.9143 | H14: 3.2836 | I14: 16.327 | J14: 7.7478 | K14: 76.0037 | L14: 52.08 | M14: 59.81 | O14: 43481 | P14: =IF(AND(B14<>"",B13<>""),LN(B14/B13),"") -> -0.00042013783 | Q14: =IF(AND(C14<>"",C13<>""),LN(C14/C13),"") -> -0.0064423641 | R14: =IF(AND(D14<>"",D13<>""),LN(D14/D13),"") -> -0.005617954 | S14: =IF(AND(E14<>"",E13<>""),LN(E14/E13),"") -> -0.0058174966 | T14: =IF(AND(F14<>"",F13<>""),LN(F14/F13),"") -> -0.01788092 | U14: =IF(AND(G14<>"",G13<>""),LN(G14/G13),"") | V14: =IF(AND(H14<>"",H13<>""),LN(H14/H13),"") -> -0.016041913 | W14: =IF(AND(I14<>"",I13<>""),LN(I14/I13),"") -> -0.03580619 | ... Y14: =IF(AND(K14<>"",K13<>""),LN(K14/K13),"") -> 0.00010921117 | Z14: 0.002417 | AA14: =IF(AND(L14<>"",L13<>""),LN(L14/L13),"") -> 0.0053908486 | AB14: =IF(AND(M14<>"",M13<>""),LN(M14/M13),"") -> 0.019585296 | AE14: 43481 | AF14: 19.04 | AG14: 38.77 | AH14: 51.95 | AI14: =IF(AND(M14<>"",L14<>""),M14-L14,"") -> 7.73 | AJ14: 3.58 | AK14: 22.005 | AL14: =IF(AND(AK14<>"",AJ14<>""),AK14-AJ14,"") -> 18.425 | AM14: 2.4 | AN14: 2.55 | AO14: 2.73 | AP14: =IF(AND(AO14<>"",AN14<>""),AO14-AN14,"") -> 0.18 | AQ14: 1.82 | AR14: 114.137 | AS14: 1291.6 | AY14: 43481 | AZ14: 0 | BA14: 0 | BB14: 0 | BE14: 43481 | BF14: Pre-COVID | BG14: 1
A15: 43482 | B15: 51.7525 | C15: 81.5291 | D15: 52.2647 | E15: 55.9819 | F15: 61.1819 | H15: 3.3072 | I15: 16.8372 | J15: 7.7267 | K15: 76.0203 | L15: 51.83 | M15: 59.85 | O15: 43482 | P15: =IF(AND(B15<>"",B14<>""),LN(B15/B14),"") -> 0.0068170581 | Q15: =IF(AND(C15<>"",C14<>""),LN(C15/C14),"") -> 0.0050144464 | R15: =IF(AND(D15<>"",D14<>""),LN(D15/D14),"") -> 0.021097417 | S15: =IF(AND(E15<>"",E14<>""),LN(E15/E14),"") -> 0.010537282 | T15: =IF(AND(F15<>"",F14<>""),LN(F15/F14),"") -> 0.0043834358 | U15: =IF(AND(G15<>"",G14<>""),LN(G15/G14),"") | V15: =IF(AND(H15<>"",H14<>""),LN(H15/H14),"") -> 0.0071615285 | W15: =IF(AND(I15<>"",I14<>""),LN(I15/I14),"") -> 0.030770545 | ... Y15: =IF(AND(K15<>"",K14<>""),LN(K15/K14),"") -> 0.00021838657 | Z15: 0.007558 | AA15: =IF(AND(L15<>"",L14<>""),LN(L15/L14),"") -> -0.0048118657 | AB15: =IF(AND(M15<>"",M14<>""),LN(M15/M14),"") -> 0.00066856095 | AE15: 43482 | AF15: 18.06 | AG15: 37.03 | AH15: 53.44 | AI15: =IF(AND(M15<>"",L15<>""),M15-L15,"") -> 8.02 | AJ15: 3.58 | AK15: 22.995 | AL15: =IF(AND(AK15<>"",AJ15<>""),AK15-AJ15,"") -> 19.415 | AM15: 2.4 | AN15: 2.56 | AO15: 2.75 | AP15: =IF(AND(AO15<>"",AN15<>""),AO15-AN15,"") -> 0.19 | AQ15: 1.79 | AR15: 114.4115 | AS15: 1291 | AY15: 43482 | AZ15: 0 | BA15: 0 | BB15: 0 | BE15: 43482 | BF15: Pre-COVID | BG15: 1
A16: 43483 | B16: 52.3696 | C16: 83.284 | D16: 52.9194 | E16: 57.0024 | F16: 61.9273 | H16: 3.4192 | I16: 17.9001 | J16: 7.7055 | K16: 76.0203 | L16: 53.6 | M16: 62.04 | O16: 43483 | P16: =IF(AND(B16<>"",B15<>""),LN(B16/B15),"") -> 0.01185353 | Q16: =IF(AND(C16<>"",C15<>""),LN(C16/C15),"") -> 0.021296442 | R16: =IF(AND(D16<>"",D15<>""),LN(D16/D15),"") -> 0.01244881 | S16: =IF(AND(E16<>"",E15<>""),LN(E16/E15),"") -> 0.018064948 | T16: =IF(AND(F16<>"",F15<>""),LN(F16/F15),"") -> 0.012109722 | U16: =IF(AND(G16<>"",G15<>""),LN(G16/G15),"") | V16: =IF(AND(H16<>"",H15<>""),LN(H16/H15),"") -> 0.033304696 | W16: =IF(AND(I16<>"",I15<>""),LN(I16/I15),"") -> 0.061215575 | ... Y16: =IF(AND(K16<>"",K15<>""),LN(K16/K15),"") -> 0 | Z16: 0.013222 | AA16: =IF(AND(L16<>"",L15<>""),LN(L16/L15),"") -> 0.033579936 | AB16: =IF(AND(M16<>"",M15<>""),LN(M16/M15),"") -> 0.035937906 | AE16: 43483 | AF16: 17.8 | AG16: 35.63 | AH16: 53.78 | AI16: =IF(AND(M16<>"",L16<>""),M16-L16,"") -> 8.44 | AJ16: 3.43 | AK16: 22.605 | AL16: =IF(AND(AK16<>"",AJ16<>""),AK16-AJ16,"") -> 19.175 | AM16: 2.4 | AN16: 2.62 | AO16: 2.79 | AP16: =IF(AND(AO16<>"",AN16<>""),AO16-AN16,"") -> 0.17 | AQ16: 1.83 | AR16: 114.558 | AS16: 1281.3 | AY16: 43483 | AZ16: 0 | BA16: 0 | BB16: 0 | BE16: 43483 | BF16: Pre-COVID | BG16: 1
A17: 43487 | B17: 51.5803 | C17: 81.8058 | D17: 51.2437 | E17: 55.3781 | F17: 60.2263 | H17: 3.3249 | I17: 17.0328 | J17: 7.457 | K17: 76.0286 | L17: 52.59 | M17: 60.9 | O17: 43487 | P17: =IF(AND(B17<>"",B16<>""),LN(B17/B16),"") -> -0.015186454 | Q17: =IF(AND(C17<>"",C16<>""),LN(C17/C16),"") -> -0.017908308 | R17: =IF(AND(D17<>"",D16<>""),LN(D17/D16),"") -> -0.032177318 | S17: =IF(AND(E17<>"",E16<>""),LN(E17/E16),"") -> -0.028909163 | T17: =IF(AND(F17<>"",F16<>""),LN(F17/F16),"") -> -0.027851982 | U17: =IF(AND(G17<>"",G16<>""),LN(G17/G16),"") | V17: =IF(AND(H17<>"",H16<>""),LN(H17/H16),"") -> -0.027967007 | W17: =IF(AND(I17<>"",I16<>""),LN(I17/I16),"") -> -0.049665403 | ... Y17: =IF(AND(K17<>"",K16<>""),LN(K17/K16),"") -> 0.0001091754 | Z17: -0.013602 | AA17: =IF(AND(L17<>"",L16<>""),LN(L17/L16),"") -> -0.01902308 | AB17: =IF(AND(M17<>"",M16<>""),LN(M17/M16),"") -> -0.018546164 | AE17: 43487 | AF17: 20.8 | AG17: 38.26 | AH17: 54.64 | AI17: =IF(AND(M17<>"",L17<>""),M17-L17,"") -> 8.31 | AJ17: 3.43 | AK17: 21.815 | AL17: =IF(AND(AK17<>"",AJ17<>""),AK17-AJ17,"") -> 18.385 | AM17: 2.4 | AN17: 2.58 | AO17: 2.74 | AP17: =IF(AND(AO17<>"",AN17<>""),AO17-AN17,"") -> 0.16 | AQ17: 1.79 | AR17: 114.7541 | AS17: 1282.5 | AY17: 43487 | AZ17: 0 | BA17: 0 | BB17: 0 | BE17: 43487 | BF17: Pre-COVID | BG17: 1
A18: 43488 | B18: 51.157 | C18: 81.114 | D18: 51.3294 | E18: 54.9104 | F18: 59.9491 | H18: 3.3308 | I18: 16.9052 | J18: 7.4252 | K18: 76.0286 | L18: 52.44 | M18: 61.05 | O18: 43488 | P18: =IF(AND(B18<>"",B17<>""),LN(B18/B17),"") -> -0.0082404812 | Q18: =IF(AND(C18<>"",C17<>""),LN(C18/C17),"") -> -0.0084925731 | R18: =IF(AND(D18<>"",D17<>""),LN(D18/D17),"") -> 0.0016710038 | S18: =IF(AND(E18<>"",E17<>""),LN(E18/E17),"") -> -0.0084814428 | T18: =IF(AND(F18<>"",F17<>""),LN(F18/F17),"") -> -0.0046132651 | U18: =IF(AND(G18<>"",G17<>""),LN(G18/G17),"") | V18: =IF(AND(H18<>"",H17<>""),LN(H18/H17),"") -> 0.0017729169 | W18: =IF(AND(I18<>"",I17<>""),LN(I18/I17),"") -> -0.00751963 | ... Y18: =IF(AND(K18<>"",K17<>""),LN(K18/K17),"") -> 0 | Z18: 0.00209 | AA18: =IF(AND(L18<>"",L17<>""),LN(L18/L17),"") -> -0.0028563287 | AB18: =IF(AND(M18<>"",M17<>""),LN(M18/M17),"") -> 0.0024600258 | AE18: 43488 | AF18: 19.52 | AG18: 37.69 | AH18: 54.19 | AI18: =IF(AND(M18<>"",L18<>""),M18-L18,"") -> 8.61 | AJ18: 3.13 | AK18: 22.19 | AL18: =IF(AND(AK18<>"",AJ18<>""),AK18-AJ18,"") -> 19.06 | AM18: 2.4 | AN18: 2.58 | AO18: 2.76 | AP18: =IF(AND(AO18<>"",AN18<>""),AO18-AN18,"") -> 0.18 | AQ18: 1.8 | AR18: 114.5759 | AS18: 1283.1 | AY18: 43488 | AZ18: 0 | BA18: 0 | BB18: 0 | BE18: 43488 | BF18: Pre-COVID | BG18: 1
A19: 43489 | B19: 51.2287 | C19: 82.6578 | D19: 51.5321 | E19: 55.2591 | F19: 60.4174 | H19: 3.2954 | I19: 17.1773 | J19: 7.4675 | K19: 76.0535 | L19: 52.94 | M19: 61.09 | O19: 43489 | P19: =IF(AND(B19<>"",B18<>""),LN(B19/B18),"") -> 0.0014005864 | Q19: =IF(AND(C19<>"",C18<>""),LN(C19/C18),"") -> 0.018853621 | R19: =IF(AND(D19<>"",D18<>""),LN(D19/D18),"") -> 0.003941227 | S19: =IF(AND(E19<>"",E18<>""),LN(E19/E18),"") -> 0.0063302668 | T19: =IF(AND(F19<>"",F18<>""),LN(F19/F18),"") -> 0.0077812741 | U19: =IF(AND(G19<>"",G18<>""),LN(G19/G18),"") | V19: =IF(AND(H19<>"",H18<>""),LN(H19/H18),"") -> -0.010684959 | W19: =IF(AND(I19<>"",I18<>""),LN(I19/I18),"") -> 0.015967478 | ... Y19: =IF(AND(K19<>"",K18<>""),LN(K19/K18),"") -> 0.00032745471 | Z19: 0.000531 | AA19: =IF(AND(L19<>"",L18<>""),LN(L19/L18),"") -> 0.0094895379 | AB19: =IF(AND(M19<>"",M18<>""),LN(M19/M18),"") -> 0.0006549861 | AE19: 43489 | AF19: 18.89 | AG19: 36.75 | AH19: 54.18 | AI19: =IF(AND(M19<>"",L19<>""),M19-L19,"") -> 8.15 | AJ19: 3.13 | AK19: 21.28 | AL19: =IF(AND(AK19<>"",AJ19<>""),AK19-AJ19,"") -> 18.15 | AM19: 2.4 | AN19: 2.56 | AO19: 2.72 | AP19: =IF(AND(AO19<>"",AN19<>""),AO19-AN19,"") -> 0.16 | AQ19: 1.77 | AR19: 114.617 | AS19: 1279.1 | AY19: 43489 | AZ19: 0 | BA19: 0 | BB19: 0 | BE19: 43489 | BF19: Pre-COVID | BG19: 1
A20: 43490 | B20: 51.4584 | C20: 82.4466 | D20: 52.2101 | E20: 56.5772 | F20: 60.7328 | H20: 3.2188 | I20: 17.3729 | J20: 7.5839 | K20: 76.0452 | L20: 53.53 | M20: 61.49 | O20: 43490 | P20: =IF(AND(B20<>"",B19<>""),LN(B20/B19),"") -> 0.0044737924 | Q20: =IF(AND(C20<>"",C19<>""),LN(C20/C19),"") -> -0.0025583826 | R20: =IF(AND(D20<>"",D19<>""),LN(D20/D19),"") -> 0.013071048 | S20: =IF(AND(E20<>"",E19<>""),LN(E20/E19),"") -> 0.023573044 | T20: =IF(AND(F20<>"",F19<>""),LN(F20/F19),"") -> 0.0052067716 | U20: =IF(AND(G20<>"",G19<>""),LN(G20/G19),"") | V20: =IF(AND(H20<>"",H19<>""),LN(H20/H19),"") -> -0.023518937 | W20: =IF(AND(I20<>"",I19<>""),LN(I20/I19),"") -> 0.011322776 | ... Y20: =IF(AND(K20<>"",K19<>""),LN(K20/K19),"") -> -0.00010913966 | Z20: 0.008426 | AA20: =IF(AND(L20<>"",L19<>""),LN(L20/L19),"") -> 0.011083048 | AB20: =IF(AND(M20<>"",M19<>""),LN(M20/M19),"") -> 0.0065263733 | AE20: 43490 | AF20: 17.42 | AG20: 35.21 | AH20: 52.5 | AI20: =IF(AND(M20<>"",L20<>""),M20-L20,"") -> 7.96 | AJ20: 3.07 | AK20: 20.89 | AL20: =IF(AND(AK20<>"",AJ20<>""),AK20-AJ20,"") -> 17.82 | AM20: 2.4 | AN20: 2.6 | AO20: 2.76 | AP20: =IF(AND(AO20<>"",AN20<>""),AO20-AN20,"") -> 0.16 | AQ20: 1.79 | AR20: 114.0197 | AS20: 1297.4 | AY20: 43490 | AZ20: 0 | BA20: 0 | BB20: 0 | BE20: 43490 | BF20: Pre-COVID | BG20: 1
A21: 43493 | B21: 51.1139 | C21: 81.682 | D21: 50.932 | E21: 56.1945 | F21: 62.3669 | H21: 3.0714 | I21: 17.2709 | J21: 7.5098 | K21: 76.0535 | L21: 51.79 | M21: 59.71 | O21: 43493 | P21: =IF(AND(B21<>"",B20<>""),LN(B21/B20),"") -> -0.0067172384 | Q21: =IF(AND(C21<>"",C20<>""),LN(C21/C20),"") -> -0.0093171517 | R21: =IF(AND(D21<>"",D20<>""),LN(D21/D20),"") -> -0.024784553 | S21: =IF(AND(E21<>"",E20<>""),LN(E21/E20),"") -> -0.0067871899 | T21: =IF(AND(F21<>"",F20<>""),LN(F21/F20),"") -> 0.026550771 | U21: =IF(AND(G21<>"",G20<>""),LN(G21/G20),"") | V21: =IF(AND(H21<>"",H20<>""),LN(H21/H20),"") -> -0.046875136 | W21: =IF(AND(I21<>"",I20<>""),LN(I21/I20),"") -> -0.0058885165 | ... Y21: =IF(AND(K21<>"",K20<>""),LN(K21/K20),"") -> 0.00010913966 | Z21: -0.007629 | AA21: =IF(AND(L21<>"",L20<>""),LN(L21/L20),"") -> -0.033045164 | AB21: =IF(AND(M21<>"",M20<>""),LN(M21/M20),"") -> -0.029375049 | AE21: 43493 | AF21: 18.87 | AG21: 37.61 | AH21: 50.95 | AI21: =IF(AND(M21<>"",L21<>""),M21-L21,"") -> 7.92 | AJ21: 3.05 | AK21: 20.55 | AL21: =IF(AND(AK21<>"",AJ21<>""),AK21-AJ21,"") -> 17.5 | AM21: 2.4 | AN21: 2.6 | AO21: 2.75 | AP21: =IF(AND(AO21<>"",AN21<>""),AO21-AN21,"") -> 0.15 | AQ21: 1.78 | AR21: 114.0522 | AS21: 1302.4 | AY21: 43493 | AZ21: 0 | BA21: 0 | BB21: 0 | BE21: 43493 | BF21: Pre-COVID | BG21: 1
A22: 43494 | B22: 51.3077 | C22: 81.4344 | D22: 50.893 | E22: 56.5347 | F22: 62.5008 | H22: 3.0714 | I22: 17.0668 | J22: 7.5522 | K22: 76.0535 | L22: 53.07 | M22: 60.98 | O22: 43494 | P22: =IF(AND(B22<>"",B21<>""),LN(B22/B21),"") -> 0.0037843625 | Q22: =IF(AND(C22<>"",C21<>""),LN(C22/C21),"") -> -0.0030358712 | R22: =IF(AND(D22<>"",D21<>""),LN(D22/D21),"") -> -0.00076602017 | S22: =IF(AND(E22<>"",E21<>""),LN(E22/E21),"") -> 0.0060357216 | T22: =IF(AND(F22<>"",F21<>""),LN(F22/F21),"") -> 0.0021446707 | U22: =IF(AND(G22<>"",G21<>""),LN(G22/G21),"") | V22: =IF(AND(H22<>"",H21<>""),LN(H22/H21),"") -> 0 | W22: =IF(AND(I22<>"",I21<>""),LN(I22/I21),"") -> -0.011887948 | ... Y22: =IF(AND(K22<>"",K21<>""),LN(K22/K21),"") -> 0 | Z22: -0.001328 | AA22: =IF(AND(L22<>"",L21<>""),LN(L22/L21),"") -> 0.024414716 | AB22: =IF(AND(M22<>"",M21<>""),LN(M22/M21),"") -> 0.021046431 | AE22: 43494 | AF22: 19.13 | AG22: 37.13 | AH22: 49.8 | AI22: =IF(AND(M22<>"",L22<>""),M22-L22,"") -> 7.91 | AJ22: 2.94 | AK22: 20.585 | AL22: =IF(AND(AK22<>"",AJ22<>""),AK22-AJ22,"") -> 17.645 | AM22: 2.4 | AN22: 2.56 | AO22: 2.72 | AP22: =IF(AND(AO22<>"",AN22<>""),AO22-AN22,"") -> 0.16 | AQ22: 1.78 | AR22: 114.026 | AS22: 1308.2 | AY22: 43494 | AZ22: 0 | BA22: 0 | BB22: 0 | BE22: 43494 | BF22: Pre-COVID | BG22: 1
A23: 43495 | B23: 51.8673 | C23: 82.2937 | D23: 51.197 | E23: 56.9514 | F23: 63.2175 | H23: 3.148 | I23: 16.7606 | J23: 7.7584 | K23: 76.0701 | L23: 54.18 | M23: 61.89 | O23: 43495 | P23: =IF(AND(B23<>"",B22<>""),LN(B23/B22),"") -> 0.010847695 | Q23: =IF(AND(C23<>"",C22<>""),LN(C23/C22),"") -> 0.010496767 | R23: =IF(AND(D23<>"",D22<>""),LN(D23/D22),"") -> 0.005955547 | S23: =IF(AND(E23<>"",E22<>""),LN(E23/E22),"") -> 0.0073436636 | T23: =IF(AND(F23<>"",F22<>""),LN(F23/F22),"") -> 0.011401805 | U23: =IF(AND(G23<>"",G22<>""),LN(G23/G22),"") | V23: =IF(AND(H23<>"",H22<>""),LN(H23/H22),"") -> 0.024633847 | W23: =IF(AND(I23<>"",I22<>""),LN(I23/I22),"") -> -0.018104162 | ... Y23: =IF(AND(K23<>"",K22<>""),LN(K23/K22),"") -> 0.00021824359 | Z23: 0.015707 | AA23: =IF(AND(L23<>"",L22<>""),LN(L23/L22),"") -> 0.02070004 | AB23: =IF(AND(M23<>"",M22<>""),LN(M23/M22),"") -> 0.014812674 | AE23: 43495 | AF23: 17.66 | AG23: 35.59 | AH23: 48.32 | AI23: =IF(AND(M23<>"",L23<>""),M23-L23,"") -> 7.71 | AJ23: 3 | AK23: 20.18 | AL23: =IF(AND(AK23<>"",AJ23<>""),AK23-AJ23,"") -> 17.18 | AM23: 2.4 | AN23: 2.52 | AO23: 2.7 | AP23: =IF(AND(AO23<>"",AN23<>""),AO23-AN23,"") -> 0.18 | AQ23: 1.84 | AR23: 114.0731 | AS23: 1309.9 | AY23: 43495 | AZ23: 0 | BA23: 0 | BB23: 0 | BE23: 43495 | BF23: Pre-COVID | BG23: 1
A24: 43496 | B24: 52.5776 | C24: 83.4879 | D24: 52.7557 | E24: 56.7898 | F24: 62.7397 | H24: 3.036 | I24: 15.9273 | J24: 7.7796 | K24: 76.0701 | L24: 53.84 | M24: 62.46 | O24: 43496 | P24: =IF(AND(B24<>"",B23<>""),LN(B24/B23),"") -> 0.01360164 | Q24: =IF(AND(C24<>"",C23<>""),LN(C24/C23),"") -> 0.014407156 | R24: =IF(AND(D24<>"",D23<>""),LN(D24/D23),"") -> 0.029990887 | S24: =IF(AND(E24<>"",E23<>""),LN(E24/E23),"") -> -0.0028415404 | T24: =IF(AND(F24<>"",F23<>""),LN(F24/F23),"") -> -0.0075867404 | U24: =IF(AND(G24<>"",G23<>""),LN(G24/G23),"") | V24: =IF(AND(H24<>"",H23<>""),LN(H24/H23),"") -> -0.036226471 | W24: =IF(AND(I24<>"",I23<>""),LN(I24/I23),"") -> -0.050996276 | ... Y24: =IF(AND(K24<>"",K23<>""),LN(K24/K23),"") -> 0 | Z24: 0.008744 | AA24: =IF(AND(L24<>"",L23<>""),LN(L24/L23),"") -> -0.0062951513 | AB24: =IF(AND(M24<>"",M23<>""),LN(M24/M23),"") -> 0.0091677361 | AE24: 43496 | AF24: 16.57 | AG24: 34.97 | AH24: 49.81 | AI24: =IF(AND(M24<>"",L24<>""),M24-L24,"") -> 8.62 | AJ24: 2.82 | AK24: 19.85 | AL24: =IF(AND(AK24<>"",AJ24<>""),AK24-AJ24,"") -> 17.03 | AM24: 2.4 | AN24: 2.45 | AO24: 2.63 | AP24: =IF(AND(AO24<>"",AN24<>""),AO24-AN24,"") -> 0.18 | AQ24: 1.85 | AR24: 113.5504 | AS24: 1319.7 | AY24: 43496 | AZ24: 0 | BA24: 0 | BB24: 0 | BE24: 43496 | BF24: Pre-COVID | BG24: 1
A25: 43497 | B25: 54.4718 | C25: 86.1968 | D25: 53.5273 | E25: 57.8613 | F25: 64.0012 | H25: 2.9889 | I25: 15.7147 | J25: 7.9541 | K25: 76.0776 | L25: 55.29 | M25: 61.86 | O25: 43497 | P25: =IF(AND(B25<>"",B24<>""),LN(B25/B24),"") -> 0.035392963 | Q25: =IF(AND(C25<>"",C24<>""),LN(C25/C24),"") -> 0.031931343 | R25: =IF(AND(D25<>"",D24<>""),LN(D25/D24),"") -> 0.014519981 | S25: =IF(AND(E25<>"",E24<>""),LN(E25/E24),"") -> 0.018692035 | T25: =IF(AND(F25<>"",F24<>""),LN(F25/F24),"") -> 0.019907412 | U25: =IF(AND(G25<>"",G24<>""),LN(G25/G24),"") | V25: =IF(AND(H25<>"",H24<>""),LN(H25/H24),"") -> -0.015635433 | W25: =IF(AND(I25<>"",I24<>""),LN(I25/I24),"") -> -0.013438038 | ... Y25: =IF(AND(K25<>"",K24<>""),LN(K25/K24),"") -> 9.8588411e-05 | Z25: 0.000481 | AA25: =IF(AND(L25<>"",L24<>""),LN(L25/L24),"") -> 0.026575375 | AB25: =IF(AND(M25<>"",M24<>""),LN(M25/M24),"") -> -0.0096525846 | AE25: 43497 | AF25: 16.14 | AG25: 33.4 | AH25: 48.79 | AI25: =IF(AND(M25<>"",L25<>""),M25-L25,"") -> 6.57 | AJ25: 2.7 | AK25: 19.3 | AL25: =IF(AND(AK25<>"",AJ25<>""),AK25-AJ25,"") -> 16.6 | AM25: 2.4 | AN25: 2.52 | AO25: 2.7 | AP25: =IF(AND(AO25<>"",AN25<>""),AO25-AN25,"") -> 0.18 | AQ25: 1.88 | AR25: 113.7548 | AS25: 1316.9 | AT25: 253.319 | AU25: 102.8371 | AV25: 93.8 | AY25: 43497 | AZ25: 0 | BA25: 0 | BB25: 0 | BE25: 43497 | BF25: Pre-COVID | BG25: 1
A26: 43500 | B26: 53.6826 | C26: 87.1944 | D26: 54.5015 | E26: 57.6062 | F26: 64.393 | H26: 3.0007 | I26: 15.6722 | J26: 7.9752 | K26: 76.086 | L26: 54.57 | M26: 62.26 | O26: 43500 | P26: =IF(AND(B26<>"",B25<>""),LN(B26/B25),"") -> -0.01459421 | Q26: =IF(AND(C26<>"",C25<>""),LN(C26/C25),"") -> 0.011507055 | R26: =IF(AND(D26<>"",D25<>""),LN(D26/D25),"") -> 0.01803642 | S26: =IF(AND(E26<>"",E25<>""),LN(E26/E25),"") -> -0.0044185665 | T26: =IF(AND(F26<>"",F25<>""),LN(F26/F25),"") -> 0.0061030984 | U26: =IF(AND(G26<>"",G25<>""),LN(G26/G25),"") | V26: =IF(AND(H26<>"",H25<>""),LN(H26/H25),"") -> 0.003940168 | W26: =IF(AND(I26<>"",I25<>""),LN(I26/I25),"") -> -0.0027081379 | ... Y26: =IF(AND(K26<>"",K25<>""),LN(K26/K25),"") -> 0.00011040748 | Z26: 0.007011 | AA26: =IF(AND(L26<>"",L25<>""),LN(L26/L25),"") -> -0.013107779 | AB26: =IF(AND(M26<>"",M25<>""),LN(M26/M25),"") -> 0.0064453978 | AE26: 43500 | AF26: 15.73 | AG26: 33.7 | AH26: 48.87 | AI26: =IF(AND(M26<>"",L26<>""),M26-L26,"") -> 7.69 | AJ26: 2.57 | AK26: 19.355 | AL26: =IF(AND(AK26<>"",AJ26<>""),AK26-AJ26,"") -> 16.785 | AM26: 2.4 | AN26: 2.53 | AO26: 2.73 | AP26: =IF(AND(AO26<>"",AN26<>""),AO26-AN26,"") -> 0.2 | AQ26: 1.87 | AR26: 113.8766 | AS26: 1314.3 | AT26: 253.319 | AU26: 102.8371 | AV26: 93.8 | AY26: 43500 | AZ26: 0 | BA26: 0 | BB26: 0 | BE26: 43500 | BF26: Pre-COVID | BG26: 1
A27: 43501 | B27: 54.235 | C27: 87.0051 | D27: 53.9793 | E27: 57.232 | F27: 64.3261 | H27: 3.1422 | I27: 15.213 | J27: 7.9858 | K27: 76.086 | L27: 53.69 | M27: 61.67 | O27: 43501 | P27: =IF(AND(B27<>"",B26<>""),LN(B27/B26),"") -> 0.01023753 | Q27: =IF(AND(C27<>"",C26<>""),LN(C27/C26),"") -> -0.002173371 | R27: =IF(AND(D27<>"",D26<>""),LN(D27/D26),"") -> -0.0096275845 | S27: =IF(AND(E27<>"",E26<>""),LN(E27/E26),"") -> -0.0065170183 | T27: =IF(AND(F27<>"",F26<>""),LN(F27/F26),"") -> -0.0010394729 | U27: =IF(AND(G27<>"",G26<>""),LN(G27/G26),"") | V27: =IF(AND(H27<>"",H26<>""),LN(H27/H26),"") -> 0.046077597 | W27: =IF(AND(I27<>"",I26<>""),LN(I27/I26),"") -> -0.029738117 | ... Y27: =IF(AND(K27<>"",K26<>""),LN(K27/K26),"") -> 0 | Z27: 0.004183 | AA27: =IF(AND(L27<>"",L26<>""),LN(L27/L26),"") -> -0.016257517 | AB27: =IF(AND(M27<>"",M26<>""),LN(M27/M26),"") -> -0.009521576 | AE27: 43501 | AF27: 15.57 | AG27: 34.57 | AH27: 48.62 | AI27: =IF(AND(M27<>"",L27<>""),M27-L27,"") -> 7.98 | AJ27: 2.54 | AK27: 19.14 | AL27: =IF(AND(AK27<>"",AJ27<>""),AK27-AJ27,"") -> 16.6 | AM27: 2.4 | AN27: 2.53 | AO27: 2.71 | AP27: =IF(AND(AO27<>"",AN27<>""),AO27-AN27,"") -> 0.18 | AQ27: 1.87 | AR27: 114.0431 | AS27: 1314.2 | AT27: 253.319 | AU27: 102.8371 | AV27: 93.8 | AY27: 43501 | AZ27: 0 | BA27: 0 | BB27: 0 | BE27: 43501 | BF27: Pre-COVID | BG27: 1
A28: 43502 | B28: 53.9982 | C28: 86.5682 | D28: 53.8624 | E28: 56.6622 | F28: 62.9881 | H28: 3.0891 | I28: 14.3541 | J28: 7.9224 | K28: 76.1026 | L28: 53.94 | M28: 62.22 | O28: 43502 | P28: =IF(AND(B28<>"",B27<>""),LN(B28/B27),"") -> -0.0043757438 | Q28: =IF(AND(C28<>"",C27<>""),LN(C28/C27),"") -> -0.005034195 | R28: =IF(AND(D28<>"",D27<>""),LN(D28/D27),"") -> -0.0021679934 | S28: =IF(AND(E28<>"",E27<>""),LN(E28/E27),"") -> -0.010005861 | T28: =IF(AND(F28<>"",F27<>""),LN(F28/F27),"") -> -0.021019639 | U28: =IF(AND(G28<>"",G27<>""),LN(G28/G27),"") | V28: =IF(AND(H28<>"",H27<>""),LN(H28/H27),"") -> -0.017043405 | W28: =IF(AND(I28<>"",I27<>""),LN(I28/I27),"") -> -0.05811471 | ... Y28: =IF(AND(K28<>"",K27<>""),LN(K28/K27),"") -> 0.00021815037 | Z28: -0.001319 | AA28: =IF(AND(L28<>"",L27<>""),LN(L28/L27),"") -> 0.0046455533 | AB28: =IF(AND(M28<>"",M27<>""),LN(M28/M27),"") -> 0.0088789025 | AE28: 43502 | AF28: 15.38 | AG28: 33.02 | AH28: 47.44 | AI28: =IF(AND(M28<>"",L28<>""),M28-L28,"") -> 8.28 | AJ28: 2.58 | AK28: 18.915 | AL28: =IF(AND(AK28<>"",AJ28<>""),AK28-AJ28,"") -> 16.335 | AM28: 2.4 | AN28: 2.52 | AO28: 2.7 | AP28: =IF(AND(AO28<>"",AN28<>""),AO28-AN28,"") -> 0.18 | AQ28: 1.86 | AR28: 114.2305 | AS28: 1309.5 | AT28: 253.319 | AU28: 102.8371 | AV28: 93.8 | AY28: 43502 | AZ28: 0 | BA28: 0 | BB28: 0 | BE28: 43502 | BF28: Pre-COVID | BG28: 1
A29: 43503 | B29: 53.5821 | C29: 86.0949 | D29: 52.592 | E29: 55.208 | F29: 62.8735 | H29: 2.9594 | I29: 13.6313 | J29: 7.7793 | K29: 76.1026 | L29: 52.68 | M29: 61.01 | O29: 43503 | P29: =IF(AND(B29<>"",B28<>""),LN(B29/B28),"") -> -0.0077356556 | Q29: =IF(AND(C29<>"",C28<>""),LN(C29/C28),"") -> -0.0054823664 | R29: =IF(AND(D29<>"",D28<>""),LN(D29/D28),"") -> -0.023868629 | S29: =IF(AND(E29<>"",E28<>""),LN(E29/E28),"") -> -0.025999451 | T29: =IF(AND(F29<>"",F28<>""),LN(F29/F28),"") -> -0.0018210484 | U29: =IF(AND(G29<>"",G28<>""),LN(G29/G28),"") | V29: =IF(AND(H29<>"",H28<>""),LN(H29/H28),"") -> -0.042893241 | W29: =IF(AND(I29<>"",I28<>""),LN(I29/I28),"") -> -0.051666997 | ... Y29: =IF(AND(K29<>"",K28<>""),LN(K29/K28),"") -> 0 | Z29: -0.009578 | AA29: =IF(AND(L29<>"",L28<>""),LN(L29/L28),"") -> -0.023636441 | AB29: =IF(AND(M29<>"",M28<>""),LN(M29/M28),"") -> -0.019638706 | AE29: 43503 | AF29: 16.37 | AG29: 34.34 | AH29: 48.97 | AI29: =IF(AND(M29<>"",L29<>""),M29-L29,"") -> 8.33 | AJ29: 2.62 | AK29: 18.91 | AL29: =IF(AND(AK29<>"",AJ29<>""),AK29-AJ29,"") -> 16.29 | AM29: 2.4 | AN29: 2.48 | AO29: 2.65 | AP29: =IF(AND(AO29<>"",AN29<>""),AO29-AN29,"") -> 0.17 | AQ29: 1.84 | AR29: 114.4339 | AS29: 1309.4 | AT29: 253.319 | AU29: 102.8371 | AV29: 93.8 | AY29: 43503 | AZ29: 0 | BA29: 0 | BB29: 0 | BE29: 43503 | BF29: Pre-COVID | BG29: 1
A30: 43504 | B30: 53.6692 | C30: 85.6215 | D30: 51.8757 | E30: 55.2421 | F30: 62.6823 | H30: 2.8887 | I30: 13.2572 | J30: 7.7523 | K30: 76.1192 | L30: 52.75 | M30: 61.37 | O30: 43504 | P30: =IF(AND(B30<>"",B29<>""),LN(B30/B29),"") -> 0.0016242231 | Q30: =IF(AND(C30<>"",C29<>""),LN(C30/C29),"") -> -0.0055137564 | R30: =IF(AND(D30<>"",D29<>""),LN(D30/D29),"") -> -0.013713544 | S30: =IF(AND(E30<>"",E29<>""),LN(E30/E29),"") -> 0.00061747343 | T30: =IF(AND(F30<>"",F29<>""),LN(F30/F29),"") -> -0.0030456601 | U30: =IF(AND(G30<>"",G29<>""),LN(G30/G29),"") | V30: =IF(AND(H30<>"",H29<>""),LN(H30/H29),"") -> -0.024179971 | W30: =IF(AND(I30<>"",I29<>""),LN(I30/I29),"") -> -0.027827818 | ... Y30: =IF(AND(K30<>"",K29<>""),LN(K30/K29),"") -> 0.0002181028 | Z30: 0.001221 | AA30: =IF(AND(L30<>"",L29<>""),LN(L30/L29),"") -> 0.0013278955 | AB30: =IF(AND(M30<>"",M29<>""),LN(M30/M29),"") -> 0.0058833312 | AE30: 43504 | AF30: 15.72 | AG30: 32.56 | AH30: 49.63 | AI30: =IF(AND(M30<>"",L30<>""),M30-L30,"") -> 8.62 | AJ30: 2.66 | AK30: 18.265 | AL30: =IF(AND(AK30<>"",AJ30<>""),AK30-AJ30,"") -> 15.605 | AM30: 2.4 | AN30: 2.45 | AO30: 2.63 | AP30: =IF(AND(AO30<>"",AN30<>""),AO30-AN30,"") -> 0.18 | AQ30: 1.82 | AR30: 114.5003 | AS30: 1313.7 | AT30: 253.319 | AU30: 102.8371 | AV30: 93.8 | AY30: 43504 | AZ30: 0 | BA30: 0 | BB30: 0 | BE30: 43504 | BF30: Pre-COVID | BG30: 1
A31: 43507 | B31: 53.7562 | C31: 85.1628 | D31: 52.2515 | E31: 55.14 | F31: 62.4434 | H31: 2.9653 | I31: 13.7929 | J31: 7.6929 | K31: 76.1109 | L31: 52.43 | M31: 61.3 | O31: 43507 | P31: =IF(AND(B31<>"",B30<>""),LN(B31/B30),"") -> 0.001619729 | Q31: =IF(AND(C31<>"",C30<>""),LN(C31/C30),"") -> -0.0053717011 | R31: =IF(AND(D31<>"",D30<>""),LN(D31/D30),"") -> 0.0072181261 | S31: =IF(AND(E31<>"",E30<>""),LN(E31/E30),"") -> -0.0018499382 | T31: =IF(AND(F31<>"",F30<>""),LN(F31/F30),"") -> -0.0038185647 | U31: =IF(AND(G31<>"",G30<>""),LN(G31/G30),"") | V31: =IF(AND(H31<>"",H30<>""),LN(H31/H30),"") -> 0.026171634 | W31: =IF(AND(I31<>"",I30<>""),LN(I31/I30),"") -> 0.039613166 | ... Y31: =IF(AND(K31<>"",K30<>""),LN(K31/K30),"") -> -0.00010904545 | Z31: 0.000554 | AA31: =IF(AND(L31<>"",L30<>""),LN(L31/L30),"") -> -0.0060848258 | AB31: =IF(AND(M31<>"",M30<>""),LN(M31/M30),"") -> -0.0011412735 | AE31: 43507 | AF31: 15.97 | AG31: 33.34 | AH31: 48.32 | AI31: =IF(AND(M31<>"",L31<>""),M31-L31,"") -> 8.87 | AJ31: 2.76 | AK31: 18.055 | AL31: =IF(AND(AK31<>"",AJ31<>""),AK31-AJ31,"") -> 15.295 | AM31: 2.4 | AN31: 2.48 | AO31: 2.65 | AP31: =IF(AND(AO31<>"",AN31<>""),AO31-AN31,"") -> 0.17 | AQ31: 1.82 | AR31: 115.031 | AS31: 1307 | AT31: 253.319 | AU31: 102.8371 | AV31: 93.8 | AY31: 43507 | AZ31: 0 | BA31: 0 | BB31: 0 | BE31: 43507 | BF31: Pre-COVID | BG31: 1
A32: 43508 | B32: 54.6993 | C32: 86.4517 | D32: 52.8073 | E32: 55.9139 | F32: 62.9021 | H32: 3.2365 | I32: 14.4562 | J32: 7.8495 | K32: 76.1275 | L32: 53.14 | M32: 62.58 | O32: 43508 | P32: =IF(AND(B32<>"",B31<>""),LN(B32/B31),"") -> 0.017391903 | Q32: =IF(AND(C32<>"",C31<>""),LN(C32/C31),"") -> 0.015021158 | R32: =IF(AND(D32<>"",D31<>""),LN(D32/D31),"") -> 0.01058084 | S32: =IF(AND(E32<>"",E31<>""),LN(E32/E31),"") -> 0.013937602 | T32: =IF(AND(F32<>"",F31<>""),LN(F32/F31),"") -> 0.007319003 | U32: =IF(AND(G32<>"",G31<>""),LN(G32/G31),"") | V32: =IF(AND(H32<>"",H31<>""),LN(H32/H31),"") -> 0.087514291 | W32: =IF(AND(I32<>"",I31<>""),LN(I32/I31),"") -> 0.046969421 | ... Y32: =IF(AND(K32<>"",K31<>""),LN(K32/K31),"") -> 0.00021807901 | Z32: 0.012778 | AA32: =IF(AND(L32<>"",L31<>""),LN(L32/L31),"") -> 0.013450994 | AB32: =IF(AND(M32<>"",M31<>""),LN(M32/M31),"") -> 0.020665895 | AE32: 43508 | AF32: 15.43 | AG32: 32.69 | AH32: 49.02 | AI32: =IF(AND(M32<>"",L32<>""),M32-L32,"") -> 9.44 | AJ32: 2.71 | AK32: 17.785 | AL32: =IF(AND(AK32<>"",AJ32<>""),AK32-AJ32,"") -> 15.075 | AM32: 2.4 | AN32: 2.5 | AO32: 2.68 | AP32: =IF(AND(AO32<>"",AN32<>""),AO32-AN32,"") -> 0.18 | AQ32: 1.83 | AR32: 114.7297 | AS32: 1309.2 | AT32: 253.319 | AU32: 102.8371 | AV32: 93.8 | AY32: 43508 | AZ32: 0 | BA32: 0 | BB32: 0 | BE32: 43508 | BF32: Pre-COVID | BG32: 1
A33: 43509 | B33: 55.316 | C33: 87.0707 | D33: 53.0657 | E33: 55.9989 | F33: 62.9308 | H33: 3.2365 | I33: 15.1705 | J33: 8.0006 | K33: 76.1275 | L33: 53.84 | M33: 63.27 | O33: 43509 | P33: =IF(AND(B33<>"",B32<>""),LN(B33/B32),"") -> 0.011211285 | Q33: =IF(AND(C33<>"",C32<>""),LN(C33/C32),"") -> 0.0071345558 | R33: =IF(AND(D33<>"",D32<>""),LN(D33/D32),"") -> 0.0048813298 | S33: =IF(AND(E33<>"",E32<>""),LN(E33/E32),"") -> 0.0015190401 | T33: =IF(AND(F33<>"",F32<>""),LN(F33/F32),"") -> 0.00045616052 | U33: =IF(AND(G33<>"",G32<>""),LN(G33/G32),"") | V33: =IF(AND(H33<>"",H32<>""),LN(H33/H32),"") -> 0 | W33: =IF(AND(I33<>"",I32<>""),LN(I33/I32),"") -> 0.048229364 | ... Y33: =IF(AND(K33<>"",K32<>""),LN(K33/K32),"") -> 0 | Z33: 0.003241 | AA33: =IF(AND(L33<>"",L32<>""),LN(L33/L32),"") -> 0.013086745 | AB33: =IF(AND(M33<>"",M32<>""),LN(M33/M32),"") -> 0.010965545 | AE33: 43509 | AF33: 15.65 | AG33: 32.26 | AH33: 48.17 | AI33: =IF(AND(M33<>"",L33<>""),M33-L33,"") -> 9.43 | AJ33: 2.61 | AK33: 18.02 | AL33: =IF(AND(AK33<>"",AJ33<>""),AK33-AJ33,"") -> 15.41 | AM33: 2.4 | AN33: 2.53 | AO33: 2.71 | AP33: =IF(AND(AO33<>"",AN33<>""),AO33-AN33,"") -> 0.18 | AQ33: 1.86 | AR33: 114.9407 | AS33: 1310.8 | AT33: 253.319 | AU33: 102.8371 | AV33: 93.8 | AY33: 43509 | AZ33: 0 | BA33: 0 | BB33: 0 | BE33: 43509 | BF33: Pre-COVID | BG33: 1
A34: 43510 | B34: 55.3305 | C34: 86.9088 | D34: 54.0991 | E34: 56.6112 | F34: 63.0742 | H34: 3.3544 | I34: 16.4885 | J34: 8.1032 | K34: 76.1442 | L34: 54.4 | M34: 64 | O34: 43510 | P34: =IF(AND(B34<>"",B33<>""),LN(B34/B33),"") -> 0.00026209596 | Q34: =IF(AND(C34<>"",C33<>""),LN(C34/C33),"") -> -0.0018611393 | R34: =IF(AND(D34<>"",D33<>""),LN(D34/D33),"") -> 0.019286781 | S34: =IF(AND(E34<>"",E33<>""),LN(E34/E33),"") -> 0.010874798 | T34: =IF(AND(F34<>"",F33<>""),LN(F34/F33),"") -> 0.0022761011 | U34: =IF(AND(G34<>"",G33<>""),LN(G34/G33),"") | V34: =IF(AND(H34<>"",H33<>""),LN(H34/H33),"") -> 0.035780418 | W34: =IF(AND(I34<>"",I33<>""),LN(I34/I33),"") -> 0.083310416 | ... Y34: =IF(AND(K34<>"",K33<>""),LN(K34/K33),"") -> 0.00021934476 | Z34: -0.002221 | AA34: =IF(AND(L34<>"",L33<>""),LN(L34/L33),"") -> 0.010347469 | AB34: =IF(AND(M34<>"",M33<>""),LN(M34/M33),"") -> 0.0114718 | AE34: 43510 | AF34: 16.22 | AG34: 32.1 | AH34: 47.19 | AI34: =IF(AND(M34<>"",L34<>""),M34-L34,"") -> 9.6 | AJ34: 2.61 | AK34: 17.755 | AL34: =IF(AND(AK34<>"",AJ34<>""),AK34-AJ34,"") -> 15.145 | AM34: 2.4 | AN34: 2.5 | AO34: 2.66 | AP34: =IF(AND(AO34<>"",AN34<>""),AO34-AN34,"") -> 0.16 | AQ34: 1.85 | AR34: 115.1007 | AS34: 1309.8 | AT34: 253.319 | AU34: 102.8371 | AV34: 93.8 | AY34: 43510 | AZ34: 0 | BA34: 0 | BB34: 0 | BE34: 43510 | BF34: Pre-COVID | BG34: 1
A35: 43511 | B35: 56.3751 | C35: 87.7841 | D35: 54.9447 | E35: 57.1385 | F35: 63.2844 | H35: 3.4487 | I35: 16.8117 | J35: 8.1248 | K35: 76.1442 | L35: 55.58 | M35: 65.65 | O35: 43511 | P35: =IF(AND(B35<>"",B34<>""),LN(B35/B34),"") -> 0.018703278 | Q35: =IF(AND(C35<>"",C34<>""),LN(C35/C34),"") -> 0.010021098 | R35: =IF(AND(D35<>"",D34<>""),LN(D35/D34),"") -> 0.015509675 | S35: =IF(AND(E35<>"",E34<>""),LN(E35/E34),"") -> 0.0092712997 | T35: =IF(AND(F35<>"",F34<>""),LN(F35/F34),"") -> 0.0033270421 | U35: =IF(AND(G35<>"",G34<>""),LN(G35/G34),"") | V35: =IF(AND(H35<>"",H34<>""),LN(H35/H34),"") -> 0.027724432 | W35: =IF(AND(I35<>"",I34<>""),LN(I35/I34),"") -> 0.019411904 | ... Y35: =IF(AND(K35<>"",K34<>""),LN(K35/K34),"") -> 0 | Z35: 0.010839 | AA35: =IF(AND(L35<>"",L34<>""),LN(L35/L34),"") -> 0.02145927 | AB35: =IF(AND(M35<>"",M34<>""),LN(M35/M34),"") -> 0.025454517 | AE35: 43511 | AF35: 14.91 | AG35: 29.46 | AH35: 45.73 | AI35: =IF(AND(M35<>"",L35<>""),M35-L35,"") -> 10.07 | AJ35: 2.59 | AK35: 18.1 | AL35: =IF(AND(AK35<>"",AJ35<>""),AK35-AJ35,"") -> 15.51 | AM35: 2.4 | AN35: 2.52 | AO35: 2.66 | AP35: =IF(AND(AO35<>"",AN35<>""),AO35-AN35,"") -> 0.14 | AQ35: 1.86 | AR35: 114.9923 | AS35: 1318.1 | AT35: 253.319 | AU35: 102.8371 | AV35: 93.8 | AY35: 43511 | AZ35: 0 | BA35: 0 | BB35: 0 | BE35: 43511 | BF35: Pre-COVID | BG35: 1
A36: 43515 | B36: 56.7524 | C36: 87.7547 | D36: 54.4044 | E36: 57.5126 | F36: 63.9438 | H36: 3.4605 | I36: 16.9647 | J36: 8.4325 | K36: 76.1608 | L36: 56.12 | M36: 65.86 | O36: 43515 | P36: =IF(AND(B36<>"",B35<>""),LN(B36/B35),"") -> 0.0066703746 | Q36: =IF(AND(C36<>"",C35<>""),LN(C36/C35),"") -> -0.00033496868 | R36: =IF(AND(D36<>"",D35<>""),LN(D36/D35),"") -> -0.0098821919 | S36: =IF(AND(E36<>"",E35<>""),LN(E36/E35),"") -> 0.0065259091 | T36: =IF(AND(F36<>"",F35<>""),LN(F36/F35),"") -> 0.010365719 | U36: =IF(AND(G36<>"",G35<>""),LN(G36/G35),"") | V36: =IF(AND(H36<>"",H35<>""),LN(H36/H35),"") -> 0.0034157389 | W36: =IF(AND(I36<>"",I35<>""),LN(I36/I35),"") -> 0.009059642 | ... Y36: =IF(AND(K36<>"",K35<>""),LN(K36/K35),"") -> 0.00021798365 | Z36: 0.001729 | AA36: =IF(AND(L36<>"",L35<>""),LN(L36/L35),"") -> 0.0096688309 | AB36: =IF(AND(M36<>"",M35<>""),LN(M36/M35),"") -> 0.0031936762 | AE36: 43515 | AF36: 14.88 | AG36: 31 | AH36: 45.06 | AI36: =IF(AND(M36<>"",L36<>""),M36-L36,"") -> 9.74 | AJ36: 2.69 | AK36: 17.705 | AL36: =IF(AND(AK36<>"",AJ36<>""),AK36-AJ36,"") -> 15.015 | AM36: 2.4 | AN36: 2.5 | AO36: 2.65 | AP36: =IF(AND(AO36<>"",AN36<>""),AO36-AN36,"") -> 0.15 | AQ36: 1.87 | AR36: 114.57 | AS36: 1340.1 | AT36: 253.319 | AU36: 102.8371 | AV36: 93.8 | AY36: 43515 | AZ36: 0 | BA36: 0 | BB36: 0 | BE36: 43515 | BF36: Pre-COVID | BG36: 1
A37: 43516 | B37: 56.97 | C37: 88.4681 | D37: 55.3126 | E37: 58.0399 | F37: 63.0359 | H37: 3.3721 | I37: 16.7266 | J37: 8.3677 | K37: 76.1608 | L37: 56.9 | M37: 66.82 | O37: 43516 | P37: =IF(AND(B37<>"",B36<>""),LN(B37/B36),"") -> 0.0038268673 | Q37: =IF(AND(C37<>"",C36<>""),LN(C37/C36),"") -> 0.0080966129 | R37: =IF(AND(D37<>"",D36<>""),LN(D37/D36),"") -> 0.016555698 | S37: =IF(AND(E37<>"",E36<>""),LN(E37/E36),"") -> 0.0091266508 | T37: =IF(AND(F37<>"",F36<>""),LN(F37/F36),"") -> -0.014300167 | U37: =IF(AND(G37<>"",G36<>""),LN(G37/G36),"") | V37: =IF(AND(H37<>"",H36<>""),LN(H37/H36),"") -> -0.025877392 | W37: =IF(AND(I37<>"",I36<>""),LN(I37/I36),"") -> -0.014134448 | ... Y37: =IF(AND(K37<>"",K36<>""),LN(K37/K36),"") -> 0 | Z37: 0.002014 | AA37: =IF(AND(L37<>"",L36<>""),LN(L37/L36),"") -> 0.013803086 | AB37: =IF(AND(M37<>"",M36<>""),LN(M37/M36),"") -> 0.01447116 | AE37: 43516 | AF37: 14.02 | AG37: 30.76 | AH37: 44.54 | AI37: =IF(AND(M37<>"",L37<>""),M37-L37,"") -> 9.92 | AJ37: 2.69 | AK37: 18.145 | AL37: =IF(AND(AK37<>"",AJ37<>""),AK37-AJ37,"") -> 15.455 | AM37: 2.4 | AN37: 2.5 | AO37: 2.65 | AP37: =IF(AND(AO37<>"",AN37<>""),AO37-AN37,"") -> 0.15 | AQ37: 1.89 | AS37: 1343.3 | AT37: 253.319 | AU37: 102.8371 | AV37: 93.8 | AY37: 43516 | AZ37: 0 | BA37: 0 | BB37: 0 | BE37: 43516 | BF37: Pre-COVID | BG37: 1
A38: 43517 | B38: 56.4549 | C38: 87.6296 | D38: 54.9916 | E38: 56.6367 | F38: 62.4625 | H38: 3.3839 | I38: 16.6331 | J38: 8.3893 | K38: 76.1691 | L38: 56.95 | M38: 66.91 | O38: 43517 | P38: =IF(AND(B38<>"",B37<>""),LN(B38/B37),"") -> -0.0090827242 | Q38: =IF(AND(C38<>"",C37<>""),LN(C38/C37),"") -> -0.0095231946 | R38: =IF(AND(D38<>"",D37<>""),LN(D38/D37),"") -> -0.0058202844 | S38: =IF(AND(E38<>"",E37<>""),LN(E38/E37),"") -> -0.02447352 | T38: =IF(AND(F38<>"",F37<>""),LN(F38/F37),"") -> -0.0091380287 | U38: =IF(AND(G38<>"",G37<>""),LN(G38/G37),"") | V38: =IF(AND(H38<>"",H37<>""),LN(H38/H37),"") -> 0.0034931948 | W38: =IF(AND(I38<>"",I37<>""),LN(I38/I37),"") -> -0.0056055807 | ... Y38: =IF(AND(K38<>"",K37<>""),LN(K38/K37),"") -> 0.00010897401 | Z38: -0.003562 | AA38: =IF(AND(L38<>"",L37<>""),LN(L38/L37),"") -> 0.00087834876 | AB38: =IF(AND(M38<>"",M37<>""),LN(M38/M37),"") -> 0.0013459959 | AE38: 43517 | AF38: 14.46 | AG38: 30.16 | AH38: 46.55 | AI38: =IF(AND(M38<>"",L38<>""),M38-L38,"") -> 9.96 | AJ38: 2.73 | AK38: 17.52 | AL38: =IF(AND(AK38<>"",AJ38<>""),AK38-AJ38,"") -> 14.79 | AM38: 2.4 | AN38: 2.53 | AO38: 2.69 | AP38: =IF(AND(AO38<>"",AN38<>""),AO38-AN38,"") -> 0.16 | AQ38: 1.91 | AR38: 114.5091 | AS38: 1323.5 | AT38: 253.319 | AU38: 102.8371 | AV38: 93.8 | AY38: 43517 | AZ38: 0 | BA38: 0 | BB38: 0 | BE38: 43517 | BF38: Pre-COVID | BG38: 1
A39: 43518 | B39: 56.8902 | C39: 87.8135 | D39: 54.7803 | E39: 56.067 | F39: 62.3096 | H39: 3.5725 | I39: 16.5225 | J39: 8.2976 | K39: 76.1858 | L39: 57.01 | M39: 66.91 | O39: 43518 | P39: =IF(AND(B39<>"",B38<>""),LN(B39/B38),"") -> 0.007681005 | Q39: =IF(AND(C39<>"",C38<>""),LN(C39/C38),"") -> 0.002096407 | R39: =IF(AND(D39<>"",D38<>""),LN(D39/D38),"") -> -0.003849806 | S39: =IF(AND(E39<>"",E38<>""),LN(E39/E38),"") -> -0.010109781 | T39: =IF(AND(F39<>"",F38<>""),LN(F39/F38),"") -> -0.0024508697 | U39: =IF(AND(G39<>"",G38<>""),LN(G39/G38),"") | V39: =IF(AND(H39<>"",H38<>""),LN(H39/H38),"") -> 0.05423674 | W39: =IF(AND(I39<>"",I38<>""),LN(I39/I38),"") -> -0.0066715976 | ... Y39: =IF(AND(K39<>"",K38<>""),LN(K39/K38),"") -> 0.00021922498 | Z39: 0.006181 | AA39: =IF(AND(L39<>"",L38<>""),LN(L39/L38),"") -> 0.0010530012 | AB39: =IF(AND(M39<>"",M38<>""),LN(M39/M38),"") -> 0 | AE39: 43518 | AF39: 13.51 | AG39: 29.85 | AH39: 47.22 | AI39: =IF(AND(M39<>"",L39<>""),M39-L39,"") -> 9.9 | AJ39: 2.74 | AK39: 17.23 | AL39: =IF(AND(AK39<>"",AJ39<>""),AK39-AJ39,"") -> 14.49 | AM39: 2.4 | AN39: 2.48 | AO39: 2.65 | AP39: =IF(AND(AO39<>"",AN39<>""),AO39-AN39,"") -> 0.17 | AQ39: 1.91 | AR39: 114.2716 | AS39: 1329.2 | AT39: 253.319 | AU39: 102.8371 | AV39: 93.8 | AY39: 43518 | AZ39: 0 | BA39: 0 | BB39: 0 | BE39: 43518 | BF39: Pre-COVID | BG39: 1
A40: 43521 | B40: 56.9482 | C40: 87.9827 | D40: 54.2166 | E40: 56.3221 | F40: 61.7649 | H40: 3.431 | I40: 16.5821 | J40: 8.2976 | K40: 76.1775 | L40: 55.32 | M40: 64.02 | O40: 43521 | P40: =IF(AND(B40<>"",B39<>""),LN(B40/B39),"") -> 0.0010189884 | Q40: =IF(AND(C40<>"",C39<>""),LN(C40/C39),"") -> 0.0019249569 | R40: =IF(AND(D40<>"",D39<>""),LN(D40/D39),"") -> -0.010343506 | S40: =IF(AND(E40<>"",E39<>""),LN(E40/E39),"") -> 0.0045395939 | T40: =IF(AND(F40<>"",F39<>""),LN(F40/F39),"") -> -0.0087802651 | U40: =IF(AND(G40<>"",G39<>""),LN(G40/G39),"") | V40: =IF(AND(H40<>"",H39<>""),LN(H40/H39),"") -> -0.040413867 | W40: =IF(AND(I40<>"",I39<>""),LN(I40/I39),"") -> 0.0036007119 | ... Y40: =IF(AND(K40<>"",K39<>""),LN(K40/K39),"") -> -0.00010895012 | Z40: 0.001361 | AA40: =IF(AND(L40<>"",L39<>""),LN(L40/L39),"") -> -0.030092184 | AB40: =IF(AND(M40<>"",M39<>""),LN(M40/M39),"") -> -0.044152898 | AE40: 43521 | AF40: 14.85 | AG40: 32.69 | AH40: 46.16 | AI40: =IF(AND(M40<>"",L40<>""),M40-L40,"") -> 8.7 | AJ40: 2.84 | AK40: 16.945 | AL40: =IF(AND(AK40<>"",AJ40<>""),AK40-AJ40,"") -> 14.105 | AM40: 2.4 | AN40: 2.51 | AO40: 2.67 | AP40: =IF(AND(AO40<>"",AN40<>""),AO40-AN40,"") -> 0.16 | AQ40: 1.92 | AR40: 114.1457 | AS40: 1325.9 | AT40: 253.319 | AU40: 102.8371 | AV40: 93.8 | AY40: 43521 | AZ40: 0 | BA40: 0 | BB40: 0 | BE40: 43521 | BF40: Pre-COVID | BG40: 1
A41: 43522 | B41: 57.0643 | C41: 88.218 | D41: 53.9582 | E41: 56.1605 | F41: 60.7136 | H41: 3.5136 | I41: 16.7011 | J41: 8.0492 | K41: 76.1858 | L41: 55.4 | M41: 64.51 | O41: 43522 | P41: =IF(AND(B41<>"",B40<>""),LN(B41/B40),"") -> 0.0020366195 | Q41: =IF(AND(C41<>"",C40<>""),LN(C41/C40),"") -> 0.0026708196 | R41: =IF(AND(D41<>"",D40<>""),LN(D41/D40),"") -> -0.0047774619 | S41: =IF(AND(E41<>"",E40<>""),LN(E41/E40),"") -> -0.0028733353 | T41: =IF(AND(F41<>"",F40<>""),LN(F41/F40),"") -> -0.017167516 | U41: =IF(AND(G41<>"",G40<>""),LN(G41/G40),"") | V41: =IF(AND(H41<>"",H40<>""),LN(H41/H40),"") -> 0.023789389 | W41: =IF(AND(I41<>"",I40<>""),LN(I41/I40),"") -> 0.0071507852 | ... Y41: =IF(AND(K41<>"",K40<>""),LN(K41/K40),"") -> 0.00010895012 | Z41: -0.000716 | AA41: =IF(AND(L41<>"",L40<>""),LN(L41/L40),"") -> 0.001445087 | AB41: =IF(AND(M41<>"",M40<>""),LN(M41/M40),"") -> 0.007624716 | AE41: 43522 | AF41: 15.17 | AG41: 31.57 | AH41: 46.28 | AI41: =IF(AND(M41<>"",L41<>""),M41-L41,"") -> 9.11 | AJ41: 2.74 | AK41: 17.045 | AL41: =IF(AND(AK41<>"",AJ41<>""),AK41-AJ41,"") -> 14.305 | AM41: 2.4 | AN41: 2.48 | AO41: 2.64 | AP41: =IF(AND(AO41<>"",AN41<>""),AO41-AN41,"") -> 0.16 | AQ41: 1.92 | AR41: 114.0687 | AS41: 1325.1 | AT41: 253.319 | AU41: 102.8371 | AV41: 93.8 | AY41: 43522 | AZ41: 0 | BA41: 0 | BB41: 0 | BE41: 43522 | BF41: Pre-COVID | BG41: 1
A42: 43523 | B42: 57.6519 | C42: 88.321 | D42: 54.1931 | E42: 56.6792 | F42: 62.6345 | H42: 3.714 | I42: 15.9018 | J42: 8.0222 | K42: 76.1941 | L42: 56.92 | M42: 65.55 | O42: 43523 | P42: =IF(AND(B42<>"",B41<>""),LN(B42/B41),"") -> 0.010244501 | Q42: =IF(AND(C42<>"",C41<>""),LN(C42/C41),"") -> 0.0011668811 | R42: =IF(AND(D42<>"",D41<>""),LN(D42/D41),"") -> 0.0043439213 | S42: =IF(AND(E42<>"",E41<>""),LN(E42/E41),"") -> 0.0091936376 | T42: =IF(AND(F42<>"",F41<>""),LN(F42/F41),"") -> 0.031148519 | U42: =IF(AND(G42<>"",G41<>""),LN(G42/G41),"") | V42: =IF(AND(H42<>"",H41<>""),LN(H42/H41),"") -> 0.05546831 | W42: =IF(AND(I42<>"",I41<>""),LN(I42/I41),"") -> -0.049042275 | ... Y42: =IF(AND(K42<>"",K41<>""),LN(K42/K41),"") -> 0.00010893825 | Z42: -0.000429 | AA42: =IF(AND(L42<>"",L41<>""),LN(L42/L41),"") -> 0.027067179 | AB42: =IF(AND(M42<>"",M41<>""),LN(M42/M41),"") -> 0.01599296 | AE42: 43523 | AF42: 14.7 | AG42: 31.01 | AI42: =IF(AND(M42<>"",L42<>""),M42-L42,"") -> 8.63 | AJ42: 2.89 | AK42: 17.615 | AL42: =IF(AND(AK42<>"",AJ42<>""),AK42-AJ42,"") -> 14.725 | AM42: 2.4 | AN42: 2.5 | AO42: 2.69 | AP42: =IF(AND(AO42<>"",AN42<>""),AO42-AN42,"") -> 0.19 | AQ42: 1.93 | AR42: 114.0363 | AS42: 1317.7 | AT42: 253.319 | AU42: 102.8371 | AV42: 93.8 | AY42: 43523 | AZ42: 0 | BA42: 0 | BB42: 0 | BE42: 43523 | BF42: Pre-COVID | BG42: 1
A43: 43524 | B43: 57.3327 | C43: 87.9533 | D43: 53.1205 | E43: 56.2541 | F43: 61.5929 | H43: 3.7847 | I43: 15.6552 | J43: 7.9844 | K43: 76.2107 | L43: 57.21 | M43: 65.03 | O43: 43524 | P43: =IF(AND(B43<>"",B42<>""),LN(B43/B42),"") -> -0.0055520621 | Q43: =IF(AND(C43<>"",C42<>""),LN(C43/C42),"") -> -0.0041719131 | R43: =IF(AND(D43<>"",D42<>""),LN(D43/D42),"") -> -0.019990676 | S43: =IF(AND(E43<>"",E42<>""),LN(E43/E42),"") -> -0.0075283731 | T43: =IF(AND(F43<>"",F42<>""),LN(F43/F42),"") -> -0.01676964 | U43: =IF(AND(G43<>"",G42<>""),LN(G43/G42),"") | V43: =IF(AND(H43<>"",H42<>""),LN(H43/H42),"") -> 0.018857161 | W43: =IF(AND(I43<>"",I42<>""),LN(I43/I42),"") -> -0.01562918 | ... Y43: =IF(AND(K43<>"",K42<>""),LN(K43/K42),"") -> 0.00021784091 | Z43: -0.001865 | AA43: =IF(AND(L43<>"",L42<>""),LN(L43/L42),"") -> 0.0050819351 | AB43: =IF(AND(M43<>"",M42<>""),LN(M43/M42),"") -> -0.0079645083 | AE43: 43524 | AF43: 14.78 | AG43: 30.27 | AH43: 47.22 | AI43: =IF(AND(M43<>"",L43<>""),M43-L43,"") -> 7.82 | AJ43: 2.89 | AK43: 17.815 | AL43: =IF(AND(AK43<>"",AJ43<>""),AK43-AJ43,"") -> 14.925 | AM43: 2.4 | AN43: 2.52 | AO43: 2.73 | AP43: =IF(AND(AO43<>"",AN43<>""),AO43-AN43,"") -> 0.21 | AQ43: 1.95 | AR43: 114.1991 | AS43: 1312.8 | AT43: 253.319 | AU43: 102.8371 | AV43: 93.8 | AY43: 43524 | AZ43: 0 | BA43: 0 | BB43: 0 | BE43: 43524 | BF43: Pre-COVID | BG43: 1
A44: 43525 | B44: 58.0364 | C44: 89.7553 | D44: 53.966 | E44: 57.4446 | F44: 61.1628 | H44: 3.8732 | I44: 15.6722 | J44: 8.087 | K44: 76.2191 | L44: 55.76 | M44: 63.71 | O44: 43525 | P44: =IF(AND(B44<>"",B43<>""),LN(B44/B43),"") -> 0.012199258 | Q44: =IF(AND(C44<>"",C43<>""),LN(C44/C43),"") -> 0.020281087 | R44: =IF(AND(D44<>"",D43<>""),LN(D44/D43),"") -> 0.015791301 | S44: =IF(AND(E44<>"",E43<>""),LN(E44/E43),"") -> 0.020942078 | T44: =IF(AND(F44<>"",F43<>""),LN(F44/F43),"") -> -0.0070074426 | U44: =IF(AND(G44<>"",G43<>""),LN(G44/G43),"") | V44: =IF(AND(H44<>"",H43<>""),LN(H44/H43),"") -> 0.023114415 | W44: =IF(AND(I44<>"",I43<>""),LN(I44/I43),"") -> 0.001085312 | ... Y44: =IF(AND(K44<>"",K43<>""),LN(K44/K43),"") -> 0.00011021467 | Z44: 0.006224 | AA44: =IF(AND(L44<>"",L43<>""),LN(L44/L43),"") -> -0.025671942 | AB44: =IF(AND(M44<>"",M43<>""),LN(M44/M43),"") -> -0.020507166 | AE44: 43525 | AF44: 13.57 | AG44: 30.31 | AH44: 47.9 | AI44: =IF(AND(M44<>"",L44<>""),M44-L44,"") -> 7.95 | AJ44: 3.19 | AK44: 17.32 | AL44: =IF(AND(AK44<>"",AJ44<>""),AK44-AJ44,"") -> 14.13 | AM44: 2.4 | AN44: 2.55 | AO44: 2.76 | AP44: =IF(AND(AO44<>"",AN44<>""),AO44-AN44,"") -> 0.21 | AQ44: 1.96 | AR44: 114.537 | AS44: 1296.4 | AT44: 254.277 | AU44: 102.8757 | AV44: 98.4 | AY44: 43525 | AZ44: 0 | BA44: 0 | BB44: 0 | BE44: 43525 | BF44: Pre-COVID | BG44: 1
A45: 43528 | B45: 58.2613 | C45: 89.8215 | D45: 54.7255 | E45: 57.3596 | F45: 62.1185 | H45: 3.9262 | I45: 15.9528 | J45: 8.0924 | K45: 76.2107 | L45: 56.6 | M45: 64.44 | O45: 43528 | P45: =IF(AND(B45<>"",B44<>""),LN(B45/B44),"") -> 0.0038676651 | Q45: =IF(AND(C45<>"",C44<>""),LN(C45/C44),"") -> 0.00073728904 | R45: =IF(AND(D45<>"",D44<>""),LN(D45/D44),"") -> 0.013975561 | S45: =IF(AND(E45<>"",E44<>""),LN(E45/E44),"") -> -0.0014807823 | T45: =IF(AND(F45<>"",F44<>""),LN(F45/F44),"") -> 0.01550469 | U45: =IF(AND(G45<>"",G44<>""),LN(G45/G44),"") | V45: =IF(AND(H45<>"",H44<>""),LN(H45/H44),"") -> 0.013590998 | W45: =IF(AND(I45<>"",I44<>""),LN(I45/I44),"") -> 0.01774592 | ... Y45: =IF(AND(K45<>"",K44<>""),LN(K45/K44),"") -> -0.00011021467 | Z45: -0.003644 | AA45: =IF(AND(L45<>"",L44<>""),LN(L45/L44),"") -> 0.014952219 | AB45: =IF(AND(M45<>"",M44<>""),LN(M45/M44),"") -> 0.011393022 | AE45: 43528 | AF45: 14.63 | AG45: 30.2 | AH45: 46.74 | AI45: =IF(AND(M45<>"",L45<>""),M45-L45,"") -> 7.84 | AJ45: 4.25 | AK45: 17.4 | AL45: =IF(AND(AK45<>"",AJ45<>""),AK45-AJ45,"") -> 13.15 | AM45: 2.4 | AN45: 2.55 | AO45: 2.72 | AP45: =IF(AND(AO45<>"",AN45<>""),AO45-AN45,"") -> 0.17 | AQ45: 1.94 | AR45: 114.6925 | AS45: 1284.8 | AT45: 254.277 | AU45: 102.8757 | AV45: 98.4 | AY45: 43528 | AZ45: 0 | BA45: 0 | BB45: 0 | BE45: 43528 | BF45: Pre-COVID | BG45: 1
A46: 43529 | B46: 58.1743 | C46: 90.682 | D46: 54.0287 | E46: 57.4276 | F46: 63.5807 | H46: 3.9793 | I46: 15.6892 | J46: 8.0708 | K46: 76.2191 | L46: 56.55 | M46: 64.24 | O46: 43529 | P46: =IF(AND(B46<>"",B45<>""),LN(B46/B45),"") -> -0.0014943886 | Q46: =IF(AND(C46<>"",C45<>""),LN(C46/C45),"") -> 0.0095345134 | R46: =IF(AND(D46<>"",D45<>""),LN(D46/D45),"") -> -0.012814393 | S46: =IF(AND(E46<>"",E45<>""),LN(E46/E45),"") -> 0.0011848012 | T46: =IF(AND(F46<>"",F45<>""),LN(F46/F45),"") -> 0.023266114 | U46: =IF(AND(G46<>"",G45<>""),LN(G46/G45),"") | V46: =IF(AND(H46<>"",H45<>""),LN(H46/H45),"") -> 0.013433887 | W46: =IF(AND(I46<>"",I45<>""),LN(I46/I45),"") -> -0.016661785 | ... Y46: =IF(AND(K46<>"",K45<>""),LN(K46/K45),"") -> 0.00011021467 | Z46: -0.001361 | AA46: =IF(AND(L46<>"",L45<>""),LN(L46/L45),"") -> -0.00088378265 | AB46: =IF(AND(M46<>"",M45<>""),LN(M46/M45),"") -> -0.0031084887 | AE46: 43529 | AF46: 14.74 | AG46: 30.21 | AH46: 45.86 | AI46: =IF(AND(M46<>"",L46<>""),M46-L46,"") -> 7.69 | AJ46: 3.18 | AK46: 17.18 | AL46: =IF(AND(AK46<>"",AJ46<>""),AK46-AJ46,"") -> 14 | AM46: 2.4 | AN46: 2.55 | AO46: 2.72 | AP46: =IF(AND(AO46<>"",AN46<>""),AO46-AN46,"") -> 0.17 | AQ46: 1.93 | AR46: 114.804 | AS46: 1282 | AT46: 254.277 | AU46: 102.8757 | AV46: 98.4 | AY46: 43529 | AZ46: 0 | BA46: 0 | BB46: 0 | BE46: 43529 | BF46: Pre-COVID | BG46: 1
A47: 43530 | B47: 57.5141 | C47: 90.8586 | D47: 53.465 | E47: 56.2881 | F47: 62.6537 | H47: 3.8673 | I47: 14.9154 | J47: 8.0168 | K47: 76.2274 | L47: 56.22 | M47: 64.51 | O47: 43530 | P47: =IF(AND(B47<>"",B46<>""),LN(B47/B46),"") -> -0.011413541 | Q47: =IF(AND(C47<>"",C46<>""),LN(C47/C46),"") -> 0.0019455709 | R47: =IF(AND(D47<>"",D46<>""),LN(D47/D46),"") -> -0.010488153 | S47: =IF(AND(E47<>"",E46<>""),LN(E47/E46),"") -> -0.020041879 | T47: =IF(AND(F47<>"",F46<>""),LN(F47/F46),"") -> -0.014687227 | U47: =IF(AND(G47<>"",G46<>""),LN(G47/G46),"") | V47: =IF(AND(H47<>"",H46<>""),LN(H47/H46),"") -> -0.028549335 | W47: =IF(AND(I47<>"",I46<>""),LN(I47/I46),"") -> -0.050578341 | ... Y47: =IF(AND(K47<>"",K46<>""),LN(K47/K46),"") -> 0.00010889066 | Z47: -0.006076 | AA47: =IF(AND(L47<>"",L46<>""),LN(L47/L46),"") -> -0.0058526371 | AB47: =IF(AND(M47<>"",M46<>""),LN(M47/M46),"") -> 0.0041941809 | AE47: 43530 | AF47: 15.74 | AG47: 29.69 | AH47: 45.63 | AI47: =IF(AND(M47<>"",L47<>""),M47-L47,"") -> 8.29 | AJ47: 3.18 | AK47: 16.85 | AL47: =IF(AND(AK47<>"",AJ47<>""),AK47-AJ47,"") -> 13.67 | AM47: 2.4 | AN47: 2.52 | AO47: 2.69 | AP47: =IF(AND(AO47<>"",AN47<>""),AO47-AN47,"") -> 0.17 | AQ47: 1.91 | AR47: 114.9714 | AS47: 1284.9 | AT47: 254.277 | AU47: 102.8757 | AV47: 98.4 | AY47: 43530 | AZ47: 0 | BA47: 0 | BB47: 0 | BE47: 43530 | BF47: Pre-COVID | BG47: 1
A48: 43531 | B48: 58.1525 | C48: 89.6891 | D48: 53.1988 | E48: 55.9054 | F48: 63.8005 | H48: 3.7376 | I48: 14.6092 | J48: 8.1086 | K48: 76.2441 | L48: 56.6 | M48: 64.82 | O48: 43531 | P48: =IF(AND(B48<>"",B47<>""),LN(B48/B47),"") -> 0.011038735 | Q48: =IF(AND(C48<>"",C47<>""),LN(C48/C47),"") -> -0.012955206 | R48: =IF(AND(D48<>"",D47<>""),LN(D48/D47),"") -> -0.0049913945 | S48: =IF(AND(E48<>"",E47<>""),LN(E48/E47),"") -> -0.0068221686 | T48: =IF(AND(F48<>"",F47<>""),LN(F48/F47),"") -> 0.018138289 | U48: =IF(AND(G48<>"",G47<>""),LN(G48/G47),"") | V48: =IF(AND(H48<>"",H47<>""),LN(H48/H47),"") -> -0.034112895 | W48: =IF(AND(I48<>"",I47<>""),LN(I48/I47),"") -> -0.020742769 | ... Y48: =IF(AND(K48<>"",K47<>""),LN(K48/K47),"") -> 0.00021905733 | Z48: -0.008401 | AA48: =IF(AND(L48<>"",L47<>""),LN(L48/L47),"") -> 0.0067364197 | AB48: =IF(AND(M48<>"",M47<>""),LN(M48/M47),"") -> 0.0047939472 | AE48: 43531 | AF48: 16.59 | AG48: 30.43 | AH48: 45.83 | AI48: =IF(AND(M48<>"",L48<>""),M48-L48,"") -> 8.22 | AJ48: 2.9 | AK48: 16.87 | AL48: =IF(AND(AK48<>"",AJ48<>""),AK48-AJ48,"") -> 13.97 | AM48: 2.4 | AN48: 2.47 | AO48: 2.64 | AP48: =IF(AND(AO48<>"",AN48<>""),AO48-AN48,"") -> 0.17 | AQ48: 1.9 | AR48: 115.4919 | AS48: 1283.8 | AT48: 254.277 | AU48: 102.8757 | AV48: 98.4 | AY48: 43531 | AZ48: 0 | BA48: 0 | BB48: 0 | BE48: 43531 | BF48: Pre-COVID | BG48: 1
A49: 43532 | B49: 57.3182 | C49: 89.4537 | D49: 51.2258 | E49: 53.969 | F49: 63.3513 | H49: 3.7317 | I49: 14.4392 | J49: 8.0006 | K49: 76.2524 | L49: 55.77 | M49: 65.66 | O49: 43532 | P49: =IF(AND(B49<>"",B48<>""),LN(B49/B48),"") -> -0.01445067 | Q49: =IF(AND(C49<>"",C48<>""),LN(C49/C48),"") -> -0.0026280725 | R49: =IF(AND(D49<>"",D48<>""),LN(D49/D48),"") -> -0.037792528 | S49: =IF(AND(E49<>"",E48<>""),LN(E49/E48),"") -> -0.035251169 | T49: =IF(AND(F49<>"",F48<>""),LN(F49/F48),"") -> -0.0070655998 | U49: =IF(AND(G49<>"",G48<>""),LN(G49/G48),"") | V49: =IF(AND(H49<>"",H48<>""),LN(H49/H48),"") -> -0.0015798003 | W49: =IF(AND(I49<>"",I48<>""),LN(I49/I48),"") -> -0.011704737 | ... Y49: =IF(AND(K49<>"",K48<>""),LN(K49/K48),"") -> 0.00010885496 | Z49: -0.002002 | AA49: =IF(AND(L49<>"",L48<>""),LN(L49/L48),"") -> -0.014772895 | AB49: =IF(AND(M49<>"",M48<>""),LN(M49/M48),"") -> 0.012875714 | AE49: 43532 | AF49: 16.05 | AG49: 29.77 | AH49: 45.83 | AI49: =IF(AND(M49<>"",L49<>""),M49-L49,"") -> 9.89 | AJ49: 2.9 | AK49: 16.73 | AL49: =IF(AND(AK49<>"",AJ49<>""),AK49-AJ49,"") -> 13.83 | AM49: 2.4 | AN49: 2.45 | AO49: 2.62 | AP49: =IF(AND(AO49<>"",AN49<>""),AO49-AN49,"") -> 0.17 | AQ49: 1.9 | AR49: 115.3599 | AS49: 1297 | AT49: 254.277 | AU49: 102.8757 | AV49: 98.4 | AY49: 43532 | AZ49: 0 | BA49: 0 | BB49: 0 | BE49: 43532 | BF49: Pre-COVID | BG49: 1
A50: 43535 | B50: 57.8768 | C50: 90.9248 | D50: 51.5703 | E50: 54.9759 | F50: 64.9855 | H50: 3.655 | I50: 15.0769 | J50: 8.1896 | K50: 76.2524 | L50: 56.79 | M50: 65.06 | O50: 43535 | P50: =IF(AND(B50<>"",B49<>""),LN(B50/B49),"") -> 0.0096984136 | Q50: =IF(AND(C50<>"",C49<>""),LN(C50/C49),"") -> 0.016311618 | R50: =IF(AND(D50<>"",D49<>""),LN(D50/D49),"") -> 0.006702614 | S50: =IF(AND(E50<>"",E49<>""),LN(E50/E49),"") -> 0.0184851 | T50: =IF(AND(F50<>"",F49<>""),LN(F50/F49),"") -> 0.025468741 | U50: =IF(AND(G50<>"",G49<>""),LN(G50/G49),"") | V50: =IF(AND(H50<>"",H49<>""),LN(H50/H49),"") -> -0.020767801 | W50: =IF(AND(I50<>"",I49<>""),LN(I50/I49),"") -> 0.043217041 | ... Y50: =IF(AND(K50<>"",K49<>""),LN(K50/K49),"") -> 0 | Z50: 0.014397 | AA50: =IF(AND(L50<>"",L49<>""),LN(L50/L49),"") -> 0.018124163 | AB50: =IF(AND(M50<>"",M49<>""),LN(M50/M49),"") -> -0.009179991 | AE50: 43535 | AF50: 14.33 | AG50: 29.18 | AH50: 44.84 | AI50: =IF(AND(M50<>"",L50<>""),M50-L50,"") -> 8.27 | AJ50: 2.86 | AK50: 16.625 | AL50: =IF(AND(AK50<>"",AJ50<>""),AK50-AJ50,"") -> 13.765 | AM50: 2.4 | AN50: 2.47 | AO50: 2.64 | AP50: =IF(AND(AO50<>"",AN50<>""),AO50-AN50,"") -> 0.17 | AQ50: 1.91 | AR50: 115.2967 | AS50: 1288.8 | AT50: 254.277 | AU50: 102.8757 | AV50: 98.4 | AY50: 43535 | AZ50: 0 | BA50: 0 | BB50: 0 | BE50: 43535 | BF50: Pre-COVID | BG50: 1
A51: 43536 | B51: 58.0364 | C51: 91.1307 | D51: 51.3824 | E51: 55.2513 | F51: 66.505 | H51: 3.8142 | I51: 15.342 | J51: 8.2166 | K51: 76.2607 | L51: 56.89 | M51: 65.33 | O51: 43536 | P51: =IF(AND(B51<>"",B50<>""),LN(B51/B50),"") -> 0.0027537865 | Q51: =IF(AND(C51<>"",C50<>""),LN(C51/C50),"") -> 0.0022619486 | R51: =IF(AND(D51<>"",D50<>""),LN(D51/D50),"") -> -0.003650224 | S51: =IF(AND(E51<>"",E50<>""),LN(E51/E50),"") -> 0.0049969621 | T51: =IF(AND(F51<>"",F50<>""),LN(F51/F50),"") -> 0.023112965 | U51: =IF(AND(G51<>"",G50<>""),LN(G51/G50),"") | V51: =IF(AND(H51<>"",H50<>""),LN(H51/H50),"") -> 0.042634851 | W51: =IF(AND(I51<>"",I50<>""),LN(I51/I50),"") -> 0.017430394 | ... Y51: =IF(AND(K51<>"",K50<>""),LN(K51/K50),"") -> 0.00010884311 | Z51: 0.003764 | AA51: =IF(AND(L51<>"",L50<>""),LN(L51/L50),"") -> 0.0017593249 | AB51: =IF(AND(M51<>"",M50<>""),LN(M51/M50),"") -> 0.0041414278 | AE51: 43536 | AF51: 13.77 | AG51: 28.56 | AH51: 44.86 | AI51: =IF(AND(M51<>"",L51<>""),M51-L51,"") -> 8.44 | AJ51: 2.83 | AK51: 16.21 | AL51: =IF(AND(AK51<>"",AJ51<>""),AK51-AJ51,"") -> 13.38 | AM51: 2.4 | AN51: 2.45 | AO51: 2.61 | AP51: =IF(AND(AO51<>"",AN51<>""),AO51-AN51,"") -> 0.16 | AQ51: 1.9 | AR51: 114.939 | AS51: 1296.3 | AT51: 254.277 | AU51: 102.8757 | AV51: 98.4 | AY51: 43536 | AZ51: 0 | BA51: 0 | BB51: 0 | BE51: 43536 | BF51: Pre-COVID | BG51: 1
A52: 43537 | B52: 58.5515 | C52: 91.6971 | D52: 52.729 | E52: 55.9914 | F52: 66.2374 | H52: 3.8496 | I52: 15.248 | J52: 8.1842 | K52: 76.2691 | L52: 58.27 | M52: 65.89 | O52: 43537 | P52: =IF(AND(B52<>"",B51<>""),LN(B52/B51),"") -> 0.0088363089 | Q52: =IF(AND(C52<>"",C51<>""),LN(C52/C51),"") -> 0.0061960141 | R52: =IF(AND(D52<>"",D51<>""),LN(D52/D51),"") -> 0.025869887 | S52: =IF(AND(E52<>"",E51<>""),LN(E52/E51),"") -> 0.013306238 | T52: =IF(AND(F52<>"",F51<>""),LN(F52/F51),"") -> -0.0040318747 | U52: =IF(AND(G52<>"",G51<>""),LN(G52/G51),"") | V52: =IF(AND(H52<>"",H51<>""),LN(H52/H51),"") -> 0.0092383026 | W52: =IF(AND(I52<>"",I51<>""),LN(I52/I51),"") -> -0.0061458186 | ... Y52: =IF(AND(K52<>"",K51<>""),LN(K52/K51),"") -> 0.00011014241 | Z52: 0.006597 | AA52: =IF(AND(L52<>"",L51<>""),LN(L52/L51),"") -> 0.023967802 | AB52: =IF(AND(M52<>"",M51<>""),LN(M52/M51),"") -> 0.0085353361 | AE52: 43537 | AF52: 13.41 | AG52: 28.13 | AH52: 44.57 | AI52: =IF(AND(M52<>"",L52<>""),M52-L52,"") -> 7.62 | AJ52: 2.87 | AK52: 15.725 | AL52: =IF(AND(AK52<>"",AJ52<>""),AK52-AJ52,"") -> 12.855 | AM52: 2.4 | AN52: 2.45 | AO52: 2.61 | AP52: =IF(AND(AO52<>"",AN52<>""),AO52-AN52,"") -> 0.16 | AQ52: 1.92 | AR52: 114.7372 | AS52: 1307.5 | AT52: 254.277 | AU52: 102.8757 | AV52: 98.4 | AY52: 43537 | AZ52: 0 | BA52: 0 | BB52: 0 | BE52: 43537 | BF52: Pre-COVID | BG52: 1
A53: 43538 | B53: 58.3556 | C53: 91.6456 | D53: 52.4707 | E53: 56.1205 | F53: 66.1227 | H53: 3.7376 | I53: 15.0342 | J53: 8.141 | K53: 76.2691 | L53: 58.59 | M53: 66.18 | O53: 43538 | P53: =IF(AND(B53<>"",B52<>""),LN(B53/B52),"") -> -0.0033513821 | Q53: =IF(AND(C53<>"",C52<>""),LN(C53/C52),"") -> -0.00056178949 | R53: =IF(AND(D53<>"",D52<>""),LN(D53/D52),"") -> -0.0049106703 | S53: =IF(AND(E53<>"",E52<>""),LN(E53/E52),"") -> 0.0023030572 | T53: =IF(AND(F53<>"",F52<>""),LN(F53/F52),"") -> -0.0017331511 | U53: =IF(AND(G53<>"",G52<>""),LN(G53/G52),"") | V53: =IF(AND(H53<>"",H52<>""),LN(H53/H52),"") -> -0.029525553 | W53: =IF(AND(I53<>"",I52<>""),LN(I53/I52),"") -> -0.014120741 | ... Y53: =IF(AND(K53<>"",K52<>""),LN(K53/K52),"") -> 0 | Z53: -0.00064 | AA53: =IF(AND(L53<>"",L52<>""),LN(L53/L52),"") -> 0.0054766524 | AB53: =IF(AND(M53<>"",M52<>""),LN(M53/M52),"") -> 0.0043916176 | AE53: 43538 | AF53: 13.5 | AG53: 27.22 | AH53: 45.24 | AI53: =IF(AND(M53<>"",L53<>""),M53-L53,"") -> 7.59 | AJ53: 2.95 | AK53: 15.605 | AL53: =IF(AND(AK53<>"",AJ53<>""),AK53-AJ53,"") -> 12.655 | AM53: 2.4 | AN53: 2.46 | AO53: 2.63 | AP53: =IF(AND(AO53<>"",AN53<>""),AO53-AN53,"") -> 0.17 | AQ53: 1.94 | AR53: 114.79 | AS53: 1293.4 | AT53: 254.277 | AU53: 102.8757 | AV53: 98.4 | AY53: 43538 | AZ53: 0 | BA53: 0 | BB53: 0 | BE53: 43538 | BF53: Pre-COVID | BG53: 1
A54: 43539 | B54: 58.1452 | C54: 92.1678 | D54: 52.9169 | E54: 56.3443 | F54: 65.836 | H54: 3.8319 | I54: 15.8979 | J54: 8.1302 | K54: 76.2774 | L54: 58.51 | M54: 66.11 | O54: 43539 | P54: =IF(AND(B54<>"",B53<>""),LN(B54/B53),"") -> -0.0036119963 | Q54: =IF(AND(C54<>"",C53<>""),LN(C54/C53),"") -> 0.0056818644 | R54: =IF(AND(D54<>"",D53<>""),LN(D54/D53),"") -> 0.00846784 | S54: =IF(AND(E54<>"",E53<>""),LN(E54/E53),"") -> 0.0039799172 | T54: =IF(AND(F54<>"",F53<>""),LN(F54/F53),"") -> -0.0043453058 | U54: =IF(AND(G54<>"",G53<>""),LN(G54/G53),"") | V54: =IF(AND(H54<>"",H53<>""),LN(H54/H53),"") -> 0.02491707 | W54: =IF(AND(I54<>"",I53<>""),LN(I54/I53),"") -> 0.055859419 | ... Y54: =IF(AND(K54<>"",K53<>""),LN(K54/K53),"") -> 0.00010881928 | Z54: 0.004928 | AA54: =IF(AND(L54<>"",L53<>""),LN(L54/L53),"") -> -0.0013663538 | AB54: =IF(AND(M54<>"",M53<>""),LN(M54/M53),"") -> -0.0010582811 | AE54: 43539 | AF54: 12.88 | AG54: 26.27 | AH54: 46.05 | AI54: =IF(AND(M54<>"",L54<>""),M54-L54,"") -> 7.6 | AJ54: 2.95 | AK54: 15.25 | AL54: =IF(AND(AK54<>"",AJ54<>""),AK54-AJ54,"") -> 12.3 | AM54: 2.4 | AN54: 2.43 | AO54: 2.59 | AP54: =IF(AND(AO54<>"",AN54<>""),AO54-AN54,"") -> 0.16 | AQ54: 1.94 | AR54: 114.5815 | AS54: 1301.8 | AT54: 254.277 | AU54: 102.8757 | AV54: 98.4 | AY54: 43539 | AZ54: 0 | BA54: 0 | BB54: 0 | BE54: 43539 | BF54: Pre-COVID | BG54: 1
... A130: 43649 | B130: 56.0894 | C130: 91.6188 | D130: 47.602 | E130: 43.0002 | F130: 66.0176 | H130: 4.6749 | I130: 25.2294 | J130: 7.9755 | K130: 76.8219 | L130: 57.06 | M130: 63.53 | O130: 43649 | P130: =IF(AND(B130<>"",B129<>""),LN(B130/B129),"") -> 0.0094635303 | Q130: =IF(AND(C130<>"",C129<>""),LN(C130/C129),"") -> 0.0034112262 | R130: =IF(AND(D130<>"",D129<>""),LN(D130/D129),"") -> 0.0066330167 | S130: =IF(AND(E130<>"",E129<>""),LN(E130/E129),"") -> 0.0079618069 | T130: =IF(AND(F130<>"",F129<>""),LN(F130/F129),"") -> -0.0057741773 | U130: =IF(AND(G130<>"",G129<>""),LN(G130/G129),"") | V130: =IF(AND(H130<>"",H129<>""),LN(H130/H129),"") -> -0.0087956185 | W130: =IF(AND(I130<>"",I129<>""),LN(I130/I129),"") -> -0.027517876 | ... Y130: =IF(AND(K130<>"",K129<>""),LN(K130/K129),"") -> 0.00032808527 | Z130: 0.007963 | AA130: =IF(AND(L130<>"",L129<>""),LN(L130/L129),"") -> 0.018751655 | AB130: =IF(AND(M130<>"",M129<>""),LN(M130/M129),"") -> 0.012831859 | AE130: 43649 | AF130: 12.57 | AG130: 36.72 | AH130: 68.33 | AI130: =IF(AND(M130<>"",L130<>""),M130-L130,"") -> 6.47 | AJ130: 2.29 | AK130: 10.295 | AL130: =IF(AND(AK130<>"",AJ130<>""),AK130-AJ130,"") -> 8.005 | AM130: 2.41 | AN130: 1.77 | AO130: 1.96 | AP130: =IF(AND(AO130<>"",AN130<>""),AO130-AN130,"") -> 0.19 | AQ130: 1.65 | AR130: 114.8135 | AS130: 1417.7 | AT130: 255.802 | AU130: 101.9408 | AV130: 98.4 | AY130: 43649 | AZ130: 0 | BA130: 0 | BB130: 0 | BE130: 43649 | BF130: Pre-COVID | BG130: 1
A131: 43651 | B131: 55.8619 | C131: 91.7599 | D131: 47.1299 | E131: 43.0964 | F131: 65.7213 | H131: 4.7339 | I131: 26.0793 | J131: 8.0415 | K131: 76.8135 | M131: 64.23 | O131: 43651 | P131: =IF(AND(B131<>"",B130<>""),LN(B131/B130),"") -> -0.0040642728 | Q131: =IF(AND(C131<>"",C130<>""),LN(C131/C130),"") -> 0.0015388922 | R131: =IF(AND(D131<>"",D130<>""),LN(D131/D130),"") -> -0.009967158 | S131: =IF(AND(E131<>"",E130<>""),LN(E131/E130),"") -> 0.0022347001 | T131: =IF(AND(F131<>"",F130<>""),LN(F131/F130),"") -> -0.0044982993 | U131: =IF(AND(G131<>"",G130<>""),LN(G131/G130),"") | V131: =IF(AND(H131<>"",H130<>""),LN(H131/H130),"") -> 0.012541615 | W131: =IF(AND(I131<>"",I130<>""),LN(I131/I130),"") -> 0.033131915 | ... Y131: =IF(AND(K131<>"",K130<>""),LN(K131/K130),"") -> -0.0001093498 | Z131: -0.001138 | AA131: =IF(AND(L131<>"",L130<>""),LN(L131/L130),"") | AB131: =IF(AND(M131<>"",M130<>""),LN(M131/M130),"") -> 0.010958156 | AE131: 43651 | AF131: 13.28 | AG131: 34.7 | AH131: 65.28 | AI131: =IF(AND(M131<>"",L131<>""),M131-L131,"") | AK131: 11.215 | AL131: =IF(AND(AK131<>"",AJ131<>""),AK131-AJ131,"") | AM131: 2.42 | AN131: 1.87 | AO131: 2.04 | AP131: =IF(AND(AO131<>"",AN131<>""),AO131-AN131,"") -> 0.17 | AQ131: 1.69 | AR131: 115.1132 | AS131: 1396.7 | AT131: 255.802 | AU131: 101.9408 | AV131: 98.4 | AY131: 43651 | AZ131: 0 | BA131: 0 | BB131: 0 | BE131: 43651 | BF131: Pre-COVID | BG131: 1
A132: 43654 | B132: 56.1188 | C132: 91.8045 | D132: 47.1221 | E132: 43.1139 | F132: 65.7309 | H132: 5.0345 | I132: 26.0106 | J132: 8.0471 | K132: 76.8135 | L132: 57.35 | M132: 64.89 | O132: 43654 | P132: =IF(AND(B132<>"",B131<>""),LN(B132/B131),"") -> 0.0045882987 | Q132: =IF(AND(C132<>"",C131<>""),LN(C132/C131),"") -> 0.00048593301 | R132: =IF(AND(D132<>"",D131<>""),LN(D132/D131),"") -> -0.00016551373 | S132: =IF(AND(E132<>"",E131<>""),LN(E132/E131),"") -> 0.00040598398 | T132: =IF(AND(F132<>"",F131<>""),LN(F132/F131),"") -> 0.0001460607 | U132: =IF(AND(G132<>"",G131<>""),LN(G132/G131),"") | V132: =IF(AND(H132<>"",H131<>""),LN(H132/H131),"") -> 0.061564829 | W132: =IF(AND(I132<>"",I131<>""),LN(I132/I131),"") -> -0.002637749 | ... Y132: =IF(AND(K132<>"",K131<>""),LN(K132/K131),"") -> 0 | Z132: -0.00551 | AA132: =IF(AND(L132<>"",L131<>""),LN(L132/L131),"") | AB132: =IF(AND(M132<>"",M131<>""),LN(M132/M131),"") -> 0.010223137 | AE132: 43654 | AF132: 13.96 | AG132: 34 | AH132: 63.22 | AI132: =IF(AND(M132<>"",L132<>""),M132-L132,"") -> 7.54 | AJ132: 2.39 | AK132: 11.88 | AL132: =IF(AND(AK132<>"",AJ132<>""),AK132-AJ132,"") -> 9.49 | AM132: 2.41 | AN132: 1.88 | AO132: 2.05 | AP132: =IF(AND(AO132<>"",AN132<>""),AO132-AN132,"") -> 0.17 | AQ132: 1.7 | AR132: 115.0254 | AS132: 1397 | AT132: 255.802 | AU132: 101.9408 | AV132: 98.4 | AY132: 43654 | AZ132: 0 | BA132: 0 | BB132: 0 | BE132: 43654 | BF132: Pre-COVID | BG132: 1
A133: 43655 | B133: 56.0821 | C133: 91.6188 | D133: 47.1221 | E133: 43.385 | F133: 65.4633 | H133: 4.7398 | I133: 25.8647 | J133: 7.9975 | K133: 76.8219 | L133: 57.57 | M133: 64.3 | O133: 43655 | P133: =IF(AND(B133<>"",B132<>""),LN(B133/B132),"") -> -0.00065418372 | Q133: =IF(AND(C133<>"",C132<>""),LN(C133/C132),"") -> -0.0020248252 | R133: =IF(AND(D133<>"",D132<>""),LN(D133/D132),"") -> 0 | S133: =IF(AND(E133<>"",E132<>""),LN(E133/E132),"") -> 0.0062683083 | T133: =IF(AND(F133<>"",F132<>""),LN(F133/F132),"") -> -0.0040794543 | U133: =IF(AND(G133<>"",G132<>""),LN(G133/G132),"") | V133: =IF(AND(H133<>"",H132<>""),LN(H133/H132),"") -> -0.060319276 | W133: =IF(AND(I133<>"",I132<>""),LN(I133/I132),"") -> -0.0056250425 | ... Y133: =IF(AND(K133<>"",K132<>""),LN(K133/K132),"") -> 0.0001093498 | Z133: 0.001246 | AA133: =IF(AND(L133<>"",L132<>""),LN(L133/L132),"") -> 0.0038287551 | AB133: =IF(AND(M133<>"",M132<>""),LN(M133/M132),"") -> -0.0091338974 | AE133: 43655 | AF133: 14.09 | AG133: 30.3 | AH133: 62.9 | AI133: =IF(AND(M133<>"",L133<>""),M133-L133,"") -> 6.73 | AJ133: 2.41 | AK133: 11.76 | AL133: =IF(AND(AK133<>"",AJ133<>""),AK133-AJ133,"") -> 9.35 | AM133: 2.41 | AN133: 1.92 | AO133: 2.07 | AP133: =IF(AND(AO133<>"",AN133<>""),AO133-AN133,"") -> 0.15 | AQ133: 1.71 | AR133: 115.1017 | AS133: 1397.5 | AT133: 255.802 | AU133: 101.9408 | AV133: 98.4 | AY133: 43655 | AZ133: 0 | BA133: 0 | BB133: 0 | BE133: 43655 | BF133: Pre-COVID | BG133: 1
A134: 43656 | B134: 56.8746 | C134: 93.1712 | D134: 48.1606 | E134: 43.936 | F134: 65.6258 | H134: 4.8164 | I134: 25.9076 | J134: 8.0966 | K134: 76.8303 | L134: 60.28 | M134: 66.41 | O134: 43656 | P134: =IF(AND(B134<>"",B133<>""),LN(B134/B133),"") -> 0.014032156 | Q134: =IF(AND(C134<>"",C133<>""),LN(C134/C133),"") -> 0.01680217 | R134: =IF(AND(D134<>"",D133<>""),LN(D134/D133),"") -> 0.021799154 | S134: =IF(AND(E134<>"",E133<>""),LN(E134/E133),"") -> 0.01262027 | T134: =IF(AND(F134<>"",F133<>""),LN(F134/F133),"") -> 0.002479231 | U134: =IF(AND(G134<>"",G133<>""),LN(G134/G133),"") | V134: =IF(AND(H134<>"",H133<>""),LN(H134/H133),"") -> 0.01603182 | W134: =IF(AND(I134<>"",I133<>""),LN(I134/I133),"") -> 0.0016572573 | ... Y134: =IF(AND(K134<>"",K133<>""),LN(K134/K133),"") -> 0.00010933784 | Z134: 0.004767 | AA134: =IF(AND(L134<>"",L133<>""),LN(L134/L133),"") -> 0.045998775 | AB134: =IF(AND(M134<>"",M133<>""),LN(M134/M133),"") -> 0.032288016 | AE134: 43656 | AF134: 13.03 | AG134: 30.76 | AH134: 62.39 | AI134: =IF(AND(M134<>"",L134<>""),M134-L134,"") -> 6.13 | AJ134: 2.49 | AK134: 12.135 | AL134: =IF(AND(AK134<>"",AJ134<>""),AK134-AJ134,"") -> 9.645 | AM134: 2.41 | AN134: 1.82 | AO134: 2.07 | AP134: =IF(AND(AO134<>"",AN134<>""),AO134-AN134,"") -> 0.25 | AQ134: 1.74 | AR134: 115.0879 | AS134: 1410.1 | AT134: 255.802 | AU134: 101.9408 | AV134: 98.4 | AY134: 43656 | AZ134: 0 | BA134: 0 | BB134: 0 | BE134: 43656 | BF134: Pre-COVID | BG134: 1
A135: 43657 | B135: 56.9186 | C135: 93.1637 | D135: 48.3574 | E135: 44.1109 | F135: 65.9985 | H135: 4.781 | I135: 25.7016 | J135: 8.1242 | K135: 76.8471 | L135: 59.93 | M135: 67.64 | O135: 43657 | P135: =IF(AND(B135<>"",B134<>""),LN(B135/B134),"") -> 0.00077333272 | Q135: =IF(AND(C135<>"",C134<>""),LN(C135/C134),"") -> -8.0500218e-05 | R135: =IF(AND(D135<>"",D134<>""),LN(D135/D134),"") -> 0.0040780015 | S135: =IF(AND(E135<>"",E134<>""),LN(E135/E134),"") -> 0.0039728879 | T135: =IF(AND(F135<>"",F134<>""),LN(F135/F134),"") -> 0.0056631032 | U135: =IF(AND(G135<>"",G134<>""),LN(G135/G134),"") | V135: =IF(AND(H135<>"",H134<>""),LN(H135/H134),"") -> -0.0073770314 | W135: =IF(AND(I135<>"",I134<>""),LN(I135/I134),"") -> -0.0079831152 | ... Y135: =IF(AND(K135<>"",K134<>""),LN(K135/K134),"") -> 0.00021863983 | Z135: 0.002342 | AA135: =IF(AND(L135<>"",L134<>""),LN(L135/L134),"") -> -0.0058231593 | AB135: =IF(AND(M135<>"",M134<>""),LN(M135/M134),"") -> 0.018351876 | AE135: 43657 | AF135: 12.93 | AG135: 29.86 | AH135: 62.96 | AI135: =IF(AND(M135<>"",L135<>""),M135-L135,"") -> 7.71 | AJ135: 2.54 | AK135: 13.13 | AL135: =IF(AND(AK135<>"",AJ135<>""),AK135-AJ135,"") -> 10.59 | AM135: 2.4 | AN135: 1.85 | AO135: 2.13 | AP135: =IF(AND(AO135<>"",AN135<>""),AO135-AN135,"") -> 0.28 | AQ135: 1.77 | AR135: 114.8361 | AS135: 1404.3 | AT135: 255.802 | AU135: 101.9408 | AV135: 98.4 | AY135: 43657 | AZ135: 0 | BA135: 0 | BB135: 0 | BE135: 43657 | BF135: Pre-COVID | BG135: 1
A136: 43658 | B136: 56.9626 | C136: 93.5723 | D136: 48.5934 | E136: 45.2303 | F136: 66.419 | H136: 4.7398 | I136: 25.3324 | J136: 8.1627 | K136: 76.8555 | L136: 59.99 | M136: 66.65 | O136: 43658 | P136: =IF(AND(B136<>"",B135<>""),LN(B136/B135),"") -> 0.00077273513 | Q136: =IF(AND(C136<>"",C135<>""),LN(C136/C135),"") -> 0.0043762387 | R136: =IF(AND(D136<>"",D135<>""),LN(D136/D135),"") -> 0.0048684584 | S136: =IF(AND(E136<>"",E135<>""),LN(E136/E135),"") -> 0.025060299 | T136: =IF(AND(F136<>"",F135<>""),LN(F136/F135),"") -> 0.0063511456 | U136: =IF(AND(G136<>"",G135<>""),LN(G136/G135),"") | V136: =IF(AND(H136<>"",H135<>""),LN(H136/H135),"") -> -0.0086547889 | W136: =IF(AND(I136<>"",I135<>""),LN(I136/I135),"") -> -0.014469038 | ... Y136: =IF(AND(K136<>"",K135<>""),LN(K136/K135),"") -> 0.00010930199 | Z136: 0.004467 | AA136: =IF(AND(L136<>"",L135<>""),LN(L136/L135),"") -> 0.0010006672 | AB136: =IF(AND(M136<>"",M135<>""),LN(M136/M135),"") -> -0.014744477 | AE136: 43658 | AF136: 12.39 | AG136: 30.39 | AH136: 62.78 | AI136: =IF(AND(M136<>"",L136<>""),M136-L136,"") -> 6.66 | AJ136: 2.54 | AK136: 13.28 | AL136: =IF(AND(AK136<>"",AJ136<>""),AK136-AJ136,"") -> 10.74 | AM136: 2.38 | AN136: 1.84 | AO136: 2.12 | AP136: =IF(AND(AO136<>"",AN136<>""),AO136-AN136,"") -> 0.28 | AQ136: 1.77 | AR136: 114.7685 | AS136: 1409.9 | AT136: 255.802 | AU136: 101.9408 | AV136: 98.4 | AY136: 43658 | AZ136: 0 | BA136: 0 | BB136: 0 | BE136: 43658 | BF136: Pre-COVID | BG136: 1
A137: 43661 | B137: 56.559 | C137: 93.3791 | D137: 47.72 | E137: 45.1516 | F137: 65.4442 | H137: 4.6926 | I137: 24.3281 | J137: 8.2123 | K137: 76.8555 | L137: 59.3 | M137: 66.86 | O137: 43661 | P137: =IF(AND(B137<>"",B136<>""),LN(B137/B136),"") -> -0.007110571 | Q137: =IF(AND(C137<>"",C136<>""),LN(C137/C136),"") -> -0.0020668481 | R137: =IF(AND(D137<>"",D136<>""),LN(D137/D136),"") -> -0.018137122 | S137: =IF(AND(E137<>"",E136<>""),LN(E137/E136),"") -> -0.0017414996 | T137: =IF(AND(F137<>"",F136<>""),LN(F137/F136),"") -> -0.014785289 | U137: =IF(AND(G137<>"",G136<>""),LN(G137/G136),"") | V137: =IF(AND(H137<>"",H136<>""),LN(H137/H136),"") -> -0.010008141 | W137: =IF(AND(I137<>"",I136<>""),LN(I137/I136),"") -> -0.040452148 | ... Y137: =IF(AND(K137<>"",K136<>""),LN(K137/K136),"") -> 0 | Z137: 0.000332 | AA137: =IF(AND(L137<>"",L136<>""),LN(L137/L136),"") -> -0.011568576 | AB137: =IF(AND(M137<>"",M136<>""),LN(M137/M136),"") -> 0.0031458344 | AE137: 43661 | AF137: 12.68 | AG137: 30.83 | AH137: 61.9 | AI137: =IF(AND(M137<>"",L137<>""),M137-L137,"") -> 7.56 | AJ137: 2.53 | AK137: 12.895 | AL137: =IF(AND(AK137<>"",AJ137<>""),AK137-AJ137,"") -> 10.365 | AM137: 2.4 | AN137: 1.83 | AO137: 2.09 | AP137: =IF(AND(AO137<>"",AN137<>""),AO137-AN137,"") -> 0.26 | AQ137: 1.77 | AR137: 114.6819 | AS137: 1411.4 | AT137: 255.802 | AU137: 101.9408 | AV137: 98.4 | AY137: 43661 | AZ137: 0 | BA137: 0 | BB137: 0 | BE137: 43661 | BF137: Pre-COVID | BG137: 1
A138: 43662 | B138: 55.7152 | C138: 92.6661 | D138: 47.0119 | E138: 44.6881 | F138: 64.737 | H138: 4.9048 | I138: 25.238 | J138: 8.2343 | K138: 76.8639 | L138: 57.44 | M138: 65.87 | O138: 43662 | P138: =IF(AND(B138<>"",B137<>""),LN(B138/B137),"") -> -0.015031341 | Q138: =IF(AND(C138<>"",C137<>""),LN(C138/C137),"") -> -0.0076648416 | R138: =IF(AND(D138<>"",D137<>""),LN(D138/D137),"") -> -0.014949836 | S138: =IF(AND(E138<>"",E137<>""),LN(E138/E137),"") -> -0.01031847 | T138: =IF(AND(F138<>"",F137<>""),LN(F138/F137),"") -> -0.010864963 | U138: =IF(AND(G138<>"",G137<>""),LN(G138/G137),"") | V138: =IF(AND(H138<>"",H137<>""),LN(H138/H137),"") -> 0.044227518 | W138: =IF(AND(I138<>"",I137<>""),LN(I138/I137),"") -> 0.036718734 | ... Y138: =IF(AND(K138<>"",K137<>""),LN(K138/K137),"") -> 0.00010929004 | Z138: -0.00323 | AA138: =IF(AND(L138<>"",L137<>""),LN(L138/L137),"") -> -0.031868381 | AB138: =IF(AND(M138<>"",M137<>""),LN(M138/M137),"") -> -0.014917778 | AE138: 43662 | AF138: 12.86 | AG138: 32.06 | AH138: 61.29 | AI138: =IF(AND(M138<>"",L138<>""),M138-L138,"") -> 8.43 | AJ138: 2.53 | AK138: 11.415 | AL138: =IF(AND(AK138<>"",AJ138<>""),AK138-AJ138,"") -> 8.885 | AM138: 2.41 | AN138: 1.87 | AO138: 2.13 | AP138: =IF(AND(AO138<>"",AN138<>""),AO138-AN138,"") -> 0.26 | AQ138: 1.8 | AR138: 115.0111 | AS138: 1409.2 | AT138: 255.802 | AU138: 101.9408 | AV138: 98.4 | AY138: 43662 | AZ138: 0 | BA138: 0 | BB138: 0 | BE138: 43662 | BF138: Pre-COVID | BG138: 1
A139: 43663 | B139: 55.385 | C139: 92.2056 | D139: 47.0355 | E139: 44.758 | F139: 63.208 | H139: 4.7751 | I139: 24.577 | J139: 8.2949 | K139: 76.8639 | L139: 56.5 | M139: 63.67 | O139: 43663 | P139: =IF(AND(B139<>"",B138<>""),LN(B139/B138),"") -> -0.0059442012 | Q139: =IF(AND(C139<>"",C138<>""),LN(C139/C138),"") -> -0.0049818437 | R139: =IF(AND(D139<>"",D138<>""),LN(D139/D138),"") -> 0.0005018746 | S139: =IF(AND(E139<>"",E138<>""),LN(E139/E138),"") -> 0.0015629528 | T139: =IF(AND(F139<>"",F138<>""),LN(F139/F138),"") -> -0.023902033 | U139: =IF(AND(G139<>"",G138<>""),LN(G139/G138),"") | V139: =IF(AND(H139<>"",H138<>""),LN(H139/H138),"") -> -0.026799401 | W139: =IF(AND(I139<>"",I138<>""),LN(I139/I138),"") -> -0.026539749 | ... Y139: =IF(AND(K139<>"",K138<>""),LN(K139/K138),"") -> 0 | Z139: -0.006829 | AA139: =IF(AND(L139<>"",L138<>""),LN(L139/L138),"") -> -0.016500287 | AB139: =IF(AND(M139<>"",M138<>""),LN(M139/M138),"") -> -0.033969609 | AE139: 43663 | AF139: 13.97 | AG139: 34.94 | AH139: 62.29 | AI139: =IF(AND(M139<>"",L139<>""),M139-L139,"") -> 7.17 | AJ139: 2.44 | AK139: 10.99 | AL139: =IF(AND(AK139<>"",AJ139<>""),AK139-AJ139,"") -> 8.55 | AM139: 2.41 | AN139: 1.83 | AO139: 2.06 | AP139: =IF(AND(AO139<>"",AN139<>""),AO139-AN139,"") -> 0.23 | AQ139: 1.75 | AR139: 114.8819 | AS139: 1421.3 | AT139: 255.802 | AU139: 101.9408 | AV139: 98.4 | AY139: 43663 | AZ139: 0 | BA139: 0 | BB139: 0 | BE139: 43663 | BF139: Pre-COVID | BG139: 1
A140: 43664 | B140: 54.9154 | C140: 92.6067 | D140: 47.4604 | E140: 44.6094 | F140: 64.2401 | H140: 4.557 | I140: 24.5684 | J140: 8.2453 | K140: 76.8891 | L140: 55.08 | M140: 60.7 | O140: 43664 | P140: =IF(AND(B140<>"",B139<>""),LN(B140/B139),"") -> -0.0085149798 | Q140: =IF(AND(C140<>"",C139<>""),LN(C140/C139),"") -> 0.004340627 | R140: =IF(AND(D140<>"",D139<>""),LN(D140/D139),"") -> 0.0089930434 | S140: =IF(AND(E140<>"",E139<>""),LN(E140/E139),"") -> -0.0033256005 | T140: =IF(AND(F140<>"",F139<>""),LN(F140/F139),"") -> 0.016196751 | U140: =IF(AND(G140<>"",G139<>""),LN(G140/G139),"") | V140: =IF(AND(H140<>"",H139<>""),LN(H140/H139),"") -> -0.046750404 | W140: =IF(AND(I140<>"",I139<>""),LN(I140/I139),"") -> -0.00034998189 | ... Y140: =IF(AND(K140<>"",K139<>""),LN(K140/K139),"") -> 0.00032779848 | Z140: 0.003654 | AA140: =IF(AND(L140<>"",L139<>""),LN(L140/L139),"") -> -0.025453964 | AB140: =IF(AND(M140<>"",M139<>""),LN(M140/M139),"") -> -0.047769796 | AE140: 43664 | AF140: 13.53 | AG140: 33.07 | AH140: 63.12 | AI140: =IF(AND(M140<>"",L140<>""),M140-L140,"") -> 5.62 | AJ140: 2.38 | AK140: 10.735 | AL140: =IF(AND(AK140<>"",AJ140<>""),AK140-AJ140,"") -> 8.355 | AM140: 2.41 | AN140: 1.77 | AO140: 2.04 | AP140: =IF(AND(AO140<>"",AN140<>""),AO140-AN140,"") -> 0.27 | AQ140: 1.79 | AR140: 114.8744 | AS140: 1426.1 | AT140: 255.802 | AU140: 101.9408 | AV140: 98.4 | AY140: 43664 | AZ140: 0 | BA140: 0 | BB140: 0 | BE140: 43664 | BF140: Pre-COVID | BG140: 1
A141: 43665 | B141: 55.0255 | C141: 92.8741 | D141: 47.7095 | E141: 45.7637 | F141: 64.0394 | H141: 4.5865 | I141: 23.8988 | J141: 8.3169 | K141: 76.8891 | L141: 55.42 | M141: 61.04 | O141: 43665 | P141: =IF(AND(B141<>"",B140<>""),LN(B141/B140),"") -> 0.002002895 | Q141: =IF(AND(C141<>"",C140<>""),LN(C141/C140),"") -> 0.0028833193 | R141: =IF(AND(D141<>"",D140<>""),LN(D141/D140),"") -> 0.0052348604 | S141: =IF(AND(E141<>"",E140<>""),LN(E141/E140),"") -> 0.025546601 | T141: =IF(AND(F141<>"",F140<>""),LN(F141/F140),"") -> -0.0031291074 | U141: =IF(AND(G141<>"",G140<>""),LN(G141/G140),"") | V141: =IF(AND(H141<>"",H140<>""),LN(H141/H140),"") -> 0.0064526937 | W141: =IF(AND(I141<>"",I140<>""),LN(I141/I140),"") -> -0.027632816 | ... Y141: =IF(AND(K141<>"",K140<>""),LN(K141/K140),"") -> 0 | Z141: -0.005571 | AA141: =IF(AND(L141<>"",L140<>""),LN(L141/L140),"") -> 0.0061538656 | AB141: =IF(AND(M141<>"",M140<>""),LN(M141/M140),"") -> 0.0055856889 | AE141: 43665 | AF141: 14.45 | AG141: 34.84 | AH141: 63.86 | AI141: =IF(AND(M141<>"",L141<>""),M141-L141,"") -> 5.62 | AJ141: 2.3 | AK141: 10.815 | AL141: =IF(AND(AK141<>"",AJ141<>""),AK141-AJ141,"") -> 8.515 | AM141: 2.41 | AN141: 1.8 | AO141: 2.05 | AP141: =IF(AND(AO141<>"",AN141<>""),AO141-AN141,"") -> 0.25 | AQ141: 1.8 | AR141: 114.8695 | AS141: 1425.1 | AT141: 255.802 | AU141: 101.9408 | AV141: 98.4 | AY141: 43665 | AZ141: 0 | BA141: 0 | BB141: 0 | BE141: 43665 | BF141: Pre-COVID | BG141: 1
A142: 43668 | B142: 55.0842 | C142: 93.0746 | D142: 47.7965 | E142: 45.9211 | F142: 64.3069 | H142: 4.6749 | I142: 24.1392 | J142: 8.3004 | K142: 76.8891 | L142: 55.87 | M142: 61.96 | O142: 43668 | P142: =IF(AND(B142<>"",B141<>""),LN(B142/B141),"") -> 0.0010662095 | Q142: =IF(AND(C142<>"",C141<>""),LN(C142/C141),"") -> 0.0021565096 | R142: =IF(AND(D142<>"",D141<>""),LN(D142/D141),"") -> 0.0018218756 | S142: =IF(AND(E142<>"",E141<>""),LN(E142/E141),"") -> 0.003433506 | T142: =IF(AND(F142<>"",F141<>""),LN(F142/F141),"") -> 0.004168416 | U142: =IF(AND(G142<>"",G141<>""),LN(G142/G141),"") | V142: =IF(AND(H142<>"",H141<>""),LN(H142/H141),"") -> 0.019090566 | W142: =IF(AND(I142<>"",I141<>""),LN(I142/I141),"") -> 0.010008827 | ... Y142: =IF(AND(K142<>"",K141<>""),LN(K142/K141),"") -> 0 | Z142: 0.002454 | AA142: =IF(AND(L142<>"",L141<>""),LN(L142/L141),"") -> 0.008087024 | AB142: =IF(AND(M142<>"",M141<>""),LN(M142/M141),"") -> 0.014959629 | AE142: 43668 | AF142: 13.53 | AG142: 33.63 | AH142: 60.97 | AI142: =IF(AND(M142<>"",L142<>""),M142-L142,"") -> 6.09 | AJ142: 2.33 | AK142: 10.16 | AL142: =IF(AND(AK142<>"",AJ142<>""),AK142-AJ142,"") -> 7.83 | AM142: 2.4 | AN142: 1.8 | AO142: 2.05 | AP142: =IF(AND(AO142<>"",AN142<>""),AO142-AN142,"") -> 0.25 | AQ142: 1.79 | AR142: 115.0018 | AS142: 1425.3 | AT142: 255.802 | AU142: 101.9408 | AV142: 98.4 | AY142: 43668 | AZ142: 0 | BA142: 0 | BB142: 0 | BE142: 43668 | BF142: Pre-COVID | BG142: 1
A143: 43669 | B143: 55.3043 | C143: 93.4534 | D143: 47.67 | E143: 45.3002 | F143: 63.3417 | H143: 4.728 | I143: 24.1821 | J143: 8.2453 | K143: 76.8807 | L143: 56.58 | M143: 62.28 | O143: 43669 | P143: =IF(AND(B143<>"",B142<>""),LN(B143/B142),"") -> 0.0039877395 | Q143: =IF(AND(C143<>"",C142<>""),LN(C143/C142),"") -> 0.0040615942 | R143: =IF(AND(D143<>"",D142<>""),LN(D143/D142),"") -> -0.0026501458 | S143: =IF(AND(E143<>"",E142<>""),LN(E143/E142),"") -> -0.013613259 | T143: =IF(AND(F143<>"",F142<>""),LN(F143/F142),"") -> -0.015123055 | U143: =IF(AND(G143<>"",G142<>""),LN(G143/G142),"") | V143: =IF(AND(H143<>"",H142<>""),LN(H143/H142),"") -> 0.011294508 | W143: =IF(AND(I143<>"",I142<>""),LN(I143/I142),"") -> 0.0017756149 | ... Y143: =IF(AND(K143<>"",K142<>""),LN(K143/K142),"") -> -0.00010925422 | Z143: 0.007125 | AA143: =IF(AND(L143<>"",L142<>""),LN(L143/L142),"") -> 0.012628002 | AB143: =IF(AND(M143<>"",M142<>""),LN(M143/M142),"") -> 0.0051513314 | AE143: 43669 | AF143: 12.61 | AG143: 32.25 | AH143: 61.23 | AI143: =IF(AND(M143<>"",L143<>""),M143-L143,"") -> 5.7 | AJ143: 2.34 | AK143: 10.75 | AL143: =IF(AND(AK143<>"",AJ143<>""),AK143-AJ143,"") -> 8.41 | AM143: 2.4 | AN143: 1.83 | AO143: 2.08 | AP143: =IF(AND(AO143<>"",AN143<>""),AO143-AN143,"") -> 0.25 | AQ143: 1.81 | AR143: 115.2995 | AS143: 1420.1 | AT143: 255.802 | AU143: 101.9408 | AV143: 98.4 | AY143: 43669 | AZ143: 0 | BA143: 0 | BB143: 0 | BE143: 43669 | BF143: Pre-COVID | BG143: 1
... A200: 43749 | B200: 51.2448 | C200: 87.1578 | D200: 44.6253 | E200: 36.5963 | F200: 59.8822 | H200: 6.7382 | I200: 29.9234 | J200: 7.0761 | K200: 77.2428 | L200: 54.76 | M200: 60.59 | O200: 43749 | P200: =IF(AND(B200<>"",B199<>""),LN(B200/B199),"") -> 0.01063893 | Q200: =IF(AND(C200<>"",C199<>""),LN(C200/C199),"") -> 0.013521821 | R200: =IF(AND(D200<>"",D199<>""),LN(D200/D199),"") -> 0.0097933918 | S200: =IF(AND(E200<>"",E199<>""),LN(E200/E199),"") -> 0.0021911447 | T200: =IF(AND(F200<>"",F199<>""),LN(F200/F199),"") -> 0.021291422 | U200: =IF(AND(G200<>"",G199<>""),LN(G200/G199),"") | V200: =IF(AND(H200<>"",H199<>""),LN(H200/H199),"") -> 0.021208144 | W200: =IF(AND(I200<>"",I199<>""),LN(I200/I199),"") -> 0.011870304 | ... Y200: =IF(AND(K200<>"",K199<>""),LN(K200/K199),"") -> 0.00011004867 | Z200: 0.010314 | AA200: =IF(AND(L200<>"",L199<>""),LN(L200/L199),"") -> 0.021970791 | AB200: =IF(AND(M200<>"",M199<>""),LN(M200/M199),"") -> 0.025237405 | AE200: 43749 | AF200: 15.58 | AG200: 39.65 | AH200: 79.86 | AI200: =IF(AND(M200<>"",L200<>""),M200-L200,"") -> 5.83 | AJ200: 2.13 | AK200: 16.135 | AL200: =IF(AND(AK200<>"",AJ200<>""),AK200-AJ200,"") -> 14.005 | AM200: 1.82 | AN200: 1.63 | AO200: 1.76 | AP200: =IF(AND(AO200<>"",AN200<>""),AO200-AN200,"") -> 0.13 | AQ200: 1.56 | AR200: 116.8239 | AS200: 1482.7 | AT200: 257.155 | AU200: 101.4281 | AV200: 95.5 | AY200: 43749 | AZ200: 0 | BA200: 0 | BB200: 0 | BE200: 43749 | BF200: Pre-COVID | BG200: 1
A201: 43752 | B201: 51.3934 | C201: 87.1804 | D201: 44.3881 | E201: 36.0534 | F201: 60.102 | H201: 6.9033 | I201: 31.026 | J201: 7.0198 | K201: 77.2343 | L201: 53.57 | M201: 58.81 | O201: 43752 | P201: =IF(AND(B201<>"",B200<>""),LN(B201/B200),"") -> 0.0028956101 | Q201: =IF(AND(C201<>"",C200<>""),LN(C201/C200),"") -> 0.00025926619 | R201: =IF(AND(D201<>"",D200<>""),LN(D201/D200),"") -> -0.0053295473 | S201: =IF(AND(E201<>"",E200<>""),LN(E201/E200),"") -> -0.01494597 | T201: =IF(AND(F201<>"",F200<>""),LN(F201/F200),"") -> 0.0036638198 | U201: =IF(AND(G201<>"",G200<>""),LN(G201/G200),"") | V201: =IF(AND(H201<>"",H200<>""),LN(H201/H200),"") -> 0.024206731 | W201: =IF(AND(I201<>"",I200<>""),LN(I201/I200),"") -> 0.03618478 | ... Y201: =IF(AND(K201<>"",K200<>""),LN(K201/K200),"") -> -0.00011004867 | Z201: -0.001115 | AA201: =IF(AND(L201<>"",L200<>""),LN(L201/L200),"") -> -0.021970791 | AB201: =IF(AND(M201<>"",M200<>""),LN(M201/M200),"") -> -0.029817954 | AE201: 43752 | AF201: 14.57 | AG201: 40.21 | AI201: =IF(AND(M201<>"",L201<>""),M201-L201,"") -> 5.24 | AJ201: 2.13 | AK201: 16.04 | AL201: =IF(AND(AK201<>"",AJ201<>""),AK201-AJ201,"") -> 13.91 | AM201: 1.82 | AP201: =IF(AND(AO201<>"",AN201<>""),AO201-AN201,"") | AS201: 1491.7 | AT201: 257.155 | AU201: 101.4281 | AV201: 95.5 | AY201: 43752 | AZ201: 0 | BA201: 0 | BB201: 0 | BE201: 43752 | BF201: Pre-COVID | BG201: 1
A202: 43753 | B202: 51.5717 | C202: 87.2779 | D202: 44.2458 | E202: 36.3115 | F202: 60.2071 | H202: 6.3433 | I202: 30.4489 | J202: 7.031 | K202: 77.2428 | L202: 52.81 | M202: 59.19 | O202: 43753 | P202: =IF(AND(B202<>"",B201<>""),LN(B202/B201),"") -> 0.0034633129 | Q202: =IF(AND(C202<>"",C201<>""),LN(C202/C201),"") -> 0.0011177457 | R202: =IF(AND(D202<>"",D201<>""),LN(D202/D201),"") -> -0.0032109638 | S202: =IF(AND(E202<>"",E201<>""),LN(E202/E201),"") -> 0.0071333228 | T202: =IF(AND(F202<>"",F201<>""),LN(F202/F201),"") -> 0.0017471667 | U202: =IF(AND(G202<>"",G201<>""),LN(G202/G201),"") | V202: =IF(AND(H202<>"",H201<>""),LN(H202/H201),"") -> -0.08460042 | W202: =IF(AND(I202<>"",I201<>""),LN(I202/I201),"") -> -0.018775694 | ... Y202: =IF(AND(K202<>"",K201<>""),LN(K202/K201),"") -> 0.00011004867 | Z202: 0.009852 | AA202: =IF(AND(L202<>"",L201<>""),LN(L202/L201),"") -> -0.014288643 | AB202: =IF(AND(M202<>"",M201<>""),LN(M202/M201),"") -> 0.0064407002 | AE202: 43753 | AF202: 13.54 | AG202: 39.47 | AH202: 80.06 | AI202: =IF(AND(M202<>"",L202<>""),M202-L202,"") -> 6.38 | AJ202: 2.29 | AK202: 16.065 | AL202: =IF(AND(AK202<>"",AJ202<>""),AK202-AJ202,"") -> 13.775 | AM202: 1.9 | AN202: 1.61 | AO202: 1.77 | AP202: =IF(AND(AO202<>"",AN202<>""),AO202-AN202,"") -> 0.16 | AQ202: 1.56 | AR202: 116.8111 | AS202: 1477.6 | AT202: 257.155 | AU202: 101.4281 | AV202: 95.5 | AY202: 43753 | AZ202: 0 | BA202: 0 | BB202: 0 | BE202: 43753 | BF202: Pre-COVID | BG202: 1
A203: 43754 | B203: 50.6877 | C203: 86.3774 | D203: 43.5127 | E203: 35.9021 | F203: 59.6911 | H203: 6.2312 | I203: 30.3369 | J203: 7.0648 | K203: 77.2512 | L203: 53.42 | M203: 59.3 | O203: 43754 | P203: =IF(AND(B203<>"",B202<>""),LN(B203/B202),"") -> -0.017289795 | Q203: =IF(AND(C203<>"",C202<>""),LN(C203/C202),"") -> -0.010371213 | R203: =IF(AND(D203<>"",D202<>""),LN(D203/D202),"") -> -0.016707602 | S203: =IF(AND(E203<>"",E202<>""),LN(E203/E202),"") -> -0.011338706 | T203: =IF(AND(F203<>"",F202<>""),LN(F203/F202),"") -> -0.008607355 | U203: =IF(AND(G203<>"",G202<>""),LN(G203/G202),"") | V203: =IF(AND(H203<>"",H202<>""),LN(H203/H202),"") -> -0.017830207 | W203: =IF(AND(I203<>"",I202<>""),LN(I203/I202),"") -> -0.0036850754 | ... Y203: =IF(AND(K203<>"",K202<>""),LN(K203/K202),"") -> 0.00010874209 | Z203: -0.001607 | AA203: =IF(AND(L203<>"",L202<>""),LN(L203/L202),"") -> 0.011484641 | AB203: =IF(AND(M203<>"",M202<>""),LN(M203/M202),"") -> 0.0018566973 | AE203: 43754 | AF203: 13.68 | AG203: 39.47 | AH203: 77.94 | AI203: =IF(AND(M203<>"",L203<>""),M203-L203,"") -> 5.88 | AJ203: 2.44 | AK203: 16.075 | AL203: =IF(AND(AK203<>"",AJ203<>""),AK203-AJ203,"") -> 13.635 | AM203: 1.9 | AN203: 1.58 | AO203: 1.75 | AP203: =IF(AND(AO203<>"",AN203<>""),AO203-AN203,"") -> 0.17 | AQ203: 1.57 | AR203: 116.6425 | AS203: 1488 | AT203: 257.155 | AU203: 101.4281 | AV203: 95.5 | AY203: 43754 | AZ203: 0 | BA203: 0 | BB203: 0 | BE203: 43754 | BF203: Pre-COVID | BG203: 1
A204: 43755 | B204: 50.6208 | C204: 86.5575 | D204: 43.449 | E204: 35.8932 | F204: 59.6529 | H204: 6.3904 | I204: 30.6125 | J204: 7.0704 | K204: 77.2596 | L204: 53.89 | M204: 59.35 | O204: 43755 | P204: =IF(AND(B204<>"",B203<>""),LN(B204/B203),"") -> -0.0013207186 | Q204: =IF(AND(C204<>"",C203<>""),LN(C204/C203),"") -> 0.0020828655 | R204: =IF(AND(D204<>"",D203<>""),LN(D204/D203),"") -> -0.001465013 | S204: =IF(AND(E204<>"",E203<>""),LN(E204/E203),"") -> -0.00024792709 | T204: =IF(AND(F204<>"",F203<>""),LN(F204/F203),"") -> -0.00064016626 | U204: =IF(AND(G204<>"",G203<>""),LN(G204/G203),"") | V204: =IF(AND(H204<>"",H203<>""),LN(H204/H203),"") -> 0.025227934 | W204: =IF(AND(I204<>"",I203<>""),LN(I204/I203),"") -> 0.0090436289 | ... Y204: =IF(AND(K204<>"",K203<>""),LN(K204/K203),"") -> 0.00010873026 | Z204: 0.002945 | AA204: =IF(AND(L204<>"",L203<>""),LN(L204/L203),"") -> 0.0087597243 | AB204: =IF(AND(M204<>"",M203<>""),LN(M204/M203),"") -> 0.00084281505 | AE204: 43755 | AF204: 13.79 | AG204: 37.71 | AH204: 77.61 | AI204: =IF(AND(M204<>"",L204<>""),M204-L204,"") -> 5.46 | AJ204: 2.29 | AK204: 16.025 | AL204: =IF(AND(AK204<>"",AJ204<>""),AK204-AJ204,"") -> 13.735 | AM204: 1.85 | AN204: 1.6 | AO204: 1.76 | AP204: =IF(AND(AO204<>"",AN204<>""),AO204-AN204,"") -> 0.16 | AQ204: 1.59 | AR204: 116.2615 | AS204: 1492.3 | AT204: 257.155 | AU204: 101.4281 | AV204: 95.5 | AY204: 43755 | AZ204: 0 | BA204: 0 | BB204: 0 | BE204: 43755 | BF204: Pre-COVID | BG204: 1
A205: 43756 | B205: 50.2271 | C205: 86.0998 | D205: 42.9868 | E205: 36 | F205: 59.7771 | H205: 6.2961 | I205: 30.0354 | J205: 7.1718 | K205: 77.2596 | L205: 53.75 | M205: 59.96 | O205: 43756 | P205: =IF(AND(B205<>"",B204<>""),LN(B205/B204),"") -> -0.0078078373 | Q205: =IF(AND(C205<>"",C204<>""),LN(C205/C204),"") -> -0.0053018444 | R205: =IF(AND(D205<>"",D204<>""),LN(D205/D204),"") -> -0.010694745 | S205: =IF(AND(E205<>"",E204<>""),LN(E205/E204),"") -> 0.0029710759 | T205: =IF(AND(F205<>"",F204<>""),LN(F205/F204),"") -> 0.0020798802 | U205: =IF(AND(G205<>"",G204<>""),LN(G205/G204),"") | V205: =IF(AND(H205<>"",H204<>""),LN(H205/H204),"") -> -0.01486647 | W205: =IF(AND(I205<>"",I204<>""),LN(I205/I204),"") -> -0.019031736 | ... Y205: =IF(AND(K205<>"",K204<>""),LN(K205/K204),"") -> 0 | Z205: -0.004387 | AA205: =IF(AND(L205<>"",L204<>""),LN(L205/L204),"") -> -0.0026012649 | AB205: =IF(AND(M205<>"",M204<>""),LN(M205/M204),"") -> 0.010225552 | AE205: 43756 | AF205: 14.25 | AG205: 36.43 | AH205: 78.35 | AI205: =IF(AND(M205<>"",L205<>""),M205-L205,"") -> 6.21 | AJ205: 2.08 | AK205: 15.965 | AL205: =IF(AND(AK205<>"",AJ205<>""),AK205-AJ205,"") -> 13.885 | AM205: 1.85 | AN205: 1.58 | AO205: 1.76 | AP205: =IF(AND(AO205<>"",AN205<>""),AO205-AN205,"") -> 0.18 | AQ205: 1.6 | AR205: 116.1344 | AS205: 1488.2 | AT205: 257.155 | AU205: 101.4281 | AV205: 95.5 | AY205: 43756 | AZ205: 0 | BA205: 0 | BB205: 0 | BE205: 43756 | BF205: Pre-COVID | BG205: 1
A206: 43759 | B206: 51.0666 | C206: 87.503 | D206: 44.5884 | E206: 36.3293 | F206: 60.8474 | H206: 6.2195 | I206: 28.7951 | J206: 7.2393 | K206: 77.2681 | L206: 53.28 | M206: 58.95 | O206: 43759 | P206: =IF(AND(B206<>"",B205<>""),LN(B206/B205),"") -> 0.016575941 | Q206: =IF(AND(C206<>"",C205<>""),LN(C206/C205),"") -> 0.01616599 | R206: =IF(AND(D206<>"",D205<>""),LN(D206/D205),"") -> 0.036580644 | S206: =IF(AND(E206<>"",E205<>""),LN(E206/E205),"") -> 0.0091056398 | T206: =IF(AND(F206<>"",F205<>""),LN(F206/F205),"") -> 0.017746446 | U206: =IF(AND(G206<>"",G205<>""),LN(G206/G205),"") | V206: =IF(AND(H206<>"",H205<>""),LN(H206/H205),"") -> -0.012240876 | W206: =IF(AND(I206<>"",I205<>""),LN(I206/I205),"") -> -0.042171452 | ... Y206: =IF(AND(K206<>"",K205<>""),LN(K206/K205),"") -> 0.00011001264 | Z206: 0.006756 | AA206: =IF(AND(L206<>"",L205<>""),LN(L206/L205),"") -> -0.0087826408 | AB206: =IF(AND(M206<>"",M205<>""),LN(M206/M205),"") -> -0.016988046 | AE206: 43759 | AF206: 14 | AG206: 36.66 | AH206: 80.25 | AI206: =IF(AND(M206<>"",L206<>""),M206-L206,"") -> 5.67 | AJ206: 2.13 | AK206: 15.61 | AL206: =IF(AND(AK206<>"",AJ206<>""),AK206-AJ206,"") -> 13.48 | AM206: 1.85 | AN206: 1.62 | AO206: 1.8 | AP206: =IF(AND(AO206<>"",AN206<>""),AO206-AN206,"") -> 0.18 | AQ206: 1.61 | AR206: 116.0436 | AS206: 1482.4 | AT206: 257.155 | AU206: 101.4281 | AV206: 95.5 | AY206: 43759 | AZ206: 0 | BA206: 0 | BB206: 0 | BE206: 43759 | BF206: Pre-COVID | BG206: 1
A207: 43760 | B207: 51.3266 | C207: 88.396 | D207: 45.0505 | E207: 37.5753 | F207: 61.029 | H207: 6.1959 | I207: 29.019 | J207: 7.1493 | K207: 77.2681 | L207: 54.21 | M207: 60.5 | O207: 43760 | P207: =IF(AND(B207<>"",B206<>""),LN(B207/B206),"") -> 0.0050784732 | Q207: =IF(AND(C207<>"",C206<>""),LN(C207/C206),"") -> 0.010153641 | R207: =IF(AND(D207<>"",D206<>""),LN(D207/D206),"") -> 0.010310347 | S207: =IF(AND(E207<>"",E206<>""),LN(E207/E206),"") -> 0.033722341 | T207: =IF(AND(F207<>"",F206<>""),LN(F207/F206),"") -> 0.0029800705 | U207: =IF(AND(G207<>"",G206<>""),LN(G207/G206),"") | V207: =IF(AND(H207<>"",H206<>""),LN(H207/H206),"") -> -0.0038017347 | W207: =IF(AND(I207<>"",I206<>""),LN(I207/I206),"") -> 0.0077455541 | ... Y207: =IF(AND(K207<>"",K206<>""),LN(K207/K206),"") -> 0 | Z207: -0.003272 | AA207: =IF(AND(L207<>"",L206<>""),LN(L207/L206),"") -> 0.017304367 | AB207: =IF(AND(M207<>"",M206<>""),LN(M207/M206),"") -> 0.025953738 | AE207: 43760 | AF207: 14.46 | AG207: 35.52 | AH207: 78.73 | AI207: =IF(AND(M207<>"",L207<>""),M207-L207,"") -> 6.29 | AJ207: 2.21 | AK207: 15.595 | AL207: =IF(AND(AK207<>"",AJ207<>""),AK207-AJ207,"") -> 13.385 | AM207: 1.85 | AN207: 1.6 | AO207: 1.78 | AP207: =IF(AND(AO207<>"",AN207<>""),AO207-AN207,"") -> 0.18 | AQ207: 1.61 | AR207: 115.9851 | AS207: 1481.7 | AT207: 257.155 | AU207: 101.4281 | AV207: 95.5 | AY207: 43760 | AZ207: 0 | BA207: 0 | BB207: 0 | BE207: 43760 | BF207: Pre-COVID | BG207: 1
A208: 43761 | B208: 51.8169 | C208: 88.531 | D208: 44.8194 | E208: 38.1983 | F208: 61.0386 | H208: 6.3492 | I208: 30.044 | J208: 7.093 | K208: 77.2681 | L208: 55.9 | M208: 60.52 | O208: 43761 | P208: =IF(AND(B208<>"",B207<>""),LN(B208/B207),"") -> 0.0095072146 | Q208: =IF(AND(C208<>"",C207<>""),LN(C208/C207),"") -> 0.0015260534 | R208: =IF(AND(D208<>"",D207<>""),LN(D208/D207),"") -> -0.0051430014 | S208: =IF(AND(E208<>"",E207<>""),LN(E208/E207),"") -> 0.016444092 | T208: =IF(AND(F208<>"",F207<>""),LN(F208/F207),"") -> 0.0001572899 | U208: =IF(AND(G208<>"",G207<>""),LN(G208/G207),"") | V208: =IF(AND(H208<>"",H207<>""),LN(H208/H207),"") -> 0.024441038 | W208: =IF(AND(I208<>"",I207<>""),LN(I208/I207),"") -> 0.034712186 | ... Y208: =IF(AND(K208<>"",K207<>""),LN(K208/K207),"") -> 0 | Z208: 0.002905 | AA208: =IF(AND(L208<>"",L207<>""),LN(L208/L207),"") -> 0.030698987 | AB208: =IF(AND(M208<>"",M207<>""),LN(M208/M207),"") -> 0.00033052388 | AE208: 43761 | AF208: 14.01 | AG208: 35.66 | AH208: 73.03 | AI208: =IF(AND(M208<>"",L208<>""),M208-L208,"") -> 4.62 | AJ208: 2.34 | AK208: 15.415 | AL208: =IF(AND(AK208<>"",AJ208<>""),AK208-AJ208,"") -> 13.075 | AM208: 1.85 | AN208: 1.58 | AO208: 1.77 | AP208: =IF(AND(AO208<>"",AN208<>""),AO208-AN208,"") -> 0.19 | AQ208: 1.61 | AR208: 116.0586 | AS208: 1489.9 | AT208: 257.155 | AU208: 101.4281 | AV208: 95.5 | AY208: 43761 | AZ208: 0 | BA208: 0 | BB208: 0 | BE208: 43761 | BF208: Pre-COVID | BG208: 1
A209: 43762 | B209: 51.3266 | C209: 88.2309 | D209: 44.7477 | E209: 37.6376 | F209: 61.4877 | H209: 6.1841 | I209: 29.3291 | J209: 7.0029 | K209: 77.2849 | L209: 56.11 | M209: 61.71 | O209: 43762 | P209: =IF(AND(B209<>"",B208<>""),LN(B209/B208),"") -> -0.0095072146 | Q209: =IF(AND(C209<>"",C208<>""),LN(C209/C208),"") -> -0.0033955314 | R209: =IF(AND(D209<>"",D208<>""),LN(D209/D208),"") -> -0.0016010347 | S209: =IF(AND(E209<>"",E208<>""),LN(E209/E208),"") -> -0.014787461 | T209: =IF(AND(F209<>"",F208<>""),LN(F209/F208),"") -> 0.0073307039 | U209: =IF(AND(G209<>"",G208<>""),LN(G209/G208),"") | V209: =IF(AND(H209<>"",H208<>""),LN(H209/H208),"") -> -0.026347339 | W209: =IF(AND(I209<>"",I208<>""),LN(I209/I208),"") -> -0.024082777 | ... Y209: =IF(AND(K209<>"",K208<>""),LN(K209/K208),"") -> 0.00021740115 | Z209: 0.001632 | AA209: =IF(AND(L209<>"",L208<>""),LN(L209/L208),"") -> 0.0037496696 | AB209: =IF(AND(M209<>"",M208<>""),LN(M209/M208),"") -> 0.019472103 | AE209: 43762 | AF209: 13.71 | AG209: 35.95 | AH209: 68.97 | AI209: =IF(AND(M209<>"",L209<>""),M209-L209,"") -> 5.6 | AJ209: 2.33 | AK209: 15.655 | AL209: =IF(AND(AK209<>"",AJ209<>""),AK209-AJ209,"") -> 13.325 | AM209: 1.85 | AN209: 1.58 | AO209: 1.77 | AP209: =IF(AND(AO209<>"",AN209<>""),AO209-AN209,"") -> 0.19 | AQ209: 1.62 | AR209: 116.1278 | AS209: 1498.9 | AT209: 257.155 | AU209: 101.4281 | AV209: 95.5 | AY209: 43762 | AZ209: 0 | BA209: 0 | BB209: 0 | BE209: 43762 | BF209: Pre-COVID | BG209: 1
A210: 43763 | B210: 51.4454 | C210: 89.0488 | D210: 44.8991 | E210: 37.8512 | F210: 61.4495 | H210: 6.078 | I210: 28.7434 | J210: 7.0648 | K210: 77.2849 | L210: 56.52 | M210: 62.06 | O210: 43763 | P210: =IF(AND(B210<>"",B209<>""),LN(B210/B209),"") -> 0.0023119148 | Q210: =IF(AND(C210<>"",C209<>""),LN(C210/C209),"") -> 0.0092272923 | R210: =IF(AND(D210<>"",D209<>""),LN(D210/D209),"") -> 0.0033777033 | S210: =IF(AND(E210<>"",E209<>""),LN(E210/E209),"") -> 0.0056591327 | T210: =IF(AND(F210<>"",F209<>""),LN(F210/F209),"") -> -0.00062145553 | U210: =IF(AND(G210<>"",G209<>""),LN(G210/G209),"") | V210: =IF(AND(H210<>"",H209<>""),LN(H210/H209),"") -> -0.017305787 | W210: =IF(AND(I210<>"",I209<>""),LN(I210/I209),"") -> -0.020172022 | ... Y210: =IF(AND(K210<>"",K209<>""),LN(K210/K209),"") -> 0 | Z210: 0.004087 | AA210: =IF(AND(L210<>"",L209<>""),LN(L210/L209),"") -> 0.0072805081 | AB210: =IF(AND(M210<>"",M209<>""),LN(M210/M209),"") -> 0.0056556667 | AE210: 43763 | AF210: 12.65 | AG210: 34.64 | AH210: 67.07 | AI210: =IF(AND(M210<>"",L210<>""),M210-L210,"") -> 5.54 | AJ210: 2.26 | AK210: 15.235 | AL210: =IF(AND(AK210<>"",AJ210<>""),AK210-AJ210,"") -> 12.975 | AM210: 1.83 | AN210: 1.63 | AO210: 1.8 | AP210: =IF(AND(AO210<>"",AN210<>""),AO210-AN210,"") -> 0.17 | AQ210: 1.65 | AR210: 116.0774 | AS210: 1499.5 | AT210: 257.155 | AU210: 101.4281 | AV210: 95.5 | AY210: 43763 | AZ210: 0 | BA210: 0 | BB210: 0 | BE210: 43763 | BF210: Pre-COVID | BG210: 1
A211: 43766 | B211: 50.9923 | C211: 88.9062 | D211: 44.3653 | E211: 37.6287 | F211: 59.8249 | H211: 6.1016 | I211: 28.261 | J211: 6.9579 | K211: 77.2765 | L211: 55.6 | M211: 60.39 | O211: 43766 | P211: =IF(AND(B211<>"",B210<>""),LN(B211/B210),"") -> -0.0088464102 | Q211: =IF(AND(C211<>"",C210<>""),LN(C211/C210),"") -> -0.0016026527 | R211: =IF(AND(D211<>"",D210<>""),LN(D211/D210),"") -> -0.011960118 | S211: =IF(AND(E211<>"",E210<>""),LN(E211/E210),"") -> -0.0058956264 | T211: =IF(AND(F211<>"",F210<>""),LN(F211/F210),"") -> -0.026793737 | U211: =IF(AND(G211<>"",G210<>""),LN(G211/G210),"") | V211: =IF(AND(H211<>"",H210<>""),LN(H211/H210),"") -> 0.0038753374 | W211: =IF(AND(I211<>"",I210<>""),LN(I211/I210),"") -> -0.016925413 | ... Y211: =IF(AND(K211<>"",K210<>""),LN(K211/K210),"") -> -0.00010869467 | Z211: 0.005621 | AA211: =IF(AND(L211<>"",L210<>""),LN(L211/L210),"") -> -0.016411357 | AB211: =IF(AND(M211<>"",M210<>""),LN(M211/M210),"") -> -0.027278131 | AE211: 43766 | AF211: 13.11 | AG211: 35.64 | AH211: 67.41 | AI211: =IF(AND(M211<>"",L211<>""),M211-L211,"") -> 4.79 | AJ211: 2.49 | AK211: 14.39 | AL211: =IF(AND(AK211<>"",AJ211<>""),AK211-AJ211,"") -> 11.9 | AM211: 1.83 | AN211: 1.64 | AO211: 1.85 | AP211: =IF(AND(AO211<>"",AN211<>""),AO211-AN211,"") -> 0.21 | AQ211: 1.64 | AR211: 116.0222 | AS211: 1490 | AT211: 257.155 | AU211: 101.4281 | AV211: 95.5 | AY211: 43766 | AZ211: 0 | BA211: 0 | BB211: 0 | BE211: 43766 | BF211: Pre-COVID | BG211: 1
A212: 43767 | B212: 50.8437 | C212: 88.6436 | D212: 45.4887 | E212: 37.6732 | F212: 59.672 | H212: 6.2254 | I212: 28.3041 | J212: 6.9522 | K212: 77.2934 | L212: 55.34 | M212: 61.05 | O212: 43767 | P212: =IF(AND(B212<>"",B211<>""),LN(B212/B211),"") -> -0.0029184199 | Q212: =IF(AND(C212<>"",C211<>""),LN(C212/C211),"") -> -0.0029580455 | R212: =IF(AND(D212<>"",D211<>""),LN(D212/D211),"") -> 0.025006311 | S212: =IF(AND(E212<>"",E211<>""),LN(E212/E211),"") -> 0.0011819092 | T212: =IF(AND(F212<>"",F211<>""),LN(F212/F211),"") -> -0.0025590636 | U212: =IF(AND(G212<>"",G211<>""),LN(G212/G211),"") | V212: =IF(AND(H212<>"",H211<>""),LN(H212/H211),"") -> 0.020086665 | W212: =IF(AND(I212<>"",I211<>""),LN(I212/I211),"") -> 0.0015239081 | ... Y212: =IF(AND(K212<>"",K211<>""),LN(K212/K211),"") -> 0.00021867129 | Z212: -0.000297 | AA212: =IF(AND(L212<>"",L211<>""),LN(L212/L211),"") -> -0.0046872269 | AB212: =IF(AND(M212<>"",M211<>""),LN(M212/M211),"") -> 0.010869672 | AE212: 43767 | AF212: 13.2 | AG212: 35.7 | AH212: 67.61 | AI212: =IF(AND(M212<>"",L212<>""),M212-L212,"") -> 5.71 | AJ212: 2.61 | AK212: 13.835 | AL212: =IF(AND(AK212<>"",AJ212<>""),AK212-AJ212,"") -> 11.225 | AM212: 1.82 | AN212: 1.64 | AO212: 1.84 | AP212: =IF(AND(AO212<>"",AN212<>""),AO212-AN212,"") -> 0.2 | AQ212: 1.61 | AR212: 115.9797 | AS212: 1487 | AT212: 257.155 | AU212: 101.4281 | AV212: 95.5 | AY212: 43767 | AZ212: 0 | BA212: 0 | BB212: 0 | BE212: 43767 | BF212: Pre-COVID | BG212: 1
A213: 43768 | B213: 50.3088 | C213: 87.3154 | D213: 43.8553 | E213: 36.8099 | F213: 59.4617 | H213: 6.2666 | I213: 28.4075 | J213: 6.9522 | K213: 77.3018 | L213: 54.85 | M213: 60.22 | O213: 43768 | P213: =IF(AND(B213<>"",B212<>""),LN(B213/B212),"") -> -0.010576209 | Q213: =IF(AND(C213<>"",C212<>""),LN(C213/C212),"") -> -0.015096985 | R213: =IF(AND(D213<>"",D212<>""),LN(D213/D212),"") -> -0.036568365 | S213: =IF(AND(E213<>"",E212<>""),LN(E213/E212),"") -> -0.023182136 | T213: =IF(AND(F213<>"",F212<>""),LN(F213/F212),"") -> -0.0035304908 | U213: =IF(AND(G213<>"",G212<>""),LN(G213/G212),"") | V213: =IF(AND(H213<>"",H212<>""),LN(H213/H212),"") -> 0.0065962455 | W213: =IF(AND(I213<>"",I212<>""),LN(I213/I212),"") -> 0.0036465243 | ... Y213: =IF(AND(K213<>"",K212<>""),LN(K213/K212),"") -> 0.0001086709 | Z213: 0.003062 | AA213: =IF(AND(L213<>"",L212<>""),LN(L213/L212),"") -> -0.0088937876 | AB213: =IF(AND(M213<>"",M212<>""),LN(M213/M212),"") -> -0.013688678 | AE213: 43768 | AF213: 12.33 | AG213: 34.36 | AH213: 63.32 | AI213: =IF(AND(M213<>"",L213<>""),M213-L213,"") -> 5.37 | AJ213: 2.71 | AK213: 13.78 | AL213: =IF(AND(AK213<>"",AJ213<>""),AK213-AJ213,"") -> 11.07 | AM213: 1.82 | AN213: 1.61 | AO213: 1.78 | AP213: =IF(AND(AO213<>"",AN213<>""),AO213-AN213,"") -> 0.17 | AQ213: 1.57 | AR213: 116.1636 | AS213: 1493.2 | AT213: 257.155 | AU213: 101.4281 | AV213: 95.5 | AY213: 43768 | AZ213: 0 | BA213: 0 | BB213: 0 | BE213: 43768 | BF213: Pre-COVID | BG213: 1
... A220: 43777 | B220: 53.2087 | C220: 90.7447 | D220: 47.1381 | E220: 35.6885 | F220: 59.003 | H220: 5.6948 | I220: 26.2627 | J220: 7.0455 | K220: 77.3348 | L220: 57.02 | M220: 62 | O220: 43777 | P220: =IF(AND(B220<>"",B219<>""),LN(B220/B219),"") -> -0.019172759 | Q220: =IF(AND(C220<>"",C219<>""),LN(C220/C219),"") -> -0.0079074095 | R220: =IF(AND(D220<>"",D219<>""),LN(D220/D219),"") -> -0.0064031346 | S220: =IF(AND(E220<>"",E219<>""),LN(E220/E219),"") -> 0.027046137 | T220: =IF(AND(F220<>"",F219<>""),LN(F220/F219),"") -> -0.00080980032 | U220: =IF(AND(G220<>"",G219<>""),LN(G220/G219),"") | V220: =IF(AND(H220<>"",H219<>""),LN(H220/H219),"") -> 0.016697598 | W220: =IF(AND(I220<>"",I219<>""),LN(I220/I219),"") -> 0.019206446 | ... Y220: =IF(AND(K220<>"",K219<>""),LN(K220/K219),"") -> 0 | Z220: 0.002463 | AA220: =IF(AND(L220<>"",L219<>""),LN(L220/L219),"") -> 0.0019310109 | AB220: =IF(AND(M220<>"",M219<>""),LN(M220/M219),"") -> -0.0096308931 | AE220: 43777 | AF220: 12.07 | AG220: 31.45 | AH220: 64.44 | AI220: =IF(AND(M220<>"",L220<>""),M220-L220,"") -> 4.98 | AJ220: 2.87 | AK220: 15.94 | AL220: =IF(AND(AK220<>"",AJ220<>""),AK220-AJ220,"") -> 13.07 | AM220: 1.55 | AN220: 1.68 | AO220: 1.94 | AP220: =IF(AND(AO220<>"",AN220<>""),AO220-AN220,"") -> 0.26 | AQ220: 1.71 | AR220: 116.3436 | AS220: 1461.3 | AT220: 257.879 | AU220: 101.9372 | AV220: 96.8 | AY220: 43777 | AZ220: 0 | BA220: 0 | BB220: 0 | BE220: 43777 | BF220: Pre-COVID | BG220: 1
A221: 43780 | B221: 52.8854 | C221: 90.6546 | D221: 46.9389 | E221: 34.6027 | F221: 58.7163 | H221: 5.5887 | I221: 26.1335 | J221: 6.9014 | K221: 77.3348 | M221: 62.58 | O221: 43780 | P221: =IF(AND(B221<>"",B220<>""),LN(B221/B220),"") -> -0.0060946085 | Q221: =IF(AND(C221<>"",C220<>""),LN(C221/C220),"") -> -0.0009933887 | R221: =IF(AND(D221<>"",D220<>""),LN(D221/D220),"") -> -0.0042348352 | S221: =IF(AND(E221<>"",E220<>""),LN(E221/E220),"") -> -0.030896794 | T221: =IF(AND(F221<>"",F220<>""),LN(F221/F220),"") -> -0.0048709186 | U221: =IF(AND(G221<>"",G220<>""),LN(G221/G220),"") | V221: =IF(AND(H221<>"",H220<>""),LN(H221/H220),"") -> -0.018806776 | W221: =IF(AND(I221<>"",I220<>""),LN(I221/I220),"") -> -0.0049316653 | ... Y221: =IF(AND(K221<>"",K220<>""),LN(K221/K220),"") -> 0 | Z221: -0.001912 | AA221: =IF(AND(L221<>"",L220<>""),LN(L221/L220),"") | AB221: =IF(AND(M221<>"",M220<>""),LN(M221/M220),"") -> 0.0093113532 | AE221: 43780 | AF221: 12.69 | AG221: 34.22 | AH221: 64.44 | AI221: =IF(AND(M221<>"",L221<>""),M221-L221,"") | AK221: 15.845 | AL221: =IF(AND(AK221<>"",AJ221<>""),AK221-AJ221,"") | AM221: 1.55 | AP221: =IF(AND(AO221<>"",AN221<>""),AO221-AN221,"") | AS221: 1455.5 | AT221: 257.879 | AU221: 101.9372 | AV221: 96.8 | AY221: 43780 | AZ221: 0 | BA221: 0 | BB221: 0 | BE221: 43780 | BF221: Pre-COVID | BG221: 1
A222: 43781 | B222: 52.1561 | C222: 90.7672 | D222: 46.3971 | E222: 34.2111 | F222: 59.0126 | H222: 5.8245 | I222: 26.9862 | J222: 6.7226 | K222: 77.3432 | L222: 56.67 | M222: 62.19 | O222: 43781 | P222: =IF(AND(B222<>"",B221<>""),LN(B222/B221),"") -> -0.013886163 | Q222: =IF(AND(C222<>"",C221<>""),LN(C222/C221),"") -> 0.0012413063 | R222: =IF(AND(D222<>"",D221<>""),LN(D222/D221),"") -> -0.011609799 | S222: =IF(AND(E222<>"",E221<>""),LN(E222/E221),"") -> -0.011381561 | T222: =IF(AND(F222<>"",F221<>""),LN(F222/F221),"") -> 0.005033609 | U222: =IF(AND(G222<>"",G221<>""),LN(G222/G221),"") | V222: =IF(AND(H222<>"",H221<>""),LN(H222/H221),"") -> 0.041326457 | W222: =IF(AND(I222<>"",I221<>""),LN(I222/I221),"") -> 0.032107608 | ... Y222: =IF(AND(K222<>"",K221<>""),LN(K222/K221),"") -> 0.00010861273 | Z222: 0.002106 | AA222: =IF(AND(L222<>"",L221<>""),LN(L222/L221),"") | AB222: =IF(AND(M222<>"",M221<>""),LN(M222/M221),"") -> -0.0062515231 | AE222: 43781 | AF222: 12.68 | AG222: 33.74 | AH222: 69.82 | AI222: =IF(AND(M222<>"",L222<>""),M222-L222,"") -> 5.52 | AJ222: 2.72 | AK222: 15.545 | AL222: =IF(AND(AK222<>"",AJ222<>""),AK222-AJ222,"") -> 12.825 | AM222: 1.55 | AN222: 1.66 | AO222: 1.92 | AP222: =IF(AND(AO222<>"",AN222<>""),AO222-AN222,"") -> 0.26 | AQ222: 1.7 | AR222: 116.5837 | AS222: 1452.1 | AT222: 257.879 | AU222: 101.9372 | AV222: 96.8 | AY222: 43781 | AZ222: 0 | BA222: 0 | BB222: 0 | BE222: 43781 | BF222: Pre-COVID | BG222: 1
A223: 43782 | B223: 51.7275 | C223: 91.7577 | D223: 45.8633 | E223: 33.9263 | F223: 58.5538 | H223: 5.854 | I223: 26.8656 | J223: 6.4343 | K223: 77.3432 | L223: 56.88 | M223: 62.27 | O223: 43782 | P223: =IF(AND(B223<>"",B222<>""),LN(B223/B222),"") -> -0.0082515899 | Q223: =IF(AND(C223<>"",C222<>""),LN(C223/C222),"") -> 0.01085342 | R223: =IF(AND(D223<>"",D222<>""),LN(D223/D222),"") -> -0.011571724 | S223: =IF(AND(E223<>"",E222<>""),LN(E223/E222),"") -> -0.008359628 | T223: =IF(AND(F223<>"",F222<>""),LN(F223/F222),"") -> -0.0078049907 | U223: =IF(AND(G223<>"",G222<>""),LN(G223/G222),"") | V223: =IF(AND(H223<>"",H222<>""),LN(H223/H222),"") -> 0.0050520294 | W223: =IF(AND(I223<>"",I222<>""),LN(I223/I222),"") -> -0.0044789664 | ... Y223: =IF(AND(K223<>"",K222<>""),LN(K223/K222),"") -> 0 | Z223: 0.000324 | AA223: =IF(AND(L223<>"",L222<>""),LN(L223/L222),"") -> 0.0036988153 | AB223: =IF(AND(M223<>"",M222<>""),LN(M223/M222),"") -> 0.0012855538 | AE223: 43782 | AF223: 13 | AG223: 35.15 | AH223: 66.1 | AI223: =IF(AND(M223<>"",L223<>""),M223-L223,"") -> 5.39 | AJ223: 2.66 | AK223: 15.45 | AL223: =IF(AND(AK223<>"",AJ223<>""),AK223-AJ223,"") -> 12.79 | AM223: 1.55 | AN223: 1.63 | AO223: 1.88 | AP223: =IF(AND(AO223<>"",AN223<>""),AO223-AN223,"") -> 0.25 | AQ223: 1.66 | AR223: 116.8397 | AS223: 1461.7 | AT223: 257.879 | AU223: 101.9372 | AV223: 96.8 | AY223: 43782 | AZ223: 0 | BA223: 0 | BB223: 0 | BE223: 43782 | BF223: Pre-COVID | BG223: 1
A224: 43783 | B224: 51.502 | C224: 91.5176 | D224: 45.6162 | E224: 33.6059 | F224: 58.4487 | H224: 5.9247 | I224: 27.1671 | J224: 6.4459 | K224: 77.3517 | L224: 56.57 | M224: 62.46 | O224: 43783 | P224: =IF(AND(B224<>"",B223<>""),LN(B224/B223),"") -> -0.0043689131 | Q224: =IF(AND(C224<>"",C223<>""),LN(C224/C223),"") -> -0.0026201036 | R224: =IF(AND(D224<>"",D223<>""),LN(D224/D223),"") -> -0.0054023164 | S224: =IF(AND(E224<>"",E223<>""),LN(E224/E223),"") -> -0.009488878 | T224: =IF(AND(F224<>"",F223<>""),LN(F224/F223),"") -> -0.0017965433 | U224: =IF(AND(G224<>"",G223<>""),LN(G224/G223),"") | V224: =IF(AND(H224<>"",H223<>""),LN(H224/H223),"") -> 0.012004865 | W224: =IF(AND(I224<>"",I223<>""),LN(I224/I223),"") -> 0.011160025 | ... Y224: =IF(AND(K224<>"",K223<>""),LN(K224/K223),"") -> 0.00010989373 | Z224: 0.001455 | AA224: =IF(AND(L224<>"",L223<>""),LN(L224/L223),"") -> -0.0054649761 | AB224: =IF(AND(M224<>"",M223<>""),LN(M224/M223),"") -> 0.003046583 | AE224: 43783 | AF224: 13.05 | AG224: 33.94 | AH224: 64.17 | AI224: =IF(AND(M224<>"",L224<>""),M224-L224,"") -> 5.89 | AJ224: 2.68 | AK224: 15.67 | AL224: =IF(AND(AK224<>"",AJ224<>""),AK224-AJ224,"") -> 12.99 | AM224: 1.55 | AN224: 1.58 | AO224: 1.82 | AP224: =IF(AND(AO224<>"",AN224<>""),AO224-AN224,"") -> 0.24 | AQ224: 1.62 | AR224: 116.8022 | AS224: 1471.8 | AT224: 257.879 | AU224: 101.9372 | AV224: 96.8 | AY224: 43783 | AZ224: 0 | BA224: 0 | BB224: 0 | BE224: 43783 | BF224: Pre-COVID | BG224: 1
A225: 43784 | B225: 52.0207 | C225: 91.4191 | D225: 46.413 | E225: 34.665 | F225: 58.7067 | H225: 6.2195 | I225: 27.6236 | J225: 6.6996 | K225: 77.3432 | L225: 57.54 | M225: 63.32 | O225: 43784 | P225: =IF(AND(B225<>"",B224<>""),LN(B225/B224),"") -> 0.010021074 | Q225: =IF(AND(C225<>"",C224<>""),LN(C225/C224),"") -> -0.0010768753 | R225: =IF(AND(D225<>"",D224<>""),LN(D225/D224),"") -> 0.017316676 | S225: =IF(AND(E225<>"",E224<>""),LN(E225/E224),"") -> 0.031028886 | T225: =IF(AND(F225<>"",F224<>""),LN(F225/F224),"") -> 0.0044044136 | U225: =IF(AND(G225<>"",G224<>""),LN(G225/G224),"") | V225: =IF(AND(H225<>"",H224<>""),LN(H225/H224),"") -> 0.048559465 | W225: =IF(AND(I225<>"",I224<>""),LN(I225/I224),"") -> 0.016663797 | ... Y225: =IF(AND(K225<>"",K224<>""),LN(K225/K224),"") -> -0.00010989373 | Z225: 0.00721 | AA225: =IF(AND(L225<>"",L224<>""),LN(L225/L224),"") -> 0.017001549 | AB225: =IF(AND(M225<>"",M224<>""),LN(M225/M224),"") -> 0.013674883 | AE225: 43784 | AF225: 12.05 | AG225: 32.42 | AH225: 61.7 | AI225: =IF(AND(M225<>"",L225<>""),M225-L225,"") -> 5.78 | AJ225: 2.7 | AK225: 15.715 | AL225: =IF(AND(AK225<>"",AJ225<>""),AK225-AJ225,"") -> 13.015 | AM225: 1.55 | AN225: 1.61 | AO225: 1.84 | AP225: =IF(AND(AO225<>"",AN225<>""),AO225-AN225,"") -> 0.23 | AQ225: 1.63 | AR225: 116.4401 | AS225: 1467.3 | AT225: 257.879 | AU225: 101.9372 | AV225: 96.8 | AY225: 43784 | AZ225: 0 | BA225: 0 | BB225: 0 | BE225: 43784 | BF225: Pre-COVID | BG225: 1
A226: 43787 | B226: 51.517 | C226: 89.8353 | D226: 45.178 | E226: 34.9765 | F226: 57.818 | H226: 6.1546 | I226: 26.8484 | J226: 6.5324 | K226: 77.3601 | L226: 56.82 | M226: 62.82 | O226: 43787 | P226: =IF(AND(B226<>"",B225<>""),LN(B226/B225),"") -> -0.009729866 | Q226: =IF(AND(C226<>"",C225<>""),LN(C226/C225),"") -> -0.017476434 | R226: =IF(AND(D226<>"",D225<>""),LN(D226/D225),"") -> -0.02696935 | S226: =IF(AND(E226<>"",E225<>""),LN(E226/E225),"") -> 0.008945875 | T226: =IF(AND(F226<>"",F225<>""),LN(F226/F225),"") -> -0.015253714 | U226: =IF(AND(G226<>"",G225<>""),LN(G226/G225),"") | V226: =IF(AND(H226<>"",H225<>""),LN(H226/H225),"") -> -0.010489748 | W226: =IF(AND(I226<>"",I225<>""),LN(I226/I225),"") -> -0.028464251 | ... Y226: =IF(AND(K226<>"",K225<>""),LN(K226/K225),"") -> 0.00021848274 | Z226: 0.000737 | AA226: =IF(AND(L226<>"",L225<>""),LN(L226/L225),"") -> -0.012591982 | AB226: =IF(AND(M226<>"",M225<>""),LN(M226/M225),"") -> -0.0079277409 | AE226: 43787 | AF226: 12.46 | AG226: 33.68 | AH226: 64.13 | AI226: =IF(AND(M226<>"",L226<>""),M226-L226,"") -> 6 | AJ226: 2.64 | AK226: 15.23 | AL226: =IF(AND(AK226<>"",AJ226<>""),AK226-AJ226,"") -> 12.59 | AM226: 1.55 | AN226: 1.6 | AO226: 1.81 | AP226: =IF(AND(AO226<>"",AN226<>""),AO226-AN226,"") -> 0.21 | AQ226: 1.63 | AR226: 116.3625 | AS226: 1470.9 | AT226: 257.879 | AU226: 101.9372 | AV226: 96.8 | AY226: 43787 | AZ226: 0 | BA226: 0 | BB226: 0 | BE226: 43787 | BF226: Pre-COVID | BG226: 1
A227: 43788 | B227: 50.9907 | C227: 88.244 | D227: 45.5525 | E227: 33.9441 | F227: 57.149 | H227: 6.1428 | I227: 27.8906 | J227: 6.5612 | K227: 77.3517 | L227: 54.93 | M227: 62.37 | O227: 43788 | P227: =IF(AND(B227<>"",B226<>""),LN(B227/B226),"") -> -0.010268587 | Q227: =IF(AND(C227<>"",C226<>""),LN(C227/C226),"") -> -0.017872289 | R227: =IF(AND(D227<>"",D226<>""),LN(D227/D226),"") -> 0.0082552643 | S227: =IF(AND(E227<>"",E226<>""),LN(E227/E226),"") -> -0.029961353 | T227: =IF(AND(F227<>"",F226<>""),LN(F227/F226),"") -> -0.011638254 | U227: =IF(AND(G227<>"",G226<>""),LN(G227/G226),"") | V227: =IF(AND(H227<>"",H226<>""),LN(H227/H226),"") -> -0.0019191054 | W227: =IF(AND(I227<>"",I226<>""),LN(I227/I226),"") -> 0.038083486 | ... Y227: =IF(AND(K227<>"",K226<>""),LN(K227/K226),"") -> -0.000108589 | Z227: -0.000288 | AA227: =IF(AND(L227<>"",L226<>""),LN(L227/L226),"") -> -0.033828729 | AB227: =IF(AND(M227<>"",M226<>""),LN(M227/M226),"") -> -0.0071891036 | AE227: 43788 | AF227: 12.86 | AG227: 32.94 | AH227: 62.64 | AI227: =IF(AND(M227<>"",L227<>""),M227-L227,"") -> 7.44 | AJ227: 2.53 | AK227: 15.29 | AL227: =IF(AND(AK227<>"",AJ227<>""),AK227-AJ227,"") -> 12.76 | AM227: 1.55 | AN227: 1.6 | AO227: 1.79 | AP227: =IF(AND(AO227<>"",AN227<>""),AO227-AN227,"") -> 0.19 | AQ227: 1.63 | AR227: 116.5391 | AS227: 1473.3 | AT227: 257.879 | AU227: 101.9372 | AV227: 96.8 | AY227: 43788 | AZ227: 0 | BA227: 0 | BB227: 0 | BE227: 43788 | BF227: Pre-COVID | BG227: 1
A228: 43789 | B228: 51.1486 | C228: 88.9184 | D228: 47.2975 | E228: 34.2467 | F228: 57.5122 | H228: 6.414 | I228: 29.1224 | J228: 6.5497 | K228: 77.3601 | L228: 56.71 | M228: 63.8 | O228: 43789 | P228: =IF(AND(B228<>"",B227<>""),LN(B228/B227),"") -> 0.0030918584 | Q228: =IF(AND(C228<>"",C227<>""),LN(C228/C227),"") -> 0.0076133904 | R228: =IF(AND(D228<>"",D227<>""),LN(D228/D227),"") -> 0.037591933 | S228: =IF(AND(E228<>"",E227<>""),LN(E228/E227),"") -> 0.0088751558 | T228: =IF(AND(F228<>"",F227<>""),LN(F228/F227),"") -> 0.0063352069 | U228: =IF(AND(G228<>"",G227<>""),LN(G228/G227),"") | V228: =IF(AND(H228<>"",H227<>""),LN(H228/H227),"") -> 0.043202437 | W228: =IF(AND(I228<>"",I227<>""),LN(I228/I227),"") -> 0.043217923 | ... Y228: =IF(AND(K228<>"",K227<>""),LN(K228/K227),"") -> 0.000108589 | Z228: -0.003726 | AA228: =IF(AND(L228<>"",L227<>""),LN(L228/L227),"") -> 0.031890915 | AB228: =IF(AND(M228<>"",M227<>""),LN(M228/M227),"") -> 0.0226688 | AE228: 43789 | AF228: 12.78 | AG228: 32.2 | AH228: 65.58 | AI228: =IF(AND(M228<>"",L228<>""),M228-L228,"") -> 7.09 | AJ228: 2.56 | AK228: 15.59 | AL228: =IF(AND(AK228<>"",AJ228<>""),AK228-AJ228,"") -> 13.03 | AM228: 1.55 | AN228: 1.56 | AO228: 1.73 | AP228: =IF(AND(AO228<>"",AN228<>""),AO228-AN228,"") -> 0.17 | AQ228: 1.6 | AR228: 116.828 | AS228: 1473.3 | AT228: 257.879 | AU228: 101.9372 | AV228: 96.8 | AY228: 43789 | AZ228: 0 | BA228: 0 | BB228: 0 | BE228: 43789 | BF228: Pre-COVID | BG228: 1
A229: 43790 | B229: 52.3816 | C229: 90.002 | D229: 47.9747 | E229: 34.8163 | F229: 58.4583 | H229: 6.4965 | I229: 29.0104 | J229: 6.8668 | K229: 77.3601 | L229: 58.36 | M229: 64.99 | O229: 43790 | P229: =IF(AND(B229<>"",B228<>""),LN(B229/B228),"") -> 0.023820263 | Q229: =IF(AND(C229<>"",C228<>""),LN(C229/C228),"") -> 0.012112797 | R229: =IF(AND(D229<>"",D228<>""),LN(D229/D228),"") -> 0.014216349 | S229: =IF(AND(E229<>"",E228<>""),LN(E229/E228),"") -> 0.016495458 | T229: =IF(AND(F229<>"",F228<>""),LN(F229/F228),"") -> 0.01631658 | U229: =IF(AND(G229<>"",G228<>""),LN(G229/G228),"") | V229: =IF(AND(H229<>"",H228<>""),LN(H229/H228),"") -> 0.012780469 | W229: =IF(AND(I229<>"",I228<>""),LN(I229/I228),"") -> -0.0038532511 | ... Y229: =IF(AND(K229<>"",K228<>""),LN(K229/K228),"") -> 0 | Z229: -0.00161 | AA229: =IF(AND(L229<>"",L228<>""),LN(L229/L228),"") -> 0.028680162 | AB229: =IF(AND(M229<>"",M228<>""),LN(M229/M228),"") -> 0.018480222 | AE229: 43790 | AF229: 13.13 | AG229: 31.59 | AH229: 61.83 | AI229: =IF(AND(M229<>"",L229<>""),M229-L229,"") -> 6.63 | AJ229: 2.53 | AK229: 15.625 | AL229: =IF(AND(AK229<>"",AJ229<>""),AK229-AJ229,"") -> 13.095 | AM229: 1.55 | AN229: 1.6 | AO229: 1.77 | AP229: =IF(AND(AO229<>"",AN229<>""),AO229-AN229,"") -> 0.17 | AQ229: 1.63 | AR229: 116.7435 | AS229: 1463.1 | AT229: 257.879 | AU229: 101.9372 | AV229: 96.8 | AY229: 43790 | AZ229: 0 | BA229: 0 | BB229: 0 | BE229: 43790 | BF229: Pre-COVID | BG229: 1
A230: 43791 | B230: 52.1561 | C230: 89.8959 | D230: 47.7277 | E230: 35.2257 | F230: 58.1429 | H230: 6.5319 | I230: 29.3733 | J230: 6.8783 | K230: 77.3686 | L230: 57.68 | M230: 64.83 | O230: 43791 | P230: =IF(AND(B230<>"",B229<>""),LN(B230/B229),"") -> -0.0043142397 | Q230: =IF(AND(C230<>"",C229<>""),LN(C230/C229),"") -> -0.0011795581 | R230: =IF(AND(D230<>"",D229<>""),LN(D230/D229),"") -> -0.0051618465 | S230: =IF(AND(E230<>"",E229<>""),LN(E230/E229),"") -> 0.011690262 | T230: =IF(AND(F230<>"",F229<>""),LN(F230/F229),"") -> -0.0054099061 | U230: =IF(AND(G230<>"",G229<>""),LN(G230/G229),"") | V230: =IF(AND(H230<>"",H229<>""),LN(H230/H229),"") -> 0.0054342954 | W230: =IF(AND(I230<>"",I229<>""),LN(I230/I229),"") -> 0.012431712 | ... Y230: =IF(AND(K230<>"",K229<>""),LN(K230/K229),"") -> 0.00010986973 | Z230: 0.002221 | AA230: =IF(AND(L230<>"",L229<>""),LN(L230/L229),"") -> -0.011720231 | AB230: =IF(AND(M230<>"",M229<>""),LN(M230/M229),"") -> -0.0024649527 | AE230: 43791 | AF230: 12.34 | AG230: 32.38 | AH230: 62.17 | AI230: =IF(AND(M230<>"",L230<>""),M230-L230,"") -> 7.15 | AJ230: 2.62 | AK230: 16.05 | AL230: =IF(AND(AK230<>"",AJ230<>""),AK230-AJ230,"") -> 13.43 | AM230: 1.55 | AN230: 1.61 | AO230: 1.77 | AP230: =IF(AND(AO230<>"",AN230<>""),AO230-AN230,"") -> 0.16 | AQ230: 1.62 | AR230: 116.9137 | AS230: 1463.1 | AT230: 257.879 | AU230: 101.9372 | AV230: 96.8 | AY230: 43791 | AZ230: 0 | BA230: 0 | BB230: 0 | BE230: 43791 | BF230: Pre-COVID | BG230: 1
A231: 43794 | B231: 51.8102 | C231: 89.7065 | D231: 48.644 | E231: 35.5372 | F231: 58.6303 | H231: 6.7264 | I231: 30.9456 | J231: 7.0916 | K231: 77.3686 | L231: 57.79 | M231: 64.67 | O231: 43794 | P231: =IF(AND(B231<>"",B230<>""),LN(B231/B230),"") -> -0.0066541038 | Q231: =IF(AND(C231<>"",C230<>""),LN(C231/C230),"") -> -0.002109104 | R231: =IF(AND(D231<>"",D230<>""),LN(D231/D230),"") -> 0.019016529 | S231: =IF(AND(E231<>"",E230<>""),LN(E231/E230),"") -> 0.0088041053 | T231: =IF(AND(F231<>"",F230<>""),LN(F231/F230),"") -> 0.0083478543 | U231: =IF(AND(G231<>"",G230<>""),LN(G231/G230),"") | V231: =IF(AND(H231<>"",H230<>""),LN(H231/H230),"") -> 0.029342217 | W231: =IF(AND(I231<>"",I230<>""),LN(I231/I230),"") -> 0.052144726 | ... Y231: =IF(AND(K231<>"",K230<>""),LN(K231/K230),"") -> 0 | Z231: 0.00772 | AA231: =IF(AND(L231<>"",L230<>""),LN(L231/L230),"") -> 0.0019052574 | AB231: =IF(AND(M231<>"",M230<>""),LN(M231/M230),"") -> -0.0024710437 | AE231: 43794 | AF231: 11.87 | AG231: 31.9 | AH231: 61.55 | AI231: =IF(AND(M231<>"",L231<>""),M231-L231,"") -> 6.88 | AJ231: 2.51 | AK231: 16.235 | AL231: =IF(AND(AK231<>"",AJ231<>""),AK231-AJ231,"") -> 13.725 | AM231: 1.55 | AN231: 1.61 | AO231: 1.76 | AP231: =IF(AND(AO231<>"",AN231<>""),AO231-AN231,"") -> 0.15 | AQ231: 1.62 | AR231: 117.0098 | AS231: 1456.6 | AT231: 257.879 | AU231: 101.9372 | AV231: 96.8 | AY231: 43794 | AZ231: 0 | BA231: 0 | BB231: 0 | BE231: 43794 | BF231: Pre-COVID | BG231: 1
A232: 43795 | B232: 51.6824 | C232: 89.2594 | D232: 47.8951 | E232: 34.3268 | F232: 58.3436 | H232: 6.638 | I232: 29.978 | J232: 6.8956 | K232: 77.377 | L232: 58.25 | M232: 64.82 | O232: 43795 | P232: =IF(AND(B232<>"",B231<>""),LN(B232/B231),"") -> -0.0024697431 | Q232: =IF(AND(C232<>"",C231<>""),LN(C232/C231),"") -> -0.004996493 | R232: =IF(AND(D232<>"",D231<>""),LN(D232/D231),"") -> -0.015515268 | S232: =IF(AND(E232<>"",E231<>""),LN(E232/E231),"") -> -0.034653645 | T232: =IF(AND(F232<>"",F231<>""),LN(F232/F231),"") -> -0.004901958 | U232: =IF(AND(G232<>"",G231<>""),LN(G232/G231),"") | V232: =IF(AND(H232<>"",H231<>""),LN(H232/H231),"") -> -0.013229369 | W232: =IF(AND(I232<>"",I231<>""),LN(I232/I231),"") -> -0.031767045 | ... Y232: =IF(AND(K232<>"",K231<>""),LN(K232/K231),"") -> 0.00010856528 | Z232: 0.002263 | AA232: =IF(AND(L232<>"",L231<>""),LN(L232/L231),"") -> 0.0079283421 | AB232: =IF(AND(M232<>"",M231<>""),LN(M232/M231),"") -> 0.0023167823 | AE232: 43795 | AF232: 11.54 | AG232: 31.25 | AH232: 60.39 | AI232: =IF(AND(M232<>"",L232<>""),M232-L232,"") -> 6.57 | AJ232: 2.51 | AK232: 15.85 | AL232: =IF(AND(AK232<>"",AJ232<>""),AK232-AJ232,"") -> 13.34 | AM232: 1.55 | AN232: 1.58 | AO232: 1.74 | AP232: =IF(AND(AO232<>"",AN232<>""),AO232-AN232,"") -> 0.16 | AQ232: 1.62 | AR232: 117.0513 | AS232: 1459.8 | AT232: 257.879 | AU232: 101.9372 | AV232: 96.8 | AY232: 43795 | AZ232: 0 | BA232: 0 | BB232: 0 | BE232: 43795 | BF232: Pre-COVID | BG232: 1
A233: 43796 | B233: 51.6523 | C233: 89.4716 | D233: 48.0783 | E233: 34.487 | F233: 58.5538 | H233: 6.5496 | I233: 30.1594 | J233: 6.8437 | K233: 77.3939 | L233: 58.12 | M233: 65.03 | O233: 43796 | P233: =IF(AND(B233<>"",B232<>""),LN(B233/B232),"") -> -0.00058257296 | Q233: =IF(AND(C233<>"",C232<>""),LN(C233/C232),"") -> 0.0023745192 | R233: =IF(AND(D233<>"",D232<>""),LN(D233/D232),"") -> 0.0038177291 | S233: =IF(AND(E233<>"",E232<>""),LN(E233/E232),"") -> 0.0046560512 | T233: =IF(AND(F233<>"",F232<>""),LN(F233/F232),"") -> 0.00359632 | U233: =IF(AND(G233<>"",G232<>""),LN(G233/G232),"") | V233: =IF(AND(H233<>"",H232<>""),LN(H233/H232),"") -> -0.013406734 | W233: =IF(AND(I233<>"",I232<>""),LN(I233/I232),"") -> 0.0060328697 | ... Y233: =IF(AND(K233<>"",K232<>""),LN(K233/K232),"") -> 0.00021838731 | Z233: 0.004448 | AA233: =IF(AND(L233<>"",L232<>""),LN(L233/L232),"") -> -0.0022342537 | AB233: =IF(AND(M233<>"",M232<>""),LN(M233/M232),"") -> 0.0032345042 | AE233: 43796 | AF233: 11.75 | AG233: 30.82 | AH233: 57.62 | AI233: =IF(AND(M233<>"",L233<>""),M233-L233,"") -> 6.91 | AJ233: 2.46 | AK233: 15.98 | AL233: =IF(AND(AK233<>"",AJ233<>""),AK233-AJ233,"") -> 13.52 | AM233: 1.55 | AN233: 1.63 | AO233: 1.77 | AP233: =IF(AND(AO233<>"",AN233<>""),AO233-AN233,"") -> 0.14 | AQ233: 1.63 | AR233: 117.1273 | AS233: 1453.4 | AT233: 257.879 | AU233: 101.9372 | AV233: 96.8 | AY233: 43796 | AZ233: 0 | BA233: 0 | BB233: 0 | BE233: 43796 | BF233: Pre-COVID | BG233: 1
... A250: 43822 | B250: 52.8478 | C250: 91.1842 | D250: 51.4726 | E250: 36.0719 | F250: 59.8249 | H250: 7.392 | I250: 32.9931 | J250: 7.524 | K250: 77.4633 | L250: 60.51 | M250: 67.49 | O250: 43822 | P250: =IF(AND(B250<>"",B249<>""),LN(B250/B249),"") -> 0.004992783 | Q250: =IF(AND(C250<>"",C249<>""),LN(C250/C249),"") -> 0.0054168966 | R250: =IF(AND(D250<>"",D249<>""),LN(D250/D249),"") -> 0.013714454 | S250: =IF(AND(E250<>"",E249<>""),LN(E250/E249),"") -> 0.017783094 | T250: =IF(AND(F250<>"",F249<>""),LN(F250/F249),"") -> 0.022455039 | U250: =IF(AND(G250<>"",G249<>""),LN(G250/G249),"") | V250: =IF(AND(H250<>"",H249<>""),LN(H250/H249),"") -> 0.034363481 | W250: =IF(AND(I250<>"",I249<>""),LN(I250/I249),"") -> 0.032467484 | ... Y250: =IF(AND(K250<>"",K249<>""),LN(K250/K249),"") -> 0 | Z250: 0.001527 | AA250: =IF(AND(L250<>"",L249<>""),LN(L250/L249),"") -> 0.0013229703 | AB250: =IF(AND(M250<>"",M249<>""),LN(M250/M249),"") -> -0.017187349 | AE250: 43822 | AF250: 12.61 | AG250: 25.11 | AH250: 55.31 | AI250: =IF(AND(M250<>"",L250<>""),M250-L250,"") -> 6.98 | AJ250: 2.17 | AK250: 13.025 | AL250: =IF(AND(AK250<>"",AJ250<>""),AK250-AJ250,"") -> 10.855 | AM250: 1.55 | AN250: 1.64 | AO250: 1.93 | AP250: =IF(AND(AO250<>"",AN250<>""),AO250-AN250,"") -> 0.29 | AQ250: 1.75 | AR250: 115.8059 | AS250: 1482.5 | AT250: 257.879 | AU250: 101.9372 | AV250: 96.8 | AY250: 43822 | AZ250: 0 | BA250: 0 | BB250: 0 | BE250: 43822 | BF250: Pre-COVID | BG250: 1
A251: 43823 | B251: 52.6448 | C251: 91.1917 | D251: 51.5284 | E251: 36.2354 | F251: 59.175 | H251: 7.4158 | I251: 33.3386 | J251: 7.5356 | K251: 77.4718 | L251: 61.17 | M251: 69.26 | O251: 43823 | P251: =IF(AND(B251<>"",B250<>""),LN(B251/B250),"") -> -0.0038486159 | Q251: =IF(AND(C251<>"",C250<>""),LN(C251/C250),"") -> 8.2247709e-05 | R251: =IF(AND(D251<>"",D250<>""),LN(D251/D250),"") -> 0.0010834847 | S251: =IF(AND(E251<>"",E250<>""),LN(E251/E250),"") -> 0.0045223727 | T251: =IF(AND(F251<>"",F250<>""),LN(F251/F250),"") -> -0.010922807 | U251: =IF(AND(G251<>"",G250<>""),LN(G251/G250),"") | V251: =IF(AND(H251<>"",H250<>""),LN(H251/H250),"") -> 0.0032145248 | W251: =IF(AND(I251<>"",I250<>""),LN(I251/I250),"") -> 0.010417436 | ... Y251: =IF(AND(K251<>"",K250<>""),LN(K251/K250),"") -> 0.00010972336 | Z251: 3.1e-05 | AA251: =IF(AND(L251<>"",L250<>""),LN(L251/L250),"") -> 0.010848233 | AB251: =IF(AND(M251<>"",M250<>""),LN(M251/M250),"") -> 0.0258881 | AE251: 43823 | AF251: 12.67 | AG251: 25.46 | AH251: 58.32 | AI251: =IF(AND(M251<>"",L251<>""),M251-L251,"") -> 8.09 | AJ251: 2.11 | AK251: 12.605 | AL251: =IF(AND(AK251<>"",AJ251<>""),AK251-AJ251,"") -> 10.495 | AM251: 1.55 | AN251: 1.62 | AO251: 1.9 | AP251: =IF(AND(AO251<>"",AN251<>""),AO251-AN251,"") -> 0.28 | AQ251: 1.75 | AS251: 1499.1 | AT251: 257.879 | AU251: 101.9372 | AV251: 96.8 | AY251: 43823 | AZ251: 0 | BA251: 0 | BB251: 0 | BE251: 43823 | BF251: Pre-COVID | BG251: 1
A252: 43825 | B252: 52.7275 | C252: 91.3888 | D252: 51.7914 | E252: 36.4716 | F252: 59.0986 | H252: 7.5229 | I252: 33.2695 | J252: 7.5759 | K252: 77.4803 | L252: 61.72 | M252: 69.26 | O252: 43825 | P252: =IF(AND(B252<>"",B251<>""),LN(B252/B251),"") -> 0.0015696728 | Q252: =IF(AND(C252<>"",C251<>""),LN(C252/C251),"") -> 0.0021590485 | R252: =IF(AND(D252<>"",D251<>""),LN(D252/D251),"") -> 0.0050910003 | S252: =IF(AND(E252<>"",E251<>""),LN(E252/E251),"") -> 0.006497334 | T252: =IF(AND(F252<>"",F251<>""),LN(F252/F251),"") -> -0.0012919199 | U252: =IF(AND(G252<>"",G251<>""),LN(G252/G251),"") | V252: =IF(AND(H252<>"",H251<>""),LN(H252/H251),"") -> 0.014338843 | W252: =IF(AND(I252<>"",I251<>""),LN(I252/I251),"") -> -0.0020748235 | ... Y252: =IF(AND(K252<>"",K251<>""),LN(K252/K251),"") -> 0.00010971132 | Z252: 0.005309 | AA252: =IF(AND(L252<>"",L251<>""),LN(L252/L251),"") -> 0.0089511542 | AB252: =IF(AND(M252<>"",M251<>""),LN(M252/M251),"") -> 0 | AE252: 43825 | AF252: 12.65 | AG252: 24.08 | AH252: 56.42 | AI252: =IF(AND(M252<>"",L252<>""),M252-L252,"") -> 7.54 | AJ252: 2.09 | AK252: 12.605 | AL252: =IF(AND(AK252<>"",AJ252<>""),AK252-AJ252,"") -> 10.515 | AM252: 1.55 | AN252: 1.64 | AO252: 1.9 | AP252: =IF(AND(AO252<>"",AN252<>""),AO252-AN252,"") -> 0.26 | AQ252: 1.74 | AR252: 115.634 | AS252: 1509.3 | AT252: 257.879 | AU252: 101.9372 | AV252: 96.8 | AY252: 43825 | AZ252: 0 | BA252: 0 | BB252: 0 | BE252: 43825 | BF252: Pre-COVID | BG252: 1
A253: 43826 | B253: 52.547 | C253: 91.1614 | D253: 51.7754 | E253: 36.4807 | F253: 58.5634 | H253: 7.3742 | I253: 32.6994 | J253: 7.4894 | K253: 77.4718 | L253: 61.76 | M253: 68.91 | O253: 43826 | P253: =IF(AND(B253<>"",B252<>""),LN(B253/B252),"") -> -0.0034291339 | Q253: =IF(AND(C253<>"",C252<>""),LN(C253/C252),"") -> -0.0024913708 | R253: =IF(AND(D253<>"",D252<>""),LN(D253/D252),"") -> -0.00030897933 | S253: =IF(AND(E253<>"",E252<>""),LN(E253/E252),"") -> 0.00024947808 | T253: =IF(AND(F253<>"",F252<>""),LN(F253/F252),"") -> -0.0090973074 | U253: =IF(AND(G253<>"",G252<>""),LN(G253/G252),"") | V253: =IF(AND(H253<>"",H252<>""),LN(H253/H252),"") -> -0.01996428 | W253: =IF(AND(I253<>"",I252<>""),LN(I253/I252),"") -> -0.017284332 | ... Y253: =IF(AND(K253<>"",K252<>""),LN(K253/K252),"") -> -0.00010971132 | Z253: -0.000248 | AA253: =IF(AND(L253<>"",L252<>""),LN(L253/L252),"") -> 0.00064787822 | AB253: =IF(AND(M253<>"",M252<>""),LN(M253/M252),"") -> -0.0050662336 | AE253: 43826 | AF253: 13.43 | AG253: 25.16 | AH253: 55.3 | AI253: =IF(AND(M253<>"",L253<>""),M253-L253,"") -> 7.15 | AJ253: 1.75 | AK253: 12.765 | AL253: =IF(AND(AK253<>"",AJ253<>""),AK253-AJ253,"") -> 11.015 | AM253: 1.55 | AN253: 1.59 | AO253: 1.88 | AP253: =IF(AND(AO253<>"",AN253<>""),AO253-AN253,"") -> 0.29 | AQ253: 1.73 | AR253: 115.22 | AS253: 1513.8 | AT253: 257.879 | AU253: 101.9372 | AV253: 96.8 | AY253: 43826 | AZ253: 0 | BA253: 0 | BB253: 0 | BE253: 43826 | BF253: Pre-COVID | BG253: 1
...

Sheet 02_Regime
A1: MACRO REGIME DASHBOARD
A2: DEF: Regime Classification
A3: Date | B3: Regime ID | C3: Regime Name | D3: VIX | E3: OVX | F3: 2s10s | G3: WTI
A4: 43467 | B4: 0 | C4: Transition | D4: 23.22 | E4: 54.72 | F4: 0.16 | G4: 46.31
A5: 43468 | B5: 0 | C5: Transition | D5: 25.45 | E5: 53.57 | F5: 0.17 | G5: 46.92
A6: 43469 | B6: 0 | C6: Transition | D6: 21.38 | E6: 51.52 | F6: 0.17 | G6: 47.76
A7: 43472 | B7: 0 | C7: Transition | D7: 21.4 | E7: 50.42 | F7: 0.17 | G7: 48.27
A8: 43473 | B8: 0 | C8: Transition | D8: 20.47 | E8: 46.08 | F8: 0.15 | G8: 49.58
A9: 43474 | B9: 0 | C9: Transition | D9: 19.98 | E9: 44.36 | F9: 0.18 | G9: 52.19
A10: 43475 | B10: 0 | C10: Transition | D10: 19.5 | E10: 42.99 | F10: 0.18 | G10: 52.42
A11: 43476 | B11: 0 | C11: Transition | D11: 18.19 | E11: 40.99 | F11: 0.16 | G11: 51.44
A12: 43479 | B12: 0 | C12: Transition | D12: 19.07 | E12: 40.81 | F12: 0.18 | G12: 50.31
A13: 43480 | B13: 0 | C13: Transition | D13: 18.6 | E13: 39.75 | F13: 0.19 | G13: 51.8
A14: 43481 | B14: 0 | C14: Transition | D14: 19.04 | E14: 38.77 | F14: 0.18 | G14: 52.08
A15: 43482 | B15: 0 | C15: Transition | D15: 18.06 | E15: 37.03 | F15: 0.19 | G15: 51.83
... A130: 43649 | B130: 0 | C130: Transition | D130: 12.57 | E130: 36.72 | F130: 0.19 | G130: 57.06
A131: 43651 | B131: 0 | C131: Transition | D131: 13.28 | E131: 34.7 | F131: 0.17
A132: 43654 | B132: 0 | C132: Transition | D132: 13.96 | E132: 34 | F132: 0.17 | G132: 57.35
A133: 43655 | B133: 0 | C133: Transition | D133: 14.09 | E133: 30.3 | F133: 0.15 | G133: 57.57
A134: 43656 | B134: 0 | C134: Transition | D134: 13.03 | E134: 30.76 | F134: 0.25 | G134: 60.28
A135: 43657 | B135: 0 | C135: Transition | D135: 12.93 | E135: 29.86 | F135: 0.28 | G135: 59.93
A136: 43658 | B136: 0 | C136: Transition | D136: 12.39 | E136: 30.39 | F136: 0.28 | G136: 59.99
A137: 43661 | B137: 0 | C137: Transition | D137: 12.68 | E137: 30.83 | F137: 0.26 | G137: 59.3
A138: 43662 | B138: 0 | C138: Transition | D138: 12.86 | E138: 32.06 | F138: 0.26 | G138: 57.44
A139: 43663 | B139: 0 | C139: Transition | D139: 13.97 | E139: 34.94 | F139: 0.23 | G139: 56.5
A140: 43664 | B140: 0 | C140: Transition | D140: 13.53 | E140: 33.07 | F140: 0.27 | G140: 55.08
A141: 43665 | B141: 0 | C141: Transition | D141: 14.45 | E141: 34.84 | F141: 0.25 | G141: 55.42
A142: 43668 | B142: 0 | C142: Transition | D142: 13.53 | E142: 33.63 | F142: 0.25 | G142: 55.87
A143: 43669 | B143: 0 | C143: Transition | D143: 12.61 | E143: 32.25 | F143: 0.25 | G143: 56.58
... A200: 43749 | B200: 0 | C200: Transition | D200: 15.58 | E200: 39.65 | F200: 0.13 | G200: 54.76
A201: 43752 | B201: 0 | C201: Transition | D201: 14.57 | E201: 40.21 | G201: 53.57
A202: 43753 | B202: 0 | C202: Transition | D202: 13.54 | E202: 39.47 | F202: 0.16 | G202: 52.81
A203: 43754 | B203: 0 | C203: Transition | D203: 13.68 | E203: 39.47 | F203: 0.17 | G203: 53.42
A204: 43755 | B204: 0 | C204: Transition | D204: 13.79 | E204: 37.71 | F204: 0.16 | G204: 53.89
A205: 43756 | B205: 0 | C205: Transition | D205: 14.25 | E205: 36.43 | F205: 0.18 | G205: 53.75
A206: 43759 | B206: 0 | C206: Transition | D206: 14 | E206: 36.66 | F206: 0.18 | G206: 53.28
A207: 43760 | B207: 0 | C207: Transition | D207: 14.46 | E207: 35.52 | F207: 0.18 | G207: 54.21
A208: 43761 | B208: 0 | C208: Transition | D208: 14.01 | E208: 35.66 | F208: 0.19 | G208: 55.9
A209: 43762 | B209: 0 | C209: Transition | D209: 13.71 | E209: 35.95 | F209: 0.19 | G209: 56.11
A210: 43763 | B210: 0 | C210: Transition | D210: 12.65 | E210: 34.64 | F210: 0.17 | G210: 56.52
A211: 43766 | B211: 0 | C211: Transition | D211: 13.11 | E211: 35.64 | F211: 0.21 | G211: 55.6
A212: 43767 | B212: 0 | C212: Transition | D212: 13.2 | E212: 35.7 | F212: 0.2 | G212: 55.34
A213: 43768 | B213: 0 | C213: Transition | D213: 12.33 | E213: 34.36 | F213: 0.17 | G213: 54.85
... A220: 43777 | B220: 0 | C220: Transition | D220: 12.07 | E220: 31.45 | F220: 0.26 | G220: 57.02
A221: 43780 | B221: 0 | C221: Transition | D221: 12.69 | E221: 34.22
A222: 43781 | B222: 0 | C222: Transition | D222: 12.68 | E222: 33.74 | F222: 0.26 | G222: 56.67
A223: 43782 | B223: 0 | C223: Transition | D223: 13 | E223: 35.15 | F223: 0.25 | G223: 56.88
A224: 43783 | B224: 0 | C224: Transition | D224: 13.05 | E224: 33.94 | F224: 0.24 | G224: 56.57
A225: 43784 | B225: 0 | C225: Transition | D225: 12.05 | E225: 32.42 | F225: 0.23 | G225: 57.54
A226: 43787 | B226: 0 | C226: Transition | D226: 12.46 | E226: 33.68 | F226: 0.21 | G226: 56.82
A227: 43788 | B227: 0 | C227: Transition | D227: 12.86 | E227: 32.94 | F227: 0.19 | G227: 54.93
A228: 43789 | B228: 0 | C228: Transition | D228: 12.78 | E228: 32.2 | F228: 0.17 | G228: 56.71
A229: 43790 | B229: 0 | C229: Transition | D229: 13.13 | E229: 31.59 | F229: 0.17 | G229: 58.36
A230: 43791 | B230: 0 | C230: Transition | D230: 12.34 | E230: 32.38 | F230: 0.16 | G230: 57.68
A231: 43794 | B231: 0 | C231: Transition | D231: 11.87 | E231: 31.9 | F231: 0.15 | G231: 57.79
A232: 43795 | B232: 0 | C232: Transition | D232: 11.54 | E232: 31.25 | F232: 0.16 | G232: 58.25
A233: 43796 | B233: 0 | C233: Transition | D233: 11.75 | E233: 30.82 | F233: 0.14 | G233: 58.12
... A451: 44113 | B451: 0 | C451: Transition | D451: 25 | E451: 42.38 | F451: 0.63 | G451: 40.44
A452: 44116 | B452: 0 | C452: Transition | D452: 25.07 | E452: 44.04 | G452: 39.22
A453: 44117 | B453: 0 | C453: Transition | D453: 26.07 | E453: 46.07 | F453: 0.58 | G453: 40.03
A454: 44118 | B454: 0 | C454: Transition | D454: 26.4 | E454: 43.53 | F454: 0.59 | G454: 40.86
A455: 44119 | B455: 0 | C455: Transition | D455: 26.97 | E455: 43.83 | F455: 0.6 | G455: 40.84
A456: 44120 | B456: 0 | C456: Transition | D456: 27.41 | E456: 44.06 | F456: 0.62 | G456: 40.7
A457: 44123 | B457: 0 | C457: Transition | D457: 29.18 | E457: 43.35 | F457: 0.62 | G457: 40.69
A458: 44124 | B458: 0 | C458: Transition | D458: 29.35 | E458: 43.85 | F458: 0.67 | G458: 41.37
A459: 44125 | B459: 0 | C459: Transition | D459: 28.65 | E459: 47.58 | F459: 0.69 | G459: 39.88
A460: 44126 | B460: 0 | C460: Transition | D460: 28.11 | E460: 46.61 | F460: 0.71 | G460: 40.46
A461: 44127 | B461: 0 | C461: Transition | D461: 27.55 | E461: 46.32 | F461: 0.67 | G461: 39.73
A462: 44130 | B462: 0 | C462: Transition | D462: 32.46 | E462: 53.05 | F462: 0.65 | G462: 38.39
A463: 44131 | B463: 0 | C463: Transition | D463: 33.35 | E463: 50.22 | F463: 0.63 | G463: 39.34
A464: 44132 | B464: 0 | C464: Transition | D464: 40.28 | E464: 59.61 | F464: 0.63 | G464: 37.27
... A473: 44145 | B473: 0 | C473: Transition | D473: 24.8 | E473: 49.64 | F473: 0.79 | G473: 41.18
A474: 44146 | B474: 0 | C474: Transition | D474: 23.45 | E474: 49.24 | G474: 41.23
A475: 44147 | B475: 0 | C475: Transition | D475: 25.35 | E475: 50.9 | F475: 0.71 | G475: 40.9
A476: 44148 | B476: 0 | C476: Transition | D476: 23.1 | E476: 48.24 | F476: 0.72 | G476: 39.93
A477: 44151 | B477: 0 | C477: Transition | D477: 22.45 | E477: 46.89 | F477: 0.72 | G477: 41.14
A478: 44152 | B478: 0 | C478: Transition | D478: 22.71 | E478: 45.08 | F478: 0.69 | G478: 41.24
A479: 44153 | B479: 0 | C479: Transition | D479: 23.84 | E479: 46.06 | F479: 0.72 | G479: 41.64
A480: 44154 | B480: 0 | C480: Transition | D480: 23.11 | E480: 46.34 | F480: 0.68 | G480: 41.57
A481: 44155 | B481: 0 | C481: Transition | D481: 23.7 | E481: 43.94 | F481: 0.67 | G481: 41.99
A482: 44158 | B482: 0 | C482: Transition | D482: 22.66 | E482: 42.79 | F482: 0.7 | G482: 42.91
A483: 44159 | B483: 0 | C483: Transition | D483: 21.64 | E483: 42.84 | F483: 0.72 | G483: 44.71
A484: 44160 | B484: 0 | C484: Transition | D484: 21.25 | E484: 43.56 | F484: 0.71 | G484: 45.58
A485: 44162 | B485: 0 | C485: Transition | D485: 20.84 | E485: 46.21 | F485: 0.68
A486: 44165 | B486: 0 | C486: Transition | D486: 20.57 | E486: 47.37 | F486: 0.68 | G486: 45.2
A487: 44166 | B487: 0 | C487: Transition | D487: 20.77 | E487: 47.81 | F487: 0.75 | G487: 44.54
A488: 44167 | B488: 0 | C488: Transition | D488: 21.17 | E488: 45.68 | F488: 0.79 | G488: 45.23
A489: 44168 | B489: 0 | C489: Transition | D489: 21.28 | E489: 40.95 | F489: 0.76 | G489: 45.65
A490: 44169 | B490: 0 | C490: Transition | D490: 20.79 | E490: 38.34 | F490: 0.81 | G490: 46.23
A491: 44172 | B491: 0 | C491: Transition | D491: 21.3 | E491: 37.68 | F491: 0.8 | G491: 45.72
A492: 44173 | B492: 0 | C492: Transition | D492: 20.68 | E492: 37.7 | F492: 0.78 | G492: 45.64
A493: 44174 | B493: 0 | C493: Transition | D493: 22.27 | E493: 39.52 | F493: 0.79 | G493: 45.48
A494: 44175 | B494: 0 | C494: Transition | D494: 22.52 | E494: 39.7 | F494: 0.78 | G494: 46.76
A495: 44176 | B495: 0 | C495: Transition | D495: 23.31 | E495: 39.51 | F495: 0.79 | G495: 46.59
A496: 44179 | B496: 0 | C496: Transition | D496: 24.72 | E496: 39.96 | F496: 0.77 | G496: 47.02
A497: 44180 | B497: 0 | C497: Transition | D497: 22.89 | E497: 39.34 | F497: 0.81 | G497: 47.58
... A702: 44477 | B702: 0 | C702: Transition | D702: 18.77 | E702: 38 | F702: 1.29 | G702: 79.55
A703: 44480 | B703: 0 | C703: Transition | D703: 20 | E703: 38.51 | G703: 80.64
A704: 44481 | B704: 0 | C704: Transition | D704: 19.85 | E704: 37.1 | F704: 1.24 | G704: 80.75
A705: 44482 | B705: 2 | C705: Inflation Shock | D705: 18.64 | E705: 36.05 | F705: 1.19 | G705: 80.67
...

Sheet 03_Profiles
A1: COMPANY PROFILES & FUNDAMENTAL SNAPSHOT
A3: XOM — Exxon Mobil
A4: Company Name | B4: Exxon Mobil
A5: Subsector | B5: Integrated Major
A6: Market Cap | B6: 460000000000
A7: Enterprise Value | B7: 490000000000
A8: FY2025 Revenue | B8: 340000000000
A9: FY2025 EBITDA | B9: 55000000000
A10: FY2025 Net Income | B10: 33000000000
A11: FY2025 EPS | B11: 8
A12: P/E (TTM) | B12: 14
A13: EV/EBITDA | B13: 9
A14: Dividend Yield | B14: 0.035
A15: Net Debt / EBITDA | B15: 0.5
A16: FCF Yield | B16: 0.08
A17: Production | B17: 3.7M boe/d
A18: Current Price (latest) | B18: ='01_Data'!B1826 -> 160.69
A19: Oil Beta (from Tab 6) | B19: (see Tab 06_Regression)
A20: Geopolitical Sensitivity | B20: (see Tab 06_Regression)
A22: CVX — Chevron
A23: Company Name | B23: Chevron
A24: Subsector | B24: Integrated Major
A25: Market Cap | B25: 270000000000
A26: Enterprise Value | B26: 290000000000
A27: FY2025 Revenue | B27: 195000000000
A28: FY2025 EBITDA | B28: 45000000000
A29: FY2025 Net Income | B29: 18000000000
A30: FY2025 EPS | B30: 9.5
A31: P/E (TTM) | B31: 15
A32: EV/EBITDA | B32: 6.5
A33: Dividend Yield | B33: 0.043
A34: Net Debt / EBITDA | B34: 0.8
A35: FCF Yield | B35: 0.07
A36: Production | B36: 3.7M boe/d
A37: Current Price (latest) | B37: ='01_Data'!C1826 -> 198.97
A38: Oil Beta (from Tab 6) | B38: (see Tab 06_Regression)
A39: Geopolitical Sensitivity | B39: (see Tab 06_Regression)
A41: COP — ConocoPhillips
A42: Company Name | B42: ConocoPhillips
A43: Subsector | B43: Pure E&P
A44: Market Cap | B44: 120000000000
A45: Enterprise Value | B45: 130000000000
A46: FY2025 Revenue | B46: 55000000000
A47: FY2025 EBITDA | B47: 25000000000
A48: FY2025 Net Income | B48: 10000000000
A49: FY2025 EPS | B49: 7.5
A50: P/E (TTM) | B50: 12
A51: EV/EBITDA | B51: 5
A52: Dividend Yield | B52: 0.03
A53: Net Debt / EBITDA | B53: 0.4
A54: FCF Yield | B54: 0.09
A55: Production | B55: 1.9M boe/d
A56: Current Price (latest) | B56: ='01_Data'!D1826 -> 130.52
A57: Oil Beta (from Tab 6) | B57: (see Tab 06_Regression)
A58: Geopolitical Sensitivity | B58: (see Tab 06_Regression)
A60: OXY — Occidental Petroleum
A61: Company Name | B61: Occidental Petroleum
A62: Subsector | B62: E&P + Chemicals
A63: Market Cap | B63: 35000000000
A64: Enterprise Value | B64: 50000000000
A65: FY2025 Revenue | B65: 26000000000
A66: FY2025 EBITDA | B66: 12000000000
A67: FY2025 Net Income | B67: 2500000000
A68: FY2025 EPS | B68: 2.5
A69: P/E (TTM) | B69: 14
A70: EV/EBITDA | B70: 4
A71: Dividend Yield | B71: 0.02
A72: Net Debt / EBITDA | B72: 1.3
A73: FCF Yield | B73: 0.06
A74: Production | B74: 1.48M boe/d
A75: Current Price (latest) | B75: ='01_Data'!E1826 -> 62.97
A76: Oil Beta (from Tab 6) | B76: (see Tab 06_Regression)
A77: Geopolitical Sensitivity | B77: (see Tab 06_Regression)
A79: LNG — Cheniere Energy
A80: Company Name | B80: Cheniere Energy
A81: Subsector | B81: LNG Export
A82: Market Cap | B82: 50000000000
A83: Enterprise Value | B83: 70000000000
A84: FY2025 Revenue | B84: 20000000000
A85: FY2025 EBITDA | B85: 7000000000
A86: FY2025 Net Income | B86: 5000000000
A87: FY2025 EPS | B87: 20
A88: P/E (TTM) | B88: 10
A89: EV/EBITDA | B89: 10
A90: Dividend Yield | B90: 0.01
A91: Net Debt / EBITDA | B91: 3
A92: FCF Yield | B92: 0.07
A93: Production | B93: 9 trains
A94: Current Price (latest) | B94: ='01_Data'!F1826 -> 281.16
A95: Oil Beta (from Tab 6) | B95: (see Tab 06_Regression)
A96: Geopolitical Sensitivity | B96: (see Tab 06_Regression)
A98: VG — Venture Global
A99: Company Name | B99: Venture Global
A100: Subsector | B100: LNG Export (Growth)
A101: Market Cap | B101: 21000000000
A102: Enterprise Value | B102: 50000000000
A103: FY2025 Revenue | B103: 13800000000
A104: FY2025 EBITDA | B104: 6000000000
A105: FY2025 Net Income | B105: 2000000000
A106: FY2025 EPS | B106: 0.54
...

Sheet 04_Performance
A1: HISTORICAL PERFORMANCE ANALYTICS
A3: SECTION A — FULL-PERIOD DESCRIPTIVE STATISTICS
A4: DEF: Descriptive Statistics
A5: Annualized mean = AVERAGE(daily log returns) * 252. Annualized vol = STDEV.S * SQRT(252). Sharpe = (AnnMean - Rf) / AnnVol.
A6: Ticker | B6: N | C6: Ann Mean Ret | D6: Ann Volatility | E6: Skewness | F6: Excess Kurtosis | G6: Max Daily Ret | H6: Min Daily Ret | I6: Max Drawdown | J6: Sharpe Ratio | K6: Sortino Ratio | L6: Calmar Ratio
A7: XOM | B7: 1822 | C7: =AVERAGE('01_Data'!P4:P1826)*252 -> 0.16146506 | D7: =_xlfn.STDEV.S('01_Data'!P4:P1826)*SQRT(252) -> 0.31112703 | E7: =SKEW('01_Data'!P4:P1826) -> -0.22353143 | F7: =KURT('01_Data'!P4:P1826) -> 5.3132667 | G7: =MAX('01_Data'!P4:P1826) -> 0.11943962 | H7: =MIN('01_Data'!P4:P1826) -> -0.1303929 | I7: -0.60347368 | J7: =(C7-0.0319)/D7 -> 0.41643783 | K7: 0.59019745 | L7: 0.26755922
A8: CVX | B8: 1822 | C8: =AVERAGE('01_Data'!Q4:Q1826)*252 -> 0.12497697 | D8: =_xlfn.STDEV.S('01_Data'!Q4:Q1826)*SQRT(252) -> 0.3224034 | E8: =SKEW('01_Data'!Q4:Q1826) -> -1.1294611 | F8: =KURT('01_Data'!Q4:Q1826) -> 26.352214 | G8: =MAX('01_Data'!Q4:Q1826) -> 0.20490391 | H8: =MIN('01_Data'!Q4:Q1826) -> -0.25006283 | I8: -0.55773924 | J8: =(C8-0.0319)/D8 -> 0.28869722 | K8: 0.39243204 | L8: 0.22407765
A9: COP | B9: 1822 | C9: =AVERAGE('01_Data'!R4:R1826)*252 -> 0.13438777 | D9: =_xlfn.STDEV.S('01_Data'!R4:R1826)*SQRT(252) -> 0.40685414 | E9: =SKEW('01_Data'!R4:R1826) -> -0.65836002 | F9: =KURT('01_Data'!R4:R1826) -> 16.167115 | G9: =MAX('01_Data'!R4:R1826) -> 0.22485582 | H9: =MIN('01_Data'!R4:R1826) -> -0.28555004 | I9: -0.67112245 | J9: =(C9-0.0319)/D9 -> 0.25190297 | K9: 0.34987146 | L9: 0.2002433
A10: OXY | B10: 1822 | C10: =AVERAGE('01_Data'!S4:S1826)*252 -> 0.024559709 | D10: =_xlfn.STDEV.S('01_Data'!S4:S1826)*SQRT(252) -> 0.57994572 | E10: =SKEW('01_Data'!S4:S1826) -> -4.0133523 | F10: =KURT('01_Data'!S4:S1826) -> 94.331669 | G10: =MAX('01_Data'!S4:S1826) -> 0.2904131 | H10: =MIN('01_Data'!S4:S1826) -> -0.73426089 | I10: -0.85853504 | J10: =(C10-0.0319)/D10 -> -0.012656859 | K10: -0.016709129 | L10: 0.028606629
A11: LNG | B11: 1822 | C11: =AVERAGE('01_Data'!T4:T1826)*252 -> 0.21944121 | D11: =_xlfn.STDEV.S('01_Data'!T4:T1826)*SQRT(252) -> 0.33640169 | E11: =SKEW('01_Data'!T4:T1826) -> -0.87082106 | F11: =KURT('01_Data'!T4:T1826) -> 9.5353371 | G11: =MAX('01_Data'!T4:T1826) -> 0.11607337 | H11: =MIN('01_Data'!T4:T1826) -> -0.19969472 | I11: -0.57472903 | J11: =(C11-0.0319)/D11 -> 0.55749186 | K11: 0.7750267 | L11: 0.38181694
A12: VG | B12: 298 | C12: =AVERAGE('01_Data'!U4:U1826)*252 -> -0.41097944 | D12: =_xlfn.STDEV.S('01_Data'!U4:U1826)*SQRT(252) -> 0.92446522 | E12: =SKEW('01_Data'!U4:U1826) -> -1.8553034 | F12: =KURT('01_Data'!U4:U1826) -> 13.183407 | G12: =MAX('01_Data'!U4:U1826) -> 0.19160885 | H12: =MIN('01_Data'!U4:U1826) -> -0.4470775 | I12: -0.72196286 | J12: =(C12-0.0319)/D12 -> -0.47906555 | K12: -0.60210494 | L12: -0.56925345
A13: FRO | B13: 1822 | C13: =AVERAGE('01_Data'!V4:V1826)*252 -> 0.33175048 | D13: =_xlfn.STDEV.S('01_Data'!V4:V1826)*SQRT(252) -> 0.53905521 | E13: =SKEW('01_Data'!V4:V1826) -> 0.12182438 | F13: =KURT('01_Data'!V4:V1826) -> 4.4543652 | G13: =MAX('01_Data'!V4:V1826) -> 0.24408426 | H13: =MIN('01_Data'!V4:V1826) -> -0.18510162 | I13: -0.52037234 | J13: =(C13-0.0319)/D13 -> 0.55625189 | K13: 0.81423359 | L13: 0.63752486
A14: STNG | B14: 1822 | C14: =AVERAGE('01_Data'!W4:W1826)*252 -> 0.21713811 | D14: =_xlfn.STDEV.S('01_Data'!W4:W1826)*SQRT(252) -> 0.55525292 | E14: =SKEW('01_Data'!W4:W1826) -> -0.049901623 | F14: =KURT('01_Data'!W4:W1826) -> 5.0414826 | G14: =MAX('01_Data'!W4:W1826) -> 0.24837037 | H14: =MIN('01_Data'!W4:W1826) -> -0.25222154 | I14: -0.7736644 | J14: =(C14-0.0319)/D14 -> 0.33361032 | K14: 0.47961125 | L14: 0.28066208
A15: ET | B15: 1822 | C15: =AVERAGE('01_Data'!X4:X1826)*252 -> 0.13744943 | D15: =_xlfn.STDEV.S('01_Data'!X4:X1826)*SQRT(252) -> 0.35810477 | E15: =SKEW('01_Data'!X4:X1826) -> -1.8935112 | F15: =KURT('01_Data'!X4:X1826) -> 30.802747 | G15: =MAX('01_Data'!X4:X1826) -> 0.17827097 | H15: =MIN('01_Data'!X4:X1826) -> -0.32594063 | I15: -0.68524815 | J15: =(C15-0.0319)/D15 -> 0.29474456 | K15: 0.39430343 | L15: 0.20058275
A16: BIL | B16: 1822 | C16: =AVERAGE('01_Data'!Y4:Y1826)*252 -> 0.025679323 | D16: =_xlfn.STDEV.S('01_Data'!Y4:Y1826)*SQRT(252) -> 0.0024986306 | E16: =SKEW('01_Data'!Y4:Y1826) -> 0.7955491 | F16: =KURT('01_Data'!Y4:Y1826) -> 1.1535796 | G16: =MAX('01_Data'!Y4:Y1826) -> 0.00076464479 | H16: =MIN('01_Data'!Y4:Y1826) -> -0.00032770895 | I16: -0.002085089 | J16: =(C16-0.0319)/D16 -> -2.4896346 | K16: -3.4291474 | L16: 12.315708
A20: SECTION B — EVENT-WINDOW STATISTICS
A21: DEF: Event-Window Stats
A22: Ann Mean Return and Ann Volatility use AVERAGEIFS/STDEV formulas referencing Tab 1 event IDs. Skewness, Kurtosis, Max, Min, Drawdown, Sortino, Calmar remain Python-computed (complex conditionals).
A23: Event 1: Pre-COVID (2019-01-01 to 2020-02-19)
A24: Ticker | B24: N | C24: Ann Mean Ret | D24: Ann Volatility | E24: Sharpe | F24: Skewness | G24: Excess Kurtosis | H24: Max Daily Ret | I24: Min Daily Ret | J24: Max Drawdown | K24: Sortino Ratio | L24: Calmar Ratio
A25: XOM | B25: 284 | C25: =AVERAGEIFS('01_Data'!P4:P1826,'01_Data'!BG4:BG1826,1)*252 -> -0.073669367 | D25: 0.18979737 | E25: =(C25-0.0319)/D25 -> -0.55622145 | F25: 0.057366072 | G25: 1.2672612 | H25: 0.044995772 | I25: -0.042083142 | J25: -0.25459068 | K25: -0.77167215 | L25: -0.28936368
A26: CVX | B26: 284 | C26: =AVERAGEIFS('01_Data'!Q4:Q1826,'01_Data'!BG4:BG1826,1)*252 -> 0.046049826 | D26: 0.18422521 | E26: =(C26-0.0319)/D26 -> 0.076807218 | F26: -0.24345305 | G26: 2.5848465 | H26: 0.045091191 | I26: -0.050712513 | J26: -0.1431127 | K26: 0.10678032 | L26: 0.32177259
A27: COP | B27: 284 | C27: =AVERAGEIFS('01_Data'!R4:R1826,'01_Data'!BG4:BG1826,1)*252 -> -0.03376955 | D27: 0.27519087 | E27: =(C27-0.0319)/D27 -> -0.23863274 | F27: 0.29729531 | G27: 2.2433211 | H27: 0.086647823 | I27: -0.057951891 | J27: -0.27914146 | K27: -0.34138932 | L27: -0.1209778
A28: OXY | B28: 284 | C28: =AVERAGEIFS('01_Data'!S4:S1826,'01_Data'!BG4:BG1826,1)*252 -> -0.27634521 | D28: 0.29748263 | E28: =(C28-0.0319)/D28 -> -1.0361789 | F28: -0.32792522 | G28: 0.88249556 | H28: 0.05836519 | I28: -0.066611434 | J28: -0.42885951 | K28: -1.3475246 | L28: -0.64437142
A29: LNG | B29: 284 | C29: =AVERAGEIFS('01_Data'!T4:T1826,'01_Data'!BG4:BG1826,1)*252 -> -0.074531444 | D29: 0.22571715 | E29: =(C29-0.0319)/D29 -> -0.47152573 | F29: -0.097793712 | G29: 0.33791516 | H29: 0.043668581 | I29: -0.051052837 | J29: -0.22219044 | K29: -0.6496208 | L29: -0.33543924
A30: VG | B30: 0
A31: FRO | B31: 284 | C31: =AVERAGEIFS('01_Data'!V4:V1826,'01_Data'!BG4:BG1826,1)*252 -> 0.36120996 | D31: 0.52139365 | E31: =(C31-0.0319)/D31 -> 0.63159564 | F31: 0.32327409 | G31: 1.2284012 | H31: 0.12439237 | I31: -0.099497051 | J31: -0.40819418 | K31: 0.96156004 | L31: 0.88490499
A32: STNG | B32: 284 | C32: =AVERAGEIFS('01_Data'!W4:W1826,'01_Data'!BG4:BG1826,1)*252 -> 0.2103224 | D32: 0.50841709 | E32: =(C32-0.0319)/D32 -> 0.35093707 | F32: 0.0025937601 | G32: 0.68702342 | H32: 0.098265699 | I32: -0.096232037 | J32: -0.4525069 | K32: 0.50635954 | L32: 0.46479963
A33: ET | B33: 284 | C33: =AVERAGEIFS('01_Data'!X4:X1826,'01_Data'!BG4:BG1826,1)*252 -> 0.058671019 | D33: 0.25440167 | E33: =(C33-0.0319)/D33 -> 0.1052313 | F33: 0.21769342 | G33: 1.2152288 | H33: 0.061065626 | I33: -0.043828361 | J33: -0.24277761 | K33: 0.15305229 | L33: 0.24162908
A34: BIL | B34: 284 | C34: =AVERAGEIFS('01_Data'!Y4:Y1826,'01_Data'!BG4:BG1826,1)*252 -> 0.019672606 | D34: 0.0018527271 | E34: =(C34-0.0319)/D34 -> -6.5996735 | F34: 0.23452806 | G34: -0.31158464 | H34: 0.00043684263 | I34: -0.00021804265 | J34: -0.00021801888 | K34: -6.9715292 | L34: 90.234412
A36: Event 2: COVID (2020-02-20 to 2020-06-30)
A37: Ticker | B37: N | C37: Ann Mean Ret | D37: Ann Volatility | E37: Sharpe | F37: Skewness | G37: Excess Kurtosis | H37: Max Daily Ret | I37: Min Daily Ret | J37: Max Drawdown | K37: Sortino Ratio | L37: Calmar Ratio
A38: XOM | B38: 92 | C38: =AVERAGEIFS('01_Data'!P4:P1826,'01_Data'!BG4:BG1826,2)*252 -> -0.7679673 | D38: 0.72325265 | E38: =(C38-0.0319)/D38 -> -1.1059307 | F38: -0.246198 | G38: 0.62456999 | H38: 0.1194423 | I38: -0.13039107 | J38: -0.47460751 | K38: -1.4442635 | L38: -1.6181196
A39: CVX | B39: 92 | C39: =AVERAGEIFS('01_Data'!Q4:Q1826,'01_Data'!BG4:BG1826,2)*252 -> -0.55164098 | D39: 0.91647368 | E39: =(C39-0.0319)/D39 -> -0.63672421 | F39: -0.84117427 | G39: 5.4692734 | H39: 0.20490346 | I39: -0.25006221 | J39: -0.50623784 | K39: -0.81943349 | L39: -1.0896934
A40: COP | B40: 92 | C40: =AVERAGEIFS('01_Data'!R4:R1826,'01_Data'!BG4:BG1826,2)*252 -> -0.91442631 | D40: 1.0496463 | E40: =(C40-0.0319)/D40 -> -0.90156681 | F40: -0.56963894 | G40: 4.5852004 | H40: 0.22485294 | I40: -0.28555163 | J40: -0.61497959 | K40: -1.1764941 | L40: -1.4869237
A41: OXY | B41: 92 | C41: =AVERAGEIFS('01_Data'!S4:S1826,'01_Data'!BG4:BG1826,2)*252 -> -2.2253005 | D41: 1.7669188 | E41: =(C41-0.0319)/D41 -> -1.2774784 | F41: -2.8405566 | G41: 19.386793 | H41: 0.29041157 | I41: -0.73425689 | J41: -0.76766027 | K41: -1.5049344 | L41: -2.8988071
A42: LNG | B42: 92 | C42: =AVERAGEIFS('01_Data'!T4:T1826,'01_Data'!BG4:BG1826,2)*252 -> -0.37206174 | D42: 0.79854116 | E42: =(C42-0.0319)/D42 -> -0.50587466 | F42: -1.0261637 | G42: 3.1223217 | H42: 0.11607222 | I42: -0.19969497 | J42: -0.45653374 | K42: -0.64496776 | L42: -0.81496532
A43: VG | B43: 0
A44: FRO | B44: 92 | C44: =AVERAGEIFS('01_Data'!V4:V1826,'01_Data'!BG4:BG1826,2)*252 -> -0.1654488 | D44: 1.064492 | E44: =(C44-0.0319)/D44 -> -0.18539246 | F44: 0.047461439 | G44: 1.7640933 | H44: 0.24408665 | I44: -0.18510625 | J44: -0.33972612 | K44: -0.25893334 | L44: -0.48703744
A45: STNG | B45: 92 | C45: =AVERAGEIFS('01_Data'!W4:W1826,'01_Data'!BG4:BG1826,2)*252 -> -1.6125043 | D45: 1.2517812 | E45: =(C45-0.0319)/D45 -> -1.3136515 | F45: 0.038457106 | G45: 1.3803196 | H45: 0.24836862 | I45: -0.25222053 | J45: -0.51647269 | K45: -1.7660235 | L45: -3.1221732
A46: ET | B46: 92 | C46: =AVERAGEIFS('01_Data'!X4:X1826,'01_Data'!BG4:BG1826,2)*252 -> -1.4772391 | D46: 0.99275902 | E46: =(C46-0.0319)/D46 -> -1.5201464 | F46: -1.4658107 | G46: 7.3788719 | H46: 0.17829301 | I46: -0.32595 | J46: -0.63875587 | K46: -1.8214937 | L46: -2.3126736
A47: BIL | B47: 92 | C47: =AVERAGEIFS('01_Data'!Y4:Y1826,'01_Data'!BG4:BG1826,2)*252 -> 0.0057769328 | D47: 0.0023651026 | E47: =(C47-0.0319)/D47 -> -11.045215 | F47: 0.28610585 | G47: 0.28700513 | H47: 0.00043741235 | I47: -0.00032777417 | J47: -0.00085095073 | K47: -9.7032404 | L47: 6.787314
A49: Event 3: Recovery (2020-07-01 to 2022-02-23)
A50: Ticker | B50: N | C50: Ann Mean Ret | D50: Ann Volatility | E50: Sharpe | F50: Skewness | G50: Excess Kurtosis | H50: Max Daily Ret | I50: Min Daily Ret | J50: Max Drawdown | K50: Sortino Ratio | L50: Calmar Ratio
A51: XOM | B51: 416 | C51: =AVERAGEIFS('01_Data'!P4:P1826,'01_Data'!BG4:BG1826,3)*252 -> 0.39645622 | D51: 0.3332067 | E51: =(C51-0.0319)/D51 -> 1.0940843 | F51: 0.64058063 | G51: 2.1096192 | H51: 0.11920553 | I51: -0.052616812 | J51: -0.28412697 | K51: 1.7707837 | L51: 1.3953507
A52: CVX | B52: 416 | C52: =AVERAGEIFS('01_Data'!Q4:Q1826,'01_Data'!BG4:BG1826,3)*252 -> 0.3080786 | D52: 0.29381286 | E52: =(C52-0.0319)/D52 -> 0.9399813 | F52: 0.62155112 | G52: 3.1975229 | H52: 0.10970808 | I52: -0.048558694 | J52: -0.25764105 | K52: 1.4693827 | L52: 1.1957692
A53: COP | B53: 416 | C53: =AVERAGEIFS('01_Data'!R4:R1826,'01_Data'!BG4:BG1826,3)*252 -> 0.48610525 | D53: 0.40552002 | E53: =(C53-0.0319)/D53 -> 1.1200563 | F53: 0.3145885 | G53: 1.6764234 | H53: 0.13413101 | I53: -0.078252207 | J53: -0.30456265 | K53: 1.7359279 | L53: 1.5960792
A54: OXY | B54: 416 | C54: =AVERAGEIFS('01_Data'!S4:S1826,'01_Data'!BG4:BG1826,3)*252 -> 0.45528912 | D54: 0.6237793 | E54: =(C54-0.0319)/D54 -> 0.67874826 | F54: 0.63387197 | G54: 1.9101752 | H54: 0.2003072 | I54: -0.10219096 | J54: -0.51107277 | K54: 1.0721621 | L54: 0.89084867
A55: LNG | B55: 416 | C55: =AVERAGEIFS('01_Data'!T4:T1826,'01_Data'!BG4:BG1826,3)*252 -> 0.54920252 | D55: 0.30367314 | E55: =(C55-0.0319)/D55 -> 1.7034846 | F55: 0.066773067 | G55: 0.36066683 | H55: 0.059051673 | I55: -0.068025164 | J55: -0.1555029 | K55: 2.6697846 | L55: 3.5317811
A56: VG | B56: 0
A57: FRO | B57: 416 | C57: =AVERAGEIFS('01_Data'!V4:V1826,'01_Data'!BG4:BG1826,3)*252 -> 0.15998361 | D57: 0.46299202 | E57: =(C57-0.0319)/D57 -> 0.27664324 | F57: -0.094437481 | G57: 0.55666691 | H57: 0.099660614 | I57: -0.10412522 | J57: -0.3357513 | K57: 0.39564009 | L57: 0.47648208
A58: STNG | B58: 416 | C58: =AVERAGEIFS('01_Data'!W4:W1826,'01_Data'!BG4:BG1826,3)*252 -> 0.15528664 | D58: 0.61789664 | E58: =(C58-0.0319)/D58 -> 0.19968816 | F58: 0.247577 | G58: 0.39493342 | H58: 0.13474171 | I58: -0.099158794 | J58: -0.51067377 | K58: 0.29511439 | L58: 0.30408413
A59: ET | B59: 416 | C59: =AVERAGEIFS('01_Data'!X4:X1826,'01_Data'!BG4:BG1826,3)*252 -> 0.28982437 | D59: 0.39802776 | E59: =(C59-0.0319)/D59 -> 0.64800599 | F59: -0.032211682 | G59: 2.5371667 | H59: 0.091567116 | I59: -0.13190941 | J59: -0.25816253 | K59: 0.96140176 | L59: 1.1226687
A60: BIL | B60: 416 | C60: =AVERAGEIFS('01_Data'!Y4:Y1826,'01_Data'!BG4:BG1826,3)*252 -> -0.00077527526 | D60: 0.001433053 | E60: =(C60-0.0319)/D60 -> -22.801164 | F60: -0.12612692 | G60: -0.11060373 | H60: 0.00021897696 | I60: -0.00021880943 | J60: -0.0014968812 | K60: -13.075798 | L60: -0.51754323
A62: Event 4: Russia-Ukraine (2022-02-24 to 2022-12-31)
A63: Ticker | B63: N | C63: Ann Mean Ret | D63: Ann Volatility | E63: Sharpe | F63: Skewness | G63: Excess Kurtosis | H63: Max Daily Ret | I63: Min Daily Ret | J63: Max Drawdown | K63: Sortino Ratio | L63: Calmar Ratio
A64: XOM | B64: 215 | C64: =AVERAGEIFS('01_Data'!P4:P1826,'01_Data'!BG4:BG1826,4)*252 -> 0.45743159 | D64: 0.35869267 | E64: =(C64-0.0319)/D64 -> 1.1863404 | F64: -0.51786631 | G64: 0.66217279 | H64: 0.060378767 | I64: -0.082135063 | J64: -0.20508648 | K64: 1.660239 | L64: 2.2304311
A65: CVX | B65: 215 | C65: =AVERAGEIFS('01_Data'!Q4:Q1826,'01_Data'!BG4:BG1826,4)*252 -> 0.3583354 | D65: 0.34210786 | E65: =(C65-0.0319)/D65 -> 0.95418854 | F65: -0.19990115 | G65: 1.3796184 | H65: 0.085292233 | I65: -0.0693737 | J65: -0.24948942 | K65: 1.3620678 | L65: 1.4362747
A66: COP | B66: 215 | C66: =AVERAGEIFS('01_Data'!R4:R1826,'01_Data'!BG4:BG1826,4)*252 -> 0.39233381 | D66: 0.4443565 | E66: =(C66-0.0319)/D66 -> 0.81113657 | F66: -0.56109065 | G66: 1.1697036 | H66: 0.071906898 | I66: -0.10248577 | J66: -0.3297754 | K66: 1.1308312 | L66: 1.1896996
A67: OXY | B67: 215 | C67: =AVERAGEIFS('01_Data'!S4:S1826,'01_Data'!BG4:BG1826,4)*252 -> 0.58102942 | D67: 0.55011466 | E67: =(C67-0.0319)/D67 -> 0.99820902 | F67: 0.52689609 | G67: 2.6115022 | H67: 0.16204778 | I67: -0.11578323 | J67: -0.22938241 | K67: 1.5807447 | L67: 2.5330205
A68: LNG | B68: 215 | C68: =AVERAGEIFS('01_Data'!T4:T1826,'01_Data'!BG4:BG1826,4)*252 -> 0.27979483 | D68: 0.4123549 | E68: =(C68-0.0319)/D68 -> 0.60116862 | F68: -0.25347777 | G68: 0.52042578 | H68: 0.073579285 | I68: -0.089650636 | J68: -0.1784003 | K68: 0.85145103 | L68: 1.5683552
A69: VG | B69: 0
A70: FRO | B70: 215 | C70: =AVERAGEIFS('01_Data'!V4:V1826,'01_Data'!BG4:BG1826,4)*252 -> 0.42972461 | D70: 0.62389082 | E70: =(C70-0.0319)/D70 -> 0.63765102 | F70: -0.3572439 | G70: 1.7783502 | H70: 0.11663712 | I70: -0.16617964 | J70: -0.29221348 | K70: 0.91000256 | L70: 1.470592
A71: STNG | B71: 215 | C71: =AVERAGEIFS('01_Data'!W4:W1826,'01_Data'!BG4:BG1826,4)*252 -> 1.4469277 | D71: 0.54206923 | E71: =(C71-0.0319)/D71 -> 2.6104187 | F71: -0.38717852 | G71: 1.4232184 | H71: 0.095341288 | I71: -0.11501008 | J71: -0.22080339 | K71: 4.0290346 | L71: 6.5530143
A72: ET | B72: 215 | C72: =AVERAGEIFS('01_Data'!X4:X1826,'01_Data'!BG4:BG1826,4)*252 -> 0.29683198 | D72: 0.33768122 | E72: =(C72-0.0319)/D72 -> 0.78456237 | F72: -0.38868311 | G72: 0.59526714 | H72: 0.057423181 | I72: -0.071393569 | J72: -0.22502044 | K72: 1.1057655 | L72: 1.3191143
A73: BIL | B73: 215 | C73: =AVERAGEIFS('01_Data'!Y4:Y1826,'01_Data'!BG4:BG1826,4)*252 -> 0.016604337 | D73: 0.0025207003 | E73: =(C73-0.0319)/D73 -> -6.0680215 | F73: 0.76364453 | G73: 1.1840788 | H73: 0.00065685604 | I73: -0.00027368441 | J73: -0.00032813503 | K73: -6.8607476 | L73: 50.602011
A75: Event 5: Normalization (2023-01-01 to 2025-05-31)
A76: Ticker | B76: N | C76: Ann Mean Ret | D76: Ann Volatility | E76: Sharpe | F76: Skewness | G76: Excess Kurtosis | H76: Max Daily Ret | I76: Min Daily Ret | J76: Max Drawdown | K76: Sortino Ratio | L76: Calmar Ratio
A77: XOM | B77: 604 | C77: =AVERAGEIFS('01_Data'!P4:P1826,'01_Data'!BG4:BG1826,5)*252 -> 0.004127633 | D77: 0.23474966 | E77: =(C77-0.0319)/D77 -> -0.11830631 | F77: -0.31267776 | G77: 1.9732866 | H77: 0.057325437 | I77: -0.074676073 | J77: -0.1891814 | K77: -0.1619843 | L77: 0.021818836
A78: CVX | B78: 604 | C78: =AVERAGEIFS('01_Data'!Q4:Q1826,'01_Data'!BG4:BG1826,5)*252 -> -0.070291127 | D78: 0.2330952 | E78: =(C78-0.0319)/D78 -> -0.4384094 | F78: -0.9304517 | G78: 4.9872832 | H78: 0.064342211 | I78: -0.085824222 | J78: -0.22260668 | K78: -0.56255553 | L78: -0.31576422
A79: COP | B79: 604 | C79: =AVERAGEIFS('01_Data'!R4:R1826,'01_Data'!BG4:BG1826,5)*252 -> -0.10164152 | D79: 0.29281792 | E79: =(C79-0.0319)/D79 -> -0.45605652 | F79: -0.44305673 | G79: 6.4341336 | H79: 0.1017125 | I79: -0.10787697 | J79: -0.36295864 | K79: -0.60952581 | L79: -0.28003712
A80: OXY | B80: 604 | C80: =AVERAGEIFS('01_Data'!S4:S1826,'01_Data'!BG4:BG1826,5)*252 -> -0.16763135 | D80: 0.29235443 | E80: =(C80-0.0319)/D80 -> -0.68249812 | F80: -0.45184531 | G80: 6.324859 | H80: 0.10804315 | I80: -0.11661818 | J80: -0.46940055 | K80: -0.90878105 | L80: -0.35711771
A81: LNG | B81: 604 | C81: =AVERAGEIFS('01_Data'!T4:T1826,'01_Data'!BG4:BG1826,5)*252 -> 0.20140987 | D81: 0.26893821 | E81: =(C81-0.0319)/D81 -> 0.63029298 | F81: -0.50568617 | G81: 5.2350297 | H81: 0.090219128 | I81: -0.10947367 | J81: -0.22060169 | K81: 0.87983645 | L81: 0.91300203
A82: VG | B82: 87 | C82: =AVERAGEIFS('01_Data'!U4:U1826,'01_Data'!BG4:BG1826,5)*252 -> -2.1080891 | D82: 1.1666086 | E82: =(C82-0.0319)/D82 -> -1.8343676 | F82: -2.6988426 | G82: 14.177813 | H82: 0.11077441 | I82: -0.44707784 | J82: -0.67290498 | K82: -2.076387 | L82: -3.1328274
A83: FRO | B83: 604 | C83: =AVERAGEIFS('01_Data'!V4:V1826,'01_Data'!BG4:BG1826,5)*252 -> 0.28607056 | D83: 0.47985022 | E83: =(C83-0.0319)/D83 -> 0.52968729 | F83: 0.68512682 | G83: 5.9555644 | H83: 0.22860086 | I83: -0.11126667 | J83: -0.52037234 | K83: 0.80239841 | L83: 0.54974458
A84: STNG | B84: 604 | C84: =AVERAGEIFS('01_Data'!W4:W1826,'01_Data'!BG4:BG1826,5)*252 -> -0.099263408 | D84: 0.38317539 | E84: =(C84-0.0319)/D84 -> -0.34230645 | F84: -0.11878823 | G84: 1.9532728 | H84: 0.10422996 | I84: -0.11012031 | J84: -0.60967083 | K84: -0.4722424 | L84: -0.1628145
A85: ET | B85: 604 | C85: =AVERAGEIFS('01_Data'!X4:X1826,'01_Data'!BG4:BG1826,5)*252 -> 0.24956291 | D85: 0.21900929 | E85: =(C85-0.0319)/D85 -> 0.99385242 | F85: -0.53377405 | G85: 6.0212182 | H85: 0.066078905 | I85: -0.092718985 | J85: -0.24555304 | K85: 1.4169752 | L85: 1.0163237
A86: BIL | B86: 604 | C86: =AVERAGEIFS('01_Data'!Y4:Y1826,'01_Data'!BG4:BG1826,5)*252 -> 0.048357846 | D86: 0.0025864676 | E86: =(C86-0.0319)/D86 -> 6.3630592 | F86: 0.84020877 | G86: 0.63027572 | H86: 0.00076448609 | I86: -0.00021875799 | J86: -0.00021873406 | K86: 16.775117 | L86: 221.08037
A88: Event 6: 12-Day War (2025-06-01 to 2025-06-30)
A89: Ticker | B89: N | C89: Ann Mean Ret | D89: Ann Volatility | E89: Sharpe | F89: Skewness | G89: Excess Kurtosis | H89: Max Daily Ret | I89: Min Daily Ret | J89: Max Drawdown | K89: Sortino Ratio | L89: Calmar Ratio
A90: XOM | B90: 20 | C90: =AVERAGEIFS('01_Data'!P4:P1826,'01_Data'!BG4:BG1826,6)*252 -> 0.65983971 | D90: 0.24772799 | E90: =(C90-0.0319)/D90 -> 2.5347952 | F90: -0.64155729 | G90: -0.23953941 | H90: 0.02367895 | I90: -0.030900278 | J90: -0.060156893 | K90: 3.7790314 | L90: 10.968589
A91: CVX | B91: 20 | C91: =AVERAGEIFS('01_Data'!Q4:Q1826,'01_Data'!BG4:BG1826,6)*252 -> 0.58443788 | D91: 0.19496914 | E91: =(C91-0.0319)/D91 -> 2.833976 | F91: -0.32870192 | G91: -0.15322633 | H91: 0.023890795 | I91: -0.022796347 | J91: -0.042527605 | K91: 4.5112319 | L91: 13.742474
A92: COP | B92: 20 | C92: =AVERAGEIFS('01_Data'!R4:R1826,'01_Data'!BG4:BG1826,6)*252 -> 0.63196157 | D92: 0.3059207 | E92: =(C92-0.0319)/D92 -> 1.9614938 | F92: -0.24235008 | G92: -1.0501866 | H92: 0.035044429 | I92: -0.031976959 | J92: -0.082095636 | K92: 3.0276196 | L92: 7.6979427
A93: OXY | B93: 20 | C93: =AVERAGEIFS('01_Data'!S4:S1826,'01_Data'!BG4:BG1826,6)*252 -> 0.44454185 | D93: 0.33562554 | E93: =(C93-0.0319)/D93 -> 1.229471 | F93: -0.29897277 | G93: -0.83427676 | H93: 0.037061738 | I93: -0.037512775 | J93: -0.095586853 | K93: 1.814144 | L93: 4.6507518
A94: LNG | B94: 20 | C94: =AVERAGEIFS('01_Data'!T4:T1826,'01_Data'!BG4:BG1826,6)*252 -> 0.34248185 | D94: 0.32747452 | E94: =(C94-0.0319)/D94 -> 0.9484153 | F94: -1.2787119 | G94: 3.1832891 | H94: 0.031411295 | I94: -0.060670835 | J94: -0.063643465 | K94: 1.2682066 | L94: 5.3812682
A95: VG | B95: 20 | C95: =AVERAGEIFS('01_Data'!U4:U1826,'01_Data'!BG4:BG1826,6)*252 -> 3.762988 | D95: 1.0530228 | E95: =(C95-0.0319)/D95 -> 3.5432165 | F95: 0.28147147 | G95: 2.6181841 | H95: 0.1916082 | I95: -0.13918356 | J95: -0.1804314 | K95: 6.2142622 | L95: 20.855733
A96: FRO | B96: 20 | C96: =AVERAGEIFS('01_Data'!V4:V1826,'01_Data'!BG4:BG1826,6)*252 -> -1.2328071 | D96: 0.49725705 | E96: =(C96-0.0319)/D96 -> -2.5433668 | F96: 0.74671881 | G96: 0.67564286 | H96: 0.071928105 | I96: -0.05817198 | J96: -0.16995445 | K96: -3.5656885 | L96: -7.2538993
A97: STNG | B97: 20 | C97: =AVERAGEIFS('01_Data'!W4:W1826,'01_Data'!BG4:BG1826,6)*252 -> -0.19490281 | D97: 0.43596217 | E97: =(C97-0.0319)/D97 -> -0.52023507 | F97: 0.43969751 | G97: 0.68063261 | H97: 0.065156665 | I97: -0.046212932 | J97: -0.11670423 | K97: -0.77077398 | L97: -1.6700932
A98: ET | B98: 20 | C98: =AVERAGEIFS('01_Data'!X4:X1826,'01_Data'!BG4:BG1826,6)*252 -> 0.46001808 | D98: 0.20615844 | E98: =(C98-0.0319)/D98 -> 2.0766459 | F98: 0.39487528 | G98: -0.40711666 | H98: 0.028453788 | I98: -0.020886953 | J98: -0.04390245 | K98: 3.7005152 | L98: 10.478564
A99: BIL | B99: 20 | C99: =AVERAGEIFS('01_Data'!Y4:Y1826,'01_Data'!BG4:BG1826,6)*252 -> 0.042105991 | D99: 0.0020554829 | E99: =(C99-0.0319)/D99 -> 4.9652523 | F99: 0.65290604 | G99: 0.1672646 | H99: 0.00043674042 | I99: 0 | J99: 0 | K99: 11.193937 | L99: 0
A101: Event 7: Iran Conflict (2026-02-28 to 2026-04-04)
A102: Ticker | B102: N | C102: Ann Mean Ret | D102: Ann Volatility | E102: Sharpe | F102: Skewness | G102: Excess Kurtosis | H102: Max Daily Ret | I102: Min Daily Ret | J102: Max Drawdown | K102: Sortino Ratio | L102: Calmar Ratio
A103: XOM | B103: 24 | C103: =AVERAGEIFS('01_Data'!P4:P1826,'01_Data'!BG4:BG1826,7)*252 -> 0.54928069 | D103: 0.2816121 | E103: =(C103-0.0319)/D103 -> 1.8372105 | F103: -1.1639471 | G103: 3.20603 | H103: 0.033057007 | I103: -0.053759493 | J103: -0.062868133 | K103: 2.5403792 | L103: 8.7370315
A104: CVX | B104: 24 | C104: =AVERAGEIFS('01_Data'!Q4:Q1826,'01_Data'!BG4:BG1826,7)*252 -> 0.66496174 | D104: 0.26164283 | E104: =(C104-0.0319)/D104 -> 2.4195646 | F104: -1.0275653 | G104: 2.3354519 | H104: 0.029096425 | I104: -0.046952752 | J104: -0.065072179 | K104: 3.4775685 | L104: 10.218839
A105: COP | B105: 24 | C105: =AVERAGEIFS('01_Data'!R4:R1826,'01_Data'!BG4:BG1826,7)*252 -> 1.4707993 | D105: 0.2756795 | E105: =(C105-0.0319)/D105 -> 5.2194642 | F105: -0.13227071 | G105: 0.052612923 | H105: 0.041266095 | I105: -0.027807269 | J105: -0.040508207 | K105: 9.5887628 | L105: 36.308684
A106: OXY | B106: 24 | C106: =AVERAGEIFS('01_Data'!S4:S1826,'01_Data'!BG4:BG1826,7)*252 -> 1.8437407 | D106: 0.35066473 | E106: =(C106-0.0319)/D106 -> 5.1668747 | F106: -0.22408411 | G106: 0.37243855 | H106: 0.049663648 | I106: -0.043550079 | J106: -0.060537416 | K106: 9.3113798 | L106: 30.456331
A107: LNG | B107: 24 | C107: =AVERAGEIFS('01_Data'!T4:T1826,'01_Data'!BG4:BG1826,7)*252 -> 1.8504866 | D107: 0.41911014 | E107: =(C107-0.0319)/D107 -> 4.3391616 | F107: 0.31760382 | G107: -0.34662308 | H107: 0.057122915 | I107: -0.03520398 | J107: -0.070964289 | K107: 8.5732447 | L107: 26.076312
A108: VG | B108: 24 | C108: =AVERAGEIFS('01_Data'!U4:U1826,'01_Data'!BG4:BG1826,7)*252 -> 4.347384 | D108: 1.0316088 | E108: =(C108-0.0319)/D108 -> 4.1832563 | F108: 0.49875254 | G108: -0.23720958 | H108: 0.16076305 | I108: -0.08091113 | J108: -0.16486025 | K108: 8.5700205 | L108: 26.370214
A109: FRO | B109: 24 | C109: =AVERAGEIFS('01_Data'!V4:V1826,'01_Data'!BG4:BG1826,7)*252 -> -0.052426277 | D109: 0.58316733 | E109: =(C109-0.0319)/D109 -> -0.14460048 | F109: -0.034436364 | G109: -1.1326517 | H109: 0.053229775 | I109: -0.064639545 | J109: -0.2141 | K109: -0.20898682 | L109: -0.24484388
A110: STNG | B110: 24 | C110: =AVERAGEIFS('01_Data'!W4:W1826,'01_Data'!BG4:BG1826,7)*252 -> -0.29768874 | D110: 0.49222809 | E110: =(C110-0.0319)/D110 -> -0.6695854 | F110: -0.37143549 | G110: 0.86737645 | H110: 0.06092422 | I110: -0.083073104 | J110: -0.16846012 | K110: -0.91198332 | L110: -1.7671524
...

Sheet 05_Correlation
A1: CORRELATION & COVARIANCE STRUCTURE
A3: SECTION A — FULL-PERIOD CORRELATION MATRIX
B4: XOM | C4: CVX | D4: COP | E4: OXY | F4: LNG | G4: VG | H4: FRO | I4: STNG | J4: ET | K4: BIL | L4: WTI | M4: Brent
A5: XOM | B5: 1 | C5: =CORREL('01_Data'!P4:P1826,'01_Data'!Q4:Q1826) -> 0.84790641 | D5: =CORREL('01_Data'!P4:P1826,'01_Data'!R4:R1826) -> 0.83449867 | E5: =CORREL('01_Data'!P4:P1826,'01_Data'!S4:S1826) -> 0.72397767 | F5: =CORREL('01_Data'!P4:P1826,'01_Data'!T4:T1826) -> 0.57684879 | G5: =CORREL('01_Data'!P4:P1826,'01_Data'!U4:U1826) -> 0.3361197 | H5: =CORREL('01_Data'!P4:P1826,'01_Data'!V4:V1826) -> 0.31959281 | I5: =CORREL('01_Data'!P4:P1826,'01_Data'!W4:W1826) -> 0.36632167 | J5: =CORREL('01_Data'!P4:P1826,'01_Data'!X4:X1826) -> 0.60902196 | K5: =CORREL('01_Data'!P4:P1826,'01_Data'!Y4:Y1826) -> -0.0042736182 | L5: {=CORREL(_xlfn._xlws.FILTER('01_Data'!AA4:AA1826,ISNUMBER('01_Data'!AA4:AA1826)*ISNUMBER('01_Data'!P4:P1826)),_xlfn._xlws.FILTER('01_Data'!P4:P1826,ISNUMBER('01_Data'!AA4:AA1826)*ISNUMBER('01_Data'!P4:P1826)))} -> 0.44116388 | M5: =CORREL('01_Data'!P4:P1826,'01_Data'!AB4:AB1826) -> 0.4398667
A6: CVX | B6: =CORREL('01_Data'!Q4:Q1826,'01_Data'!P4:P1826) -> 0.84790641 | C6: 1 | D6: =CORREL('01_Data'!Q4:Q1826,'01_Data'!R4:R1826) -> 0.83933531 | E6: =CORREL('01_Data'!Q4:Q1826,'01_Data'!S4:S1826) -> 0.69291243 | F6: =CORREL('01_Data'!Q4:Q1826,'01_Data'!T4:T1826) -> 0.57244496 | G6: =CORREL('01_Data'!Q4:Q1826,'01_Data'!U4:U1826) -> 0.31809397 | H6: =CORREL('01_Data'!Q4:Q1826,'01_Data'!V4:V1826) -> 0.30644426 | I6: =CORREL('01_Data'!Q4:Q1826,'01_Data'!W4:W1826) -> 0.34248853 | J6: =CORREL('01_Data'!Q4:Q1826,'01_Data'!X4:X1826) -> 0.59270514 | K6: =CORREL('01_Data'!Q4:Q1826,'01_Data'!Y4:Y1826) -> 0.014949306 | L6: {=CORREL(_xlfn._xlws.FILTER('01_Data'!AA4:AA1826,ISNUMBER('01_Data'!AA4:AA1826)*ISNUMBER('01_Data'!Q4:Q1826)),_xlfn._xlws.FILTER('01_Data'!Q4:Q1826,ISNUMBER('01_Data'!AA4:AA1826)*ISNUMBER('01_Data'!Q4:Q1826)))} -> 0.38418986 | M6: =CORREL('01_Data'!Q4:Q1826,'01_Data'!AB4:AB1826) -> 0.43830841
A7: COP | B7: =CORREL('01_Data'!R4:R1826,'01_Data'!P4:P1826) -> 0.83449867 | C7: =CORREL('01_Data'!R4:R1826,'01_Data'!Q4:Q1826) -> 0.83933531 | D7: 1 | E7: =CORREL('01_Data'!R4:R1826,'01_Data'!S4:S1826) -> 0.77072137 | F7: =CORREL('01_Data'!R4:R1826,'01_Data'!T4:T1826) -> 0.60812662 | G7: =CORREL('01_Data'!R4:R1826,'01_Data'!U4:U1826) -> 0.40277095 | H7: =CORREL('01_Data'!R4:R1826,'01_Data'!V4:V1826) -> 0.29138974 | I7: =CORREL('01_Data'!R4:R1826,'01_Data'!W4:W1826) -> 0.34384204 | J7: =CORREL('01_Data'!R4:R1826,'01_Data'!X4:X1826) -> 0.63543307 | K7: =CORREL('01_Data'!R4:R1826,'01_Data'!Y4:Y1826) -> -0.032598091 | L7: {=CORREL(_xlfn._xlws.FILTER('01_Data'!AA4:AA1826,ISNUMBER('01_Data'!AA4:AA1826)*ISNUMBER('01_Data'!R4:R1826)),_xlfn._xlws.FILTER('01_Data'!R4:R1826,ISNUMBER('01_Data'!AA4:AA1826)*ISNUMBER('01_Data'!R4:R1826)))} -> 0.46716242 | M7: =CORREL('01_Data'!R4:R1826,'01_Data'!AB4:AB1826) -> 0.4908569
A8: OXY | B8: =CORREL('01_Data'!S4:S1826,'01_Data'!P4:P1826) -> 0.72397767 | C8: =CORREL('01_Data'!S4:S1826,'01_Data'!Q4:Q1826) -> 0.69291243 | D8: =CORREL('01_Data'!S4:S1826,'01_Data'!R4:R1826) -> 0.77072137 | E8: 1 | F8: =CORREL('01_Data'!S4:S1826,'01_Data'!T4:T1826) -> 0.52283827 | G8: =CORREL('01_Data'!S4:S1826,'01_Data'!U4:U1826) -> 0.3936207 | H8: =CORREL('01_Data'!S4:S1826,'01_Data'!V4:V1826) -> 0.2347108 | I8: =CORREL('01_Data'!S4:S1826,'01_Data'!W4:W1826) -> 0.33695109 | J8: =CORREL('01_Data'!S4:S1826,'01_Data'!X4:X1826) -> 0.6378799 | K8: =CORREL('01_Data'!S4:S1826,'01_Data'!Y4:Y1826) -> -0.029790588 | L8: {=CORREL(_xlfn._xlws.FILTER('01_Data'!AA4:AA1826,ISNUMBER('01_Data'!AA4:AA1826)*ISNUMBER('01_Data'!S4:S1826)),_xlfn._xlws.FILTER('01_Data'!S4:S1826,ISNUMBER('01_Data'!AA4:AA1826)*ISNUMBER('01_Data'!S4:S1826)))} -> 0.45176201 | M8: =CORREL('01_Data'!S4:S1826,'01_Data'!AB4:AB1826) -> 0.44376945
A9: LNG | B9: =CORREL('01_Data'!T4:T1826,'01_Data'!P4:P1826) -> 0.57684879 | C9: =CORREL('01_Data'!T4:T1826,'01_Data'!Q4:Q1826) -> 0.57244496 | D9: =CORREL('01_Data'!T4:T1826,'01_Data'!R4:R1826) -> 0.60812662 | E9: =CORREL('01_Data'!T4:T1826,'01_Data'!S4:S1826) -> 0.52283827 | F9: 1 | G9: =CORREL('01_Data'!T4:T1826,'01_Data'!U4:U1826) -> 0.4416468 | H9: =CORREL('01_Data'!T4:T1826,'01_Data'!V4:V1826) -> 0.25999691 | I9: =CORREL('01_Data'!T4:T1826,'01_Data'!W4:W1826) -> 0.26542351 | J9: =CORREL('01_Data'!T4:T1826,'01_Data'!X4:X1826) -> 0.53848603 | K9: =CORREL('01_Data'!T4:T1826,'01_Data'!Y4:Y1826) -> -0.012371437 | L9: {=CORREL(_xlfn._xlws.FILTER('01_Data'!AA4:AA1826,ISNUMBER('01_Data'!AA4:AA1826)*ISNUMBER('01_Data'!T4:T1826)),_xlfn._xlws.FILTER('01_Data'!T4:T1826,ISNUMBER('01_Data'!AA4:AA1826)*ISNUMBER('01_Data'!T4:T1826)))} -> 0.25485053 | M9: =CORREL('01_Data'!T4:T1826,'01_Data'!AB4:AB1826) -> 0.27973489
A10: VG | B10: =CORREL('01_Data'!U4:U1826,'01_Data'!P4:P1826) -> 0.3361197 | C10: =CORREL('01_Data'!U4:U1826,'01_Data'!Q4:Q1826) -> 0.31809397 | D10: =CORREL('01_Data'!U4:U1826,'01_Data'!R4:R1826) -> 0.40277095 | E10: =CORREL('01_Data'!U4:U1826,'01_Data'!S4:S1826) -> 0.3936207 | F10: =CORREL('01_Data'!U4:U1826,'01_Data'!T4:T1826) -> 0.4416468 | G10: 1 | H10: =CORREL('01_Data'!U4:U1826,'01_Data'!V4:V1826) -> 0.13661704 | I10: =CORREL('01_Data'!U4:U1826,'01_Data'!W4:W1826) -> 0.17215277 | J10: =CORREL('01_Data'!U4:U1826,'01_Data'!X4:X1826) -> 0.4846497 | K10: =CORREL('01_Data'!U4:U1826,'01_Data'!Y4:Y1826) -> 0.018934322 | L10: {=CORREL(_xlfn._xlws.FILTER('01_Data'!AA4:AA1826,ISNUMBER('01_Data'!AA4:AA1826)*ISNUMBER('01_Data'!U4:U1826)),_xlfn._xlws.FILTER('01_Data'!U4:U1826,ISNUMBER('01_Data'!AA4:AA1826)*ISNUMBER('01_Data'!U4:U1826)))} -> 0.37109915 | M10: =CORREL('01_Data'!U4:U1826,'01_Data'!AB4:AB1826) -> 0.36154424
A11: FRO | B11: =CORREL('01_Data'!V4:V1826,'01_Data'!P4:P1826) -> 0.31959281 | C11: =CORREL('01_Data'!V4:V1826,'01_Data'!Q4:Q1826) -> 0.30644426 | D11: =CORREL('01_Data'!V4:V1826,'01_Data'!R4:R1826) -> 0.29138974 | E11: =CORREL('01_Data'!V4:V1826,'01_Data'!S4:S1826) -> 0.2347108 | F11: =CORREL('01_Data'!V4:V1826,'01_Data'!T4:T1826) -> 0.25999691 | G11: =CORREL('01_Data'!V4:V1826,'01_Data'!U4:U1826) -> 0.13661704 | H11: 1 | I11: =CORREL('01_Data'!V4:V1826,'01_Data'!W4:W1826) -> 0.69327196 | J11: =CORREL('01_Data'!V4:V1826,'01_Data'!X4:X1826) -> 0.24225657 | K11: =CORREL('01_Data'!V4:V1826,'01_Data'!Y4:Y1826) -> -0.020304148 | L11: {=CORREL(_xlfn._xlws.FILTER('01_Data'!AA4:AA1826,ISNUMBER('01_Data'!AA4:AA1826)*ISNUMBER('01_Data'!V4:V1826)),_xlfn._xlws.FILTER('01_Data'!V4:V1826,ISNUMBER('01_Data'!AA4:AA1826)*ISNUMBER('01_Data'!V4:V1826)))} -> 0.11502023 | M11: =CORREL('01_Data'!V4:V1826,'01_Data'!AB4:AB1826) -> 0.091249814
A12: STNG | B12: =CORREL('01_Data'!W4:W1826,'01_Data'!P4:P1826) -> 0.36632167 | C12: =CORREL('01_Data'!W4:W1826,'01_Data'!Q4:Q1826) -> 0.34248853 | D12: =CORREL('01_Data'!W4:W1826,'01_Data'!R4:R1826) -> 0.34384204 | E12: =CORREL('01_Data'!W4:W1826,'01_Data'!S4:S1826) -> 0.33695109 | F12: =CORREL('01_Data'!W4:W1826,'01_Data'!T4:T1826) -> 0.26542351 | G12: =CORREL('01_Data'!W4:W1826,'01_Data'!U4:U1826) -> 0.17215277 | H12: =CORREL('01_Data'!W4:W1826,'01_Data'!V4:V1826) -> 0.69327196 | I12: 1 | J12: =CORREL('01_Data'!W4:W1826,'01_Data'!X4:X1826) -> 0.32705227 | K12: =CORREL('01_Data'!W4:W1826,'01_Data'!Y4:Y1826) -> -0.011514746 | L12: {=CORREL(_xlfn._xlws.FILTER('01_Data'!AA4:AA1826,ISNUMBER('01_Data'!AA4:AA1826)*ISNUMBER('01_Data'!W4:W1826)),_xlfn._xlws.FILTER('01_Data'!W4:W1826,ISNUMBER('01_Data'!AA4:AA1826)*ISNUMBER('01_Data'!W4:W1826)))} -> 0.1384478 | M12: =CORREL('01_Data'!W4:W1826,'01_Data'!AB4:AB1826) -> 0.10688096
A13: ET | B13: =CORREL('01_Data'!X4:X1826,'01_Data'!P4:P1826) -> 0.60902196 | C13: =CORREL('01_Data'!X4:X1826,'01_Data'!Q4:Q1826) -> 0.59270514 | D13: =CORREL('01_Data'!X4:X1826,'01_Data'!R4:R1826) -> 0.63543307 | E13: =CORREL('01_Data'!X4:X1826,'01_Data'!S4:S1826) -> 0.6378799 | F13: =CORREL('01_Data'!X4:X1826,'01_Data'!T4:T1826) -> 0.53848603 | G13: =CORREL('01_Data'!X4:X1826,'01_Data'!U4:U1826) -> 0.4846497 | H13: =CORREL('01_Data'!X4:X1826,'01_Data'!V4:V1826) -> 0.24225657 | I13: =CORREL('01_Data'!X4:X1826,'01_Data'!W4:W1826) -> 0.32705227 | J13: 1 | K13: =CORREL('01_Data'!X4:X1826,'01_Data'!Y4:Y1826) -> -0.0084966878 | L13: {=CORREL(_xlfn._xlws.FILTER('01_Data'!AA4:AA1826,ISNUMBER('01_Data'!AA4:AA1826)*ISNUMBER('01_Data'!X4:X1826)),_xlfn._xlws.FILTER('01_Data'!X4:X1826,ISNUMBER('01_Data'!AA4:AA1826)*ISNUMBER('01_Data'!X4:X1826)))} -> 0.40912485 | M13: =CORREL('01_Data'!X4:X1826,'01_Data'!AB4:AB1826) -> 0.36256818
A14: BIL | B14: =CORREL('01_Data'!Y4:Y1826,'01_Data'!P4:P1826) -> -0.0042736182 | C14: =CORREL('01_Data'!Y4:Y1826,'01_Data'!Q4:Q1826) -> 0.014949306 | D14: =CORREL('01_Data'!Y4:Y1826,'01_Data'!R4:R1826) -> -0.032598091 | E14: =CORREL('01_Data'!Y4:Y1826,'01_Data'!S4:S1826) -> -0.029790588 | F14: =CORREL('01_Data'!Y4:Y1826,'01_Data'!T4:T1826) -> -0.012371437 | G14: =CORREL('01_Data'!Y4:Y1826,'01_Data'!U4:U1826) -> 0.018934322 | H14: =CORREL('01_Data'!Y4:Y1826,'01_Data'!V4:V1826) -> -0.020304148 | I14: =CORREL('01_Data'!Y4:Y1826,'01_Data'!W4:W1826) -> -0.011514746 | J14: =CORREL('01_Data'!Y4:Y1826,'01_Data'!X4:X1826) -> -0.0084966878 | K14: 1 | L14: {=CORREL(_xlfn._xlws.FILTER('01_Data'!AA4:AA1826,ISNUMBER('01_Data'!AA4:AA1826)*ISNUMBER('01_Data'!Y4:Y1826)),_xlfn._xlws.FILTER('01_Data'!Y4:Y1826,ISNUMBER('01_Data'!AA4:AA1826)*ISNUMBER('01_Data'!Y4:Y1826)))} -> -0.054642847 | M14: =CORREL('01_Data'!Y4:Y1826,'01_Data'!AB4:AB1826) -> -0.019803286
A15: WTI | B15: {=CORREL(_xlfn._xlws.FILTER('01_Data'!AA4:AA1826,ISNUMBER('01_Data'!AA4:AA1826)*ISNUMBER('01_Data'!P4:P1826)),_xlfn._xlws.FILTER('01_Data'!P4:P1826,ISNUMBER('01_Data'!AA4:AA1826)*ISNUMBER('01_Data'!P4:P1826)))} -> 0.44116388 | C15: {=CORREL(_xlfn._xlws.FILTER('01_Data'!AA4:AA1826,ISNUMBER('01_Data'!AA4:AA1826)*ISNUMBER('01_Data'!Q4:Q1826)),_xlfn._xlws.FILTER('01_Data'!Q4:Q1826,ISNUMBER('01_Data'!AA4:AA1826)*ISNUMBER('01_Data'!Q4:Q1826)))} -> 0.38418986 | D15: {=CORREL(_xlfn._xlws.FILTER('01_Data'!AA4:AA1826,ISNUMBER('01_Data'!AA4:AA1826)*ISNUMBER('01_Data'!R4:R1826)),_xlfn._xlws.FILTER('01_Data'!R4:R1826,ISNUMBER('01_Data'!AA4:AA1826)*ISNUMBER('01_Data'!R4:R1826)))} -> 0.46716242 | E15: {=CORREL(_xlfn._xlws.FILTER('01_Data'!AA4:AA1826,ISNUMBER('01_Data'!AA4:AA1826)*ISNUMBER('01_Data'!S4:S1826)),_xlfn._xlws.FILTER('01_Data'!S4:S1826,ISNUMBER('01_Data'!AA4:AA1826)*ISNUMBER('01_Data'!S4:S1826)))} -> 0.45176201 | F15: {=CORREL(_xlfn._xlws.FILTER('01_Data'!AA4:AA1826,ISNUMBER('01_Data'!AA4:AA1826)*ISNUMBER('01_Data'!T4:T1826)),_xlfn._xlws.FILTER('01_Data'!T4:T1826,ISNUMBER('01_Data'!AA4:AA1826)*ISNUMBER('01_Data'!T4:T1826)))} -> 0.25485053 | G15: {=CORREL(_xlfn._xlws.FILTER('01_Data'!AA4:AA1826,ISNUMBER('01_Data'!AA4:AA1826)*ISNUMBER('01_Data'!U4:U1826)),_xlfn._xlws.FILTER('01_Data'!U4:U1826,ISNUMBER('01_Data'!AA4:AA1826)*ISNUMBER('01_Data'!U4:U1826)))} -> 0.37109915 | H15: {=CORREL(_xlfn._xlws.FILTER('01_Data'!AA4:AA1826,ISNUMBER('01_Data'!AA4:AA1826)*ISNUMBER('01_Data'!V4:V1826)),_xlfn._xlws.FILTER('01_Data'!V4:V1826,ISNUMBER('01_Data'!AA4:AA1826)*ISNUMBER('01_Data'!V4:V1826)))} -> 0.11502023 | I15: {=CORREL(_xlfn._xlws.FILTER('01_Data'!AA4:AA1826,ISNUMBER('01_Data'!AA4:AA1826)*ISNUMBER('01_Data'!W4:W1826)),_xlfn._xlws.FILTER('01_Data'!W4:W1826,ISNUMBER('01_Data'!AA4:AA1826)*ISNUMBER('01_Data'!W4:W1826)))} -> 0.1384478 | J15: {=CORREL(_xlfn._xlws.FILTER('01_Data'!AA4:AA1826,ISNUMBER('01_Data'!AA4:AA1826)*ISNUMBER('01_Data'!X4:X1826)),_xlfn._xlws.FILTER('01_Data'!X4:X1826,ISNUMBER('01_Data'!AA4:AA1826)*ISNUMBER('01_Data'!X4:X1826)))} -> 0.40912485 | K15: {=CORREL(_xlfn._xlws.FILTER('01_Data'!AA4:AA1826,ISNUMBER('01_Data'!AA4:AA1826)*ISNUMBER('01_Data'!Y4:Y1826)),_xlfn._xlws.FILTER('01_Data'!Y4:Y1826,ISNUMBER('01_Data'!AA4:AA1826)*ISNUMBER('01_Data'!Y4:Y1826)))} -> -0.054642847 | L15: 1 | M15: {=CORREL(_xlfn._xlws.FILTER('01_Data'!AA4:AA1826,ISNUMBER('01_Data'!AA4:AA1826)*ISNUMBER('01_Data'!AB4:AB1826)),_xlfn._xlws.FILTER('01_Data'!AB4:AB1826,ISNUMBER('01_Data'!AA4:AA1826)*ISNUMBER('01_Data'!AB4:AB1826)))} -> 0.69875852
A16: Brent | B16: =CORREL('01_Data'!AB4:AB1826,'01_Data'!P4:P1826) -> 0.4398667 | C16: =CORREL('01_Data'!AB4:AB1826,'01_Data'!Q4:Q1826) -> 0.43830841 | D16: =CORREL('01_Data'!AB4:AB1826,'01_Data'!R4:R1826) -> 0.4908569 | E16: =CORREL('01_Data'!AB4:AB1826,'01_Data'!S4:S1826) -> 0.44376945 | F16: =CORREL('01_Data'!AB4:AB1826,'01_Data'!T4:T1826) -> 0.27973489 | G16: =CORREL('01_Data'!AB4:AB1826,'01_Data'!U4:U1826) -> 0.36154424 | H16: =CORREL('01_Data'!AB4:AB1826,'01_Data'!V4:V1826) -> 0.091249814 | I16: =CORREL('01_Data'!AB4:AB1826,'01_Data'!W4:W1826) -> 0.10688096 | J16: =CORREL('01_Data'!AB4:AB1826,'01_Data'!X4:X1826) -> 0.36256818 | K16: =CORREL('01_Data'!AB4:AB1826,'01_Data'!Y4:Y1826) -> -0.019803286 | L16: {=CORREL(_xlfn._xlws.FILTER('01_Data'!AA4:AA1826,ISNUMBER('01_Data'!AA4:AA1826)*ISNUMBER('01_Data'!AB4:AB1826)),_xlfn._xlws.FILTER('01_Data'!AB4:AB1826,ISNUMBER('01_Data'!AA4:AA1826)*ISNUMBER('01_Data'!AB4:AB1826)))} -> 0.69875852 | M16: 1
A20: SECTION B — FULL-PERIOD COVARIANCE MATRIX (ANNUALIZED)
B21: XOM | C21: CVX | D21: COP | E21: OXY | F21: LNG | G21: VG | H21: FRO | I21: STNG | J21: ET | K21: BIL | L21: WTI | M21: Brent
A22: XOM | B22: =_xlfn.COVARIANCE.S('01_Data'!P4:P1826,'01_Data'!P4:P1826)*252 -> 0.096800027 | C22: =_xlfn.COVARIANCE.S('01_Data'!P4:P1826,'01_Data'!Q4:Q1826)*252 -> 0.085052144 | D22: =_xlfn.COVARIANCE.S('01_Data'!P4:P1826,'01_Data'!R4:R1826)*252 -> 0.10563361 | E22: =_xlfn.COVARIANCE.S('01_Data'!P4:P1826,'01_Data'!S4:S1826)*252 -> 0.13063221 | F22: =_xlfn.COVARIANCE.S('01_Data'!P4:P1826,'01_Data'!T4:T1826)*252 -> 0.060375104 | G22: {=_xlfn.COVARIANCE.S(_xlfn._xlws.FILTER('01_Data'!P4:P1826,ISNUMBER('01_Data'!P4:P1826)*ISNUMBER('01_Data'!U4:U1826)),_xlfn._xlws.FILTER('01_Data'!U4:U1826,ISNUMBER('01_Data'!P4:P1826)*ISNUMBER('01_Data'!U4:U1826)))*252} -> 0.078139803 | H22: =_xlfn.COVARIANCE.S('01_Data'!P4:P1826,'01_Data'!V4:V1826)*252 -> 0.053600395 | I22: =_xlfn.COVARIANCE.S('01_Data'!P4:P1826,'01_Data'!W4:W1826)*252 -> 0.063283604 | J22: =_xlfn.COVARIANCE.S('01_Data'!P4:P1826,'01_Data'!X4:X1826)*252 -> 0.067854836 | K22: {=_xlfn.COVARIANCE.S(_xlfn._xlws.FILTER('01_Data'!P4:P1826,ISNUMBER('01_Data'!P4:P1826)*ISNUMBER('01_Data'!Y4:Y1826)),_xlfn._xlws.FILTER('01_Data'!Y4:Y1826,ISNUMBER('01_Data'!P4:P1826)*ISNUMBER('01_Data'!Y4:Y1826)))*252} -> -3.3222745e-06 | L22: {=_xlfn.COVARIANCE.S(_xlfn._xlws.FILTER('01_Data'!P4:P1826,ISNUMBER('01_Data'!P4:P1826)*ISNUMBER('01_Data'!AA4:AA1826)),_xlfn._xlws.FILTER('01_Data'!AA4:AA1826,ISNUMBER('01_Data'!P4:P1826)*ISNUMBER('01_Data'!AA4:AA1826)))*252} -> 0.07306601 | M22: {=_xlfn.COVARIANCE.S(_xlfn._xlws.FILTER('01_Data'!P4:P1826,ISNUMBER('01_Data'!P4:P1826)*ISNUMBER('01_Data'!AB4:AB1826)),_xlfn._xlws.FILTER('01_Data'!AB4:AB1826,ISNUMBER('01_Data'!P4:P1826)*ISNUMBER('01_Data'!AB4:AB1826)))*252} -> 0.075652106
A23: CVX | B23: =_xlfn.COVARIANCE.S('01_Data'!Q4:Q1826,'01_Data'!P4:P1826)*252 -> 0.085052144 | C23: =_xlfn.COVARIANCE.S('01_Data'!Q4:Q1826,'01_Data'!Q4:Q1826)*252 -> 0.10394395 | D23: =_xlfn.COVARIANCE.S('01_Data'!Q4:Q1826,'01_Data'!R4:R1826)*252 -> 0.11009658 | E23: =_xlfn.COVARIANCE.S('01_Data'!Q4:Q1826,'01_Data'!S4:S1826)*252 -> 0.12955832 | F23: =_xlfn.COVARIANCE.S('01_Data'!Q4:Q1826,'01_Data'!T4:T1826)*252 -> 0.062085691 | G23: {=_xlfn.COVARIANCE.S(_xlfn._xlws.FILTER('01_Data'!Q4:Q1826,ISNUMBER('01_Data'!Q4:Q1826)*ISNUMBER('01_Data'!U4:U1826)),_xlfn._xlws.FILTER('01_Data'!U4:U1826,ISNUMBER('01_Data'!Q4:Q1826)*ISNUMBER('01_Data'!U4:U1826)))*252} -> 0.073863724 | H23: =_xlfn.COVARIANCE.S('01_Data'!Q4:Q1826,'01_Data'!V4:V1826)*252 -> 0.053257939 | I23: =_xlfn.COVARIANCE.S('01_Data'!Q4:Q1826,'01_Data'!W4:W1826)*252 -> 0.061310732 | J23: =_xlfn.COVARIANCE.S('01_Data'!Q4:Q1826,'01_Data'!X4:X1826)*252 -> 0.068430296 | K23: {=_xlfn.COVARIANCE.S(_xlfn._xlws.FILTER('01_Data'!Q4:Q1826,ISNUMBER('01_Data'!Q4:Q1826)*ISNUMBER('01_Data'!Y4:Y1826)),_xlfn._xlws.FILTER('01_Data'!Y4:Y1826,ISNUMBER('01_Data'!Q4:Q1826)*ISNUMBER('01_Data'!Y4:Y1826)))*252} -> 1.2042667e-05 | L23: {=_xlfn.COVARIANCE.S(_xlfn._xlws.FILTER('01_Data'!Q4:Q1826,ISNUMBER('01_Data'!Q4:Q1826)*ISNUMBER('01_Data'!AA4:AA1826)),_xlfn._xlws.FILTER('01_Data'!AA4:AA1826,ISNUMBER('01_Data'!Q4:Q1826)*ISNUMBER('01_Data'!AA4:AA1826)))*252} -> 0.066104498 | M23: {=_xlfn.COVARIANCE.S(_xlfn._xlws.FILTER('01_Data'!Q4:Q1826,ISNUMBER('01_Data'!Q4:Q1826)*ISNUMBER('01_Data'!AB4:AB1826)),_xlfn._xlws.FILTER('01_Data'!AB4:AB1826,ISNUMBER('01_Data'!Q4:Q1826)*ISNUMBER('01_Data'!AB4:AB1826)))*252} -> 0.078376887
A24: COP | B24: =_xlfn.COVARIANCE.S('01_Data'!R4:R1826,'01_Data'!P4:P1826)*252 -> 0.10563361 | C24: =_xlfn.COVARIANCE.S('01_Data'!R4:R1826,'01_Data'!Q4:Q1826)*252 -> 0.11009658 | D24: =_xlfn.COVARIANCE.S('01_Data'!R4:R1826,'01_Data'!R4:R1826)*252 -> 0.16553029 | E24: =_xlfn.COVARIANCE.S('01_Data'!R4:R1826,'01_Data'!S4:S1826)*252 -> 0.18185427 | F24: =_xlfn.COVARIANCE.S('01_Data'!R4:R1826,'01_Data'!T4:T1826)*252 -> 0.083232115 | G24: {=_xlfn.COVARIANCE.S(_xlfn._xlws.FILTER('01_Data'!R4:R1826,ISNUMBER('01_Data'!R4:R1826)*ISNUMBER('01_Data'!U4:U1826)),_xlfn._xlws.FILTER('01_Data'!U4:U1826,ISNUMBER('01_Data'!R4:R1826)*ISNUMBER('01_Data'!U4:U1826)))*252} -> 0.12704009 | H24: =_xlfn.COVARIANCE.S('01_Data'!R4:R1826,'01_Data'!V4:V1826)*252 -> 0.063906679 | I24: =_xlfn.COVARIANCE.S('01_Data'!R4:R1826,'01_Data'!W4:W1826)*252 -> 0.077676306 | J24: =_xlfn.COVARIANCE.S('01_Data'!R4:R1826,'01_Data'!X4:X1826)*252 -> 0.092580318 | K24: {=_xlfn.COVARIANCE.S(_xlfn._xlws.FILTER('01_Data'!R4:R1826,ISNUMBER('01_Data'!R4:R1826)*ISNUMBER('01_Data'!Y4:Y1826)),_xlfn._xlws.FILTER('01_Data'!Y4:Y1826,ISNUMBER('01_Data'!R4:R1826)*ISNUMBER('01_Data'!Y4:Y1826)))*252} -> -3.3138509e-05 | L24: {=_xlfn.COVARIANCE.S(_xlfn._xlws.FILTER('01_Data'!R4:R1826,ISNUMBER('01_Data'!R4:R1826)*ISNUMBER('01_Data'!AA4:AA1826)),_xlfn._xlws.FILTER('01_Data'!AA4:AA1826,ISNUMBER('01_Data'!R4:R1826)*ISNUMBER('01_Data'!AA4:AA1826)))*252} -> 0.10133597 | M24: {=_xlfn.COVARIANCE.S(_xlfn._xlws.FILTER('01_Data'!R4:R1826,ISNUMBER('01_Data'!R4:R1826)*ISNUMBER('01_Data'!AB4:AB1826)),_xlfn._xlws.FILTER('01_Data'!AB4:AB1826,ISNUMBER('01_Data'!R4:R1826)*ISNUMBER('01_Data'!AB4:AB1826)))*252} -> 0.11098106
A25: OXY | B25: =_xlfn.COVARIANCE.S('01_Data'!S4:S1826,'01_Data'!P4:P1826)*252 -> 0.13063221 | C25: =_xlfn.COVARIANCE.S('01_Data'!S4:S1826,'01_Data'!Q4:Q1826)*252 -> 0.12955832 | D25: =_xlfn.COVARIANCE.S('01_Data'!S4:S1826,'01_Data'!R4:R1826)*252 -> 0.18185427 | E25: =_xlfn.COVARIANCE.S('01_Data'!S4:S1826,'01_Data'!S4:S1826)*252 -> 0.33633704 | F25: =_xlfn.COVARIANCE.S('01_Data'!S4:S1826,'01_Data'!T4:T1826)*252 -> 0.10200299 | G25: {=_xlfn.COVARIANCE.S(_xlfn._xlws.FILTER('01_Data'!S4:S1826,ISNUMBER('01_Data'!S4:S1826)*ISNUMBER('01_Data'!U4:U1826)),_xlfn._xlws.FILTER('01_Data'!U4:U1826,ISNUMBER('01_Data'!S4:S1826)*ISNUMBER('01_Data'!U4:U1826)))*252} -> 0.13788277 | H25: =_xlfn.COVARIANCE.S('01_Data'!S4:S1826,'01_Data'!V4:V1826)*252 -> 0.073375938 | I25: =_xlfn.COVARIANCE.S('01_Data'!S4:S1826,'01_Data'!W4:W1826)*252 -> 0.10850383 | J25: =_xlfn.COVARIANCE.S('01_Data'!S4:S1826,'01_Data'!X4:X1826)*252 -> 0.13247575 | K25: {=_xlfn.COVARIANCE.S(_xlfn._xlws.FILTER('01_Data'!S4:S1826,ISNUMBER('01_Data'!S4:S1826)*ISNUMBER('01_Data'!Y4:Y1826)),_xlfn._xlws.FILTER('01_Data'!Y4:Y1826,ISNUMBER('01_Data'!S4:S1826)*ISNUMBER('01_Data'!Y4:Y1826)))*252} -> -4.3168651e-05 | L25: {=_xlfn.COVARIANCE.S(_xlfn._xlws.FILTER('01_Data'!S4:S1826,ISNUMBER('01_Data'!S4:S1826)*ISNUMBER('01_Data'!AA4:AA1826)),_xlfn._xlws.FILTER('01_Data'!AA4:AA1826,ISNUMBER('01_Data'!S4:S1826)*ISNUMBER('01_Data'!AA4:AA1826)))*252} -> 0.14012554 | M25: {=_xlfn.COVARIANCE.S(_xlfn._xlws.FILTER('01_Data'!S4:S1826,ISNUMBER('01_Data'!S4:S1826)*ISNUMBER('01_Data'!AB4:AB1826)),_xlfn._xlws.FILTER('01_Data'!AB4:AB1826,ISNUMBER('01_Data'!S4:S1826)*ISNUMBER('01_Data'!AB4:AB1826)))*252} -> 0.14297888
A26: LNG | B26: =_xlfn.COVARIANCE.S('01_Data'!T4:T1826,'01_Data'!P4:P1826)*252 -> 0.060375104 | C26: =_xlfn.COVARIANCE.S('01_Data'!T4:T1826,'01_Data'!Q4:Q1826)*252 -> 0.062085691 | D26: =_xlfn.COVARIANCE.S('01_Data'!T4:T1826,'01_Data'!R4:R1826)*252 -> 0.083232115 | E26: =_xlfn.COVARIANCE.S('01_Data'!T4:T1826,'01_Data'!S4:S1826)*252 -> 0.10200299 | F26: =_xlfn.COVARIANCE.S('01_Data'!T4:T1826,'01_Data'!T4:T1826)*252 -> 0.1131661 | G26: {=_xlfn.COVARIANCE.S(_xlfn._xlws.FILTER('01_Data'!T4:T1826,ISNUMBER('01_Data'!T4:T1826)*ISNUMBER('01_Data'!U4:U1826)),_xlfn._xlws.FILTER('01_Data'!U4:U1826,ISNUMBER('01_Data'!T4:T1826)*ISNUMBER('01_Data'!U4:U1826)))*252} -> 0.12439478 | H26: =_xlfn.COVARIANCE.S('01_Data'!T4:T1826,'01_Data'!V4:V1826)*252 -> 0.047147602 | I26: =_xlfn.COVARIANCE.S('01_Data'!T4:T1826,'01_Data'!W4:W1826)*252 -> 0.049577932 | J26: =_xlfn.COVARIANCE.S('01_Data'!T4:T1826,'01_Data'!X4:X1826)*252 -> 0.064869825 | K26: {=_xlfn.COVARIANCE.S(_xlfn._xlws.FILTER('01_Data'!T4:T1826,ISNUMBER('01_Data'!T4:T1826)*ISNUMBER('01_Data'!Y4:Y1826)),_xlfn._xlws.FILTER('01_Data'!Y4:Y1826,ISNUMBER('01_Data'!T4:T1826)*ISNUMBER('01_Data'!Y4:Y1826)))*252} -> -1.0398732e-05 | L26: {=_xlfn.COVARIANCE.S(_xlfn._xlws.FILTER('01_Data'!T4:T1826,ISNUMBER('01_Data'!T4:T1826)*ISNUMBER('01_Data'!AA4:AA1826)),_xlfn._xlws.FILTER('01_Data'!AA4:AA1826,ISNUMBER('01_Data'!T4:T1826)*ISNUMBER('01_Data'!AA4:AA1826)))*252} -> 0.045829575 | M26: {=_xlfn.COVARIANCE.S(_xlfn._xlws.FILTER('01_Data'!T4:T1826,ISNUMBER('01_Data'!T4:T1826)*ISNUMBER('01_Data'!AB4:AB1826)),_xlfn._xlws.FILTER('01_Data'!AB4:AB1826,ISNUMBER('01_Data'!T4:T1826)*ISNUMBER('01_Data'!AB4:AB1826)))*252} -> 0.052189263
A27: VG | B27: {=_xlfn.COVARIANCE.S(_xlfn._xlws.FILTER('01_Data'!U4:U1826,ISNUMBER('01_Data'!U4:U1826)*ISNUMBER('01_Data'!P4:P1826)),_xlfn._xlws.FILTER('01_Data'!P4:P1826,ISNUMBER('01_Data'!U4:U1826)*ISNUMBER('01_Data'!P4:P1826)))*252} -> 0.078139803 | C27: {=_xlfn.COVARIANCE.S(_xlfn._xlws.FILTER('01_Data'!U4:U1826,ISNUMBER('01_Data'!U4:U1826)*ISNUMBER('01_Data'!Q4:Q1826)),_xlfn._xlws.FILTER('01_Data'!Q4:Q1826,ISNUMBER('01_Data'!U4:U1826)*ISNUMBER('01_Data'!Q4:Q1826)))*252} -> 0.073863724 | D27: {=_xlfn.COVARIANCE.S(_xlfn._xlws.FILTER('01_Data'!U4:U1826,ISNUMBER('01_Data'!U4:U1826)*ISNUMBER('01_Data'!R4:R1826)),_xlfn._xlws.FILTER('01_Data'!R4:R1826,ISNUMBER('01_Data'!U4:U1826)*ISNUMBER('01_Data'!R4:R1826)))*252} -> 0.12704009 | E27: {=_xlfn.COVARIANCE.S(_xlfn._xlws.FILTER('01_Data'!U4:U1826,ISNUMBER('01_Data'!U4:U1826)*ISNUMBER('01_Data'!S4:S1826)),_xlfn._xlws.FILTER('01_Data'!S4:S1826,ISNUMBER('01_Data'!U4:U1826)*ISNUMBER('01_Data'!S4:S1826)))*252} -> 0.13788277 | F27: {=_xlfn.COVARIANCE.S(_xlfn._xlws.FILTER('01_Data'!U4:U1826,ISNUMBER('01_Data'!U4:U1826)*ISNUMBER('01_Data'!T4:T1826)),_xlfn._xlws.FILTER('01_Data'!T4:T1826,ISNUMBER('01_Data'!U4:U1826)*ISNUMBER('01_Data'!T4:T1826)))*252} -> 0.12439478 | G27: {=_xlfn.COVARIANCE.S(_xlfn._xlws.FILTER('01_Data'!U4:U1826,ISNUMBER('01_Data'!U4:U1826)*ISNUMBER('01_Data'!U4:U1826)),_xlfn._xlws.FILTER('01_Data'!U4:U1826,ISNUMBER('01_Data'!U4:U1826)*ISNUMBER('01_Data'!U4:U1826)))*252} -> 0.85463595 | H27: {=_xlfn.COVARIANCE.S(_xlfn._xlws.FILTER('01_Data'!U4:U1826,ISNUMBER('01_Data'!U4:U1826)*ISNUMBER('01_Data'!V4:V1826)),_xlfn._xlws.FILTER('01_Data'!V4:V1826,ISNUMBER('01_Data'!U4:U1826)*ISNUMBER('01_Data'!V4:V1826)))*252} -> 0.060194504 | I27: {=_xlfn.COVARIANCE.S(_xlfn._xlws.FILTER('01_Data'!U4:U1826,ISNUMBER('01_Data'!U4:U1826)*ISNUMBER('01_Data'!W4:W1826)),_xlfn._xlws.FILTER('01_Data'!W4:W1826,ISNUMBER('01_Data'!U4:U1826)*ISNUMBER('01_Data'!W4:W1826)))*252} -> 0.066325552 | J27: {=_xlfn.COVARIANCE.S(_xlfn._xlws.FILTER('01_Data'!U4:U1826,ISNUMBER('01_Data'!U4:U1826)*ISNUMBER('01_Data'!X4:X1826)),_xlfn._xlws.FILTER('01_Data'!X4:X1826,ISNUMBER('01_Data'!U4:U1826)*ISNUMBER('01_Data'!X4:X1826)))*252} -> 0.11151261 | K27: {=_xlfn.COVARIANCE.S(_xlfn._xlws.FILTER('01_Data'!U4:U1826,ISNUMBER('01_Data'!U4:U1826)*ISNUMBER('01_Data'!Y4:Y1826)),_xlfn._xlws.FILTER('01_Data'!Y4:Y1826,ISNUMBER('01_Data'!U4:U1826)*ISNUMBER('01_Data'!Y4:Y1826)))*252} -> 3.5016158e-05 | L27: {=_xlfn.COVARIANCE.S(_xlfn._xlws.FILTER('01_Data'!U4:U1826,ISNUMBER('01_Data'!U4:U1826)*ISNUMBER('01_Data'!AA4:AA1826)),_xlfn._xlws.FILTER('01_Data'!AA4:AA1826,ISNUMBER('01_Data'!U4:U1826)*ISNUMBER('01_Data'!AA4:AA1826)))*252} -> 0.1360045 | M27: {=_xlfn.COVARIANCE.S(_xlfn._xlws.FILTER('01_Data'!U4:U1826,ISNUMBER('01_Data'!U4:U1826)*ISNUMBER('01_Data'!AB4:AB1826)),_xlfn._xlws.FILTER('01_Data'!AB4:AB1826,ISNUMBER('01_Data'!U4:U1826)*ISNUMBER('01_Data'!AB4:AB1826)))*252} -> 0.14008069
A28: FRO | B28: =_xlfn.COVARIANCE.S('01_Data'!V4:V1826,'01_Data'!P4:P1826)*252 -> 0.053600395 | C28: =_xlfn.COVARIANCE.S('01_Data'!V4:V1826,'01_Data'!Q4:Q1826)*252 -> 0.053257939 | D28: =_xlfn.COVARIANCE.S('01_Data'!V4:V1826,'01_Data'!R4:R1826)*252 -> 0.063906679 | E28: =_xlfn.COVARIANCE.S('01_Data'!V4:V1826,'01_Data'!S4:S1826)*252 -> 0.073375938 | F28: =_xlfn.COVARIANCE.S('01_Data'!V4:V1826,'01_Data'!T4:T1826)*252 -> 0.047147602 | G28: {=_xlfn.COVARIANCE.S(_xlfn._xlws.FILTER('01_Data'!V4:V1826,ISNUMBER('01_Data'!V4:V1826)*ISNUMBER('01_Data'!U4:U1826)),_xlfn._xlws.FILTER('01_Data'!U4:U1826,ISNUMBER('01_Data'!V4:V1826)*ISNUMBER('01_Data'!U4:U1826)))*252} -> 0.060194504 | H28: =_xlfn.COVARIANCE.S('01_Data'!V4:V1826,'01_Data'!V4:V1826)*252 -> 0.29058052 | I28: =_xlfn.COVARIANCE.S('01_Data'!V4:V1826,'01_Data'!W4:W1826)*252 -> 0.2075046 | J28: =_xlfn.COVARIANCE.S('01_Data'!V4:V1826,'01_Data'!X4:X1826)*252 -> 0.046764782 | K28: {=_xlfn.COVARIANCE.S(_xlfn._xlws.FILTER('01_Data'!V4:V1826,ISNUMBER('01_Data'!V4:V1826)*ISNUMBER('01_Data'!Y4:Y1826)),_xlfn._xlws.FILTER('01_Data'!Y4:Y1826,ISNUMBER('01_Data'!V4:V1826)*ISNUMBER('01_Data'!Y4:Y1826)))*252} -> -2.7347653e-05 | L28: {=_xlfn.COVARIANCE.S(_xlfn._xlws.FILTER('01_Data'!V4:V1826,ISNUMBER('01_Data'!V4:V1826)*ISNUMBER('01_Data'!AA4:AA1826)),_xlfn._xlws.FILTER('01_Data'!AA4:AA1826,ISNUMBER('01_Data'!V4:V1826)*ISNUMBER('01_Data'!AA4:AA1826)))*252} -> 0.032972793 | M28: {=_xlfn.COVARIANCE.S(_xlfn._xlws.FILTER('01_Data'!V4:V1826,ISNUMBER('01_Data'!V4:V1826)*ISNUMBER('01_Data'!AB4:AB1826)),_xlfn._xlws.FILTER('01_Data'!AB4:AB1826,ISNUMBER('01_Data'!V4:V1826)*ISNUMBER('01_Data'!AB4:AB1826)))*252} -> 0.027274088
